Workbook

Sheet 配当金単価推移
A1: コード | B1: 銘柄名 | C1: 配当金分配年月
C2: 配当金単価（税引き後）
C3: 【特定】保有数 / 受取金額（税引き後）
C4: 【NISA】保有数 / 受取金額（税引き後）
A5: HDV | B5: iシェアーズ コア 米国高配当株 ETF | C5: 45352 | E5: 45444 | G5: 45566 | I5: 45627 | K5: 45717 | M5: 45809 | O5: 45901 | Q5: 45992
C6: =IFERROR(__xludf.DUMMYFUNCTION("FILTER('配当金履歴一覧'!$D:$D,('配当金履歴一覧'!$C:$C=C5)*('配当金履歴一覧'!$B:$B=$B5))"),"0.75USD") -> 0.75USD | E6: =IFERROR(__xludf.DUMMYFUNCTION("FILTER('配当金履歴一覧'!$D:$D,('配当金履歴一覧'!$C:$C=E5)*('配当金履歴一覧'!$B:$B=$B5))"),"0.83USD") -> 0.83USD | G6: =IFERROR(__xludf.DUMMYFUNCTION("FILTER('配当金履歴一覧'!$D:$D,('配当金履歴一覧'!$C:$C=G5)*('配当金履歴一覧'!$B:$B=$B5))"),"1.1USD") -> 1.1USD | I6: =IFERROR(__xludf.DUMMYFUNCTION("FILTER('配当金履歴一覧'!$D:$D,('配当金履歴一覧'!$C:$C=I5)*('配当金履歴一覧'!$B:$B=$B5))"),"1.01USD") -> 1.01USD | K6: =IFERROR(__xludf.DUMMYFUNCTION("FILTER('配当金履歴一覧'!$D:$D,('配当金履歴一覧'!$C:$C=K5)*('配当金履歴一覧'!$B:$B=$B5))"),"0.71USD") -> 0.71USD | M6: =IFERROR(__xludf.DUMMYFUNCTION("FILTER('配当金履歴一覧'!$D:$D,('配当金履歴一覧'!$C:$C=M5)*('配当金履歴一覧'!$B:$B=$B5))"),"0.82USD") -> 0.82USD | O6: =IFERROR(__xludf.DUMMYFUNCTION("FILTER('配当金履歴一覧'!$D:$D,('配当金履歴一覧'!$C:$C=O5)*('配当金履歴一覧'!$B:$B=$B5))"),"0.85USD") -> 0.85USD | Q6: =IFERROR(__xludf.DUMMYFUNCTION("FILTER('配当金履歴一覧'!$D:$D,('配当金履歴一覧'!$C:$C=Q5)*('配当金履歴一覧'!$B:$B=$B5))"),"1.12USD") -> 1.12USD
C7: =IFERROR(__xludf.DUMMYFUNCTION("FILTER('配当金履歴一覧'!$E:$E,('配当金履歴一覧'!$C:$C=C5)*('配当金履歴一覧'!$B:$B=$B5))"),51.0) -> 51 | D7: =IFERROR(__xludf.DUMMYFUNCTION("FILTER('配当金履歴一覧'!$F:$F,('配当金履歴一覧'!$C:$C=C5)*('配当金履歴一覧'!$B:$B=$B5))"),4605.0) -> 4605 | E7: =IFERROR(__xludf.DUMMYFUNCTION("FILTER('配当金履歴一覧'!$E:$E,('配当金履歴一覧'!$C:$C=E5)*('配当金履歴一覧'!$B:$B=$B5))"),51.0) -> 51 | F7: =IFERROR(__xludf.DUMMYFUNCTION("FILTER('配当金履歴一覧'!$F:$F,('配当金履歴一覧'!$C:$C=E5)*('配当金履歴一覧'!$B:$B=$B5))"),5316.0) -> 5316 | G7: =IFERROR(__xludf.DUMMYFUNCTION("FILTER('配当金履歴一覧'!$E:$E,('配当金履歴一覧'!$C:$C=G5)*('配当金履歴一覧'!$B:$B=$B5))"),51.0) -> 51 | H7: =IFERROR(__xludf.DUMMYFUNCTION("FILTER('配当金履歴一覧'!$F:$F,('配当金履歴一覧'!$C:$C=G5)*('配当金履歴一覧'!$B:$B=$B5))"),6381.0) -> 6381 | I7: =IFERROR(__xludf.DUMMYFUNCTION("FILTER('配当金履歴一覧'!$E:$E,('配当金履歴一覧'!$C:$C=I5)*('配当金履歴一覧'!$B:$B=$B5))"),51.0) -> 51 | J7: =IFERROR(__xludf.DUMMYFUNCTION("FILTER('配当金履歴一覧'!$F:$F,('配当金履歴一覧'!$C:$C=I5)*('配当金履歴一覧'!$B:$B=$B5))"),6442.0) -> 6442 | K7: =IFERROR(__xludf.DUMMYFUNCTION("FILTER('配当金履歴一覧'!$E:$E,('配当金履歴一覧'!$C:$C=K5)*('配当金履歴一覧'!$B:$B=$B5))"),51.0) -> 51 | L7: =IFERROR(__xludf.DUMMYFUNCTION("FILTER('配当金履歴一覧'!$F:$F,('配当金履歴一覧'!$C:$C=K5)*('配当金履歴一覧'!$B:$B=$B5))"),4311.0) -> 4311 | M7: =IFERROR(__xludf.DUMMYFUNCTION("FILTER('配当金履歴一覧'!$E:$E,('配当金履歴一覧'!$C:$C=M5)*('配当金履歴一覧'!$B:$B=$B5))"),51.0) -> 51 | N7: =IFERROR(__xludf.DUMMYFUNCTION("FILTER('配当金履歴一覧'!$F:$F,('配当金履歴一覧'!$C:$C=M5)*('配当金履歴一覧'!$B:$B=$B5))"),4821.0) -> 4821 | O7: =IFERROR(__xludf.DUMMYFUNCTION("FILTER('配当金履歴一覧'!$E:$E,('配当金履歴一覧'!$C:$C=O5)*('配当金履歴一覧'!$B:$B=$B5))"),51.0) -> 51 | P7: =IFERROR(__xludf.DUMMYFUNCTION("FILTER('配当金履歴一覧'!$F:$F,('配当金履歴一覧'!$C:$C=O5)*('配当金履歴一覧'!$B:$B=$B5))"),5111.0) -> 5111 | Q7: =IFERROR(__xludf.DUMMYFUNCTION("FILTER('配当金履歴一覧'!$E:$E,('配当金履歴一覧'!$C:$C=Q5)*('配当金履歴一覧'!$B:$B=$B5))"),51.0) -> 51 | R7: =IFERROR(__xludf.DUMMYFUNCTION("FILTER('配当金履歴一覧'!$F:$F,('配当金履歴一覧'!$C:$C=Q5)*('配当金履歴一覧'!$B:$B=$B5))"),7097.0) -> 7097
C8: =IFERROR(__xludf.DUMMYFUNCTION("FILTER('配当金履歴一覧'!$G:$G,('配当金履歴一覧'!$C:$C=C5)*('配当金履歴一覧'!$B:$B=$B5))"),3.0) -> 3 | D8: =IFERROR(__xludf.DUMMYFUNCTION("FILTER('配当金履歴一覧'!$H:$H,('配当金履歴一覧'!$C:$C=C5)*('配当金履歴一覧'!$B:$B=$B5))"),113.3) -> 113.3 | E8: =IFERROR(__xludf.DUMMYFUNCTION("FILTER('配当金履歴一覧'!$G:$G,('配当金履歴一覧'!$C:$C=E5)*('配当金履歴一覧'!$B:$B=$B5))"),6.0) -> 6 | F8: =IFERROR(__xludf.DUMMYFUNCTION("FILTER('配当金履歴一覧'!$H:$H,('配当金履歴一覧'!$C:$C=E5)*('配当金履歴一覧'!$B:$B=$B5))"),785.0) -> 785 | G8: =IFERROR(__xludf.DUMMYFUNCTION("FILTER('配当金履歴一覧'!$G:$G,('配当金履歴一覧'!$C:$C=G5)*('配当金履歴一覧'!$B:$B=$B5))"),6.0) -> 6 | H8: =IFERROR(__xludf.DUMMYFUNCTION("FILTER('配当金履歴一覧'!$H:$H,('配当金履歴一覧'!$C:$C=G5)*('配当金履歴一覧'!$B:$B=$B5))"),942.0) -> 942 | I8: =IFERROR(__xludf.DUMMYFUNCTION("FILTER('配当金履歴一覧'!$G:$G,('配当金履歴一覧'!$C:$C=I5)*('配当金履歴一覧'!$B:$B=$B5))"),8.0) -> 8 | J8: =IFERROR(__xludf.DUMMYFUNCTION("FILTER('配当金履歴一覧'!$H:$H,('配当金履歴一覧'!$C:$C=I5)*('配当金履歴一覧'!$B:$B=$B5))"),1268.0) -> 1268 | K8: =IFERROR(__xludf.DUMMYFUNCTION("FILTER('配当金履歴一覧'!$G:$G,('配当金履歴一覧'!$C:$C=K5)*('配当金履歴一覧'!$B:$B=$B5))"),13.0) -> 13 | L8: =IFERROR(__xludf.DUMMYFUNCTION("FILTER('配当金履歴一覧'!$H:$H,('配当金履歴一覧'!$C:$C=K5)*('配当金履歴一覧'!$B:$B=$B5))"),1379.0) -> 1379 | M8: =IFERROR(__xludf.DUMMYFUNCTION("FILTER('配当金履歴一覧'!$G:$G,('配当金履歴一覧'!$C:$C=M5)*('配当金履歴一覧'!$B:$B=$B5))"),16.0) -> 16 | N8: =IFERROR(__xludf.DUMMYFUNCTION("FILTER('配当金履歴一覧'!$H:$H,('配当金履歴一覧'!$C:$C=M5)*('配当金履歴一覧'!$B:$B=$B5))"),1898.0) -> 1898 | O8: =IFERROR(__xludf.DUMMYFUNCTION("FILTER('配当金履歴一覧'!$G:$G,('配当金履歴一覧'!$C:$C=O5)*('配当金履歴一覧'!$B:$B=$B5))"),17.0) -> 17 | P8: =IFERROR(__xludf.DUMMYFUNCTION("FILTER('配当金履歴一覧'!$H:$H,('配当金履歴一覧'!$C:$C=O5)*('配当金履歴一覧'!$B:$B=$B5))"),2138.0) -> 2138 | Q8: =IFERROR(__xludf.DUMMYFUNCTION("FILTER('配当金履歴一覧'!$G:$G,('配当金履歴一覧'!$C:$C=Q5)*('配当金履歴一覧'!$B:$B=$B5))"),18.0) -> 18 | R8: =IFERROR(__xludf.DUMMYFUNCTION("FILTER('配当金履歴一覧'!$H:$H,('配当金履歴一覧'!$C:$C=Q5)*('配当金履歴一覧'!$B:$B=$B5))"),3143.0) -> 3143
A9: VYM | B9: バンガード 米国高配当株式ETF | C9: 45352 | E9: 45444 | G9: 45536 | I9: 45627 | K9: 45717 | M9: 45809 | O9: 45901 | Q9: 45992
C10: =IFERROR(__xludf.DUMMYFUNCTION("FILTER('配当金履歴一覧'!$D:$D,('配当金履歴一覧'!$C:$C=C9)*('配当金履歴一覧'!$B:$B=$B9))"),"0.59USD") -> 0.59USD | E10: =IFERROR(__xludf.DUMMYFUNCTION("FILTER('配当金履歴一覧'!$D:$D,('配当金履歴一覧'!$C:$C=E9)*('配当金履歴一覧'!$B:$B=$B9))"),"0.92USD") -> 0.92USD | G10: =IFERROR(__xludf.DUMMYFUNCTION("FILTER('配当金履歴一覧'!$D:$D,('配当金履歴一覧'!$C:$C=G9)*('配当金履歴一覧'!$B:$B=$B9))"),"0.76USD") -> 0.76USD | I10: =IFERROR(__xludf.DUMMYFUNCTION("FILTER('配当金履歴一覧'!$D:$D,('配当金履歴一覧'!$C:$C=I9)*('配当金履歴一覧'!$B:$B=$B9))"),"0.86USD") -> 0.86USD | K10: =IFERROR(__xludf.DUMMYFUNCTION("FILTER('配当金履歴一覧'!$D:$D,('配当金履歴一覧'!$C:$C=K9)*('配当金履歴一覧'!$B:$B=$B9))"),"0.76USD") -> 0.76USD | M10: =IFERROR(__xludf.DUMMYFUNCTION("FILTER('配当金履歴一覧'!$D:$D,('配当金履歴一覧'!$C:$C=M9)*('配当金履歴一覧'!$B:$B=$B9))"),"0.77USD") -> 0.77USD | O10: =IFERROR(__xludf.DUMMYFUNCTION("FILTER('配当金履歴一覧'!$D:$D,('配当金履歴一覧'!$C:$C=O9)*('配当金履歴一覧'!$B:$B=$B9))"),"0.75USD") -> 0.75USD | Q10: =IFERROR(__xludf.DUMMYFUNCTION("FILTER('配当金履歴一覧'!$D:$D,('配当金履歴一覧'!$C:$C=Q9)*('配当金履歴一覧'!$B:$B=$B9))"),"0.85USD") -> 0.85USD
C11: =IFERROR(__xludf.DUMMYFUNCTION("FILTER('配当金履歴一覧'!$G:$G,('配当金履歴一覧'!$C:$C=C9)*('配当金履歴一覧'!$B:$B=$B9))"),2.0) -> 2 | D11: =IFERROR(__xludf.DUMMYFUNCTION("FILTER('配当金履歴一覧'!$H:$H,('配当金履歴一覧'!$C:$C=C9)*('配当金履歴一覧'!$B:$B=$B9))"),174.0) -> 174 | E11: =IFERROR(__xludf.DUMMYFUNCTION("FILTER('配当金履歴一覧'!$G:$G,('配当金履歴一覧'!$C:$C=E9)*('配当金履歴一覧'!$B:$B=$B9))"),8.0) -> 8 | F11: =IFERROR(__xludf.DUMMYFUNCTION("FILTER('配当金履歴一覧'!$H:$H,('配当金履歴一覧'!$C:$C=E9)*('配当金履歴一覧'!$B:$B=$B9))"),1170.0) -> 1170 | G11: =IFERROR(__xludf.DUMMYFUNCTION("FILTER('配当金履歴一覧'!$G:$G,('配当金履歴一覧'!$C:$C=G9)*('配当金履歴一覧'!$B:$B=$B9))"),8.0) -> 8 | H11: =IFERROR(__xludf.DUMMYFUNCTION("FILTER('配当金履歴一覧'!$H:$H,('配当金履歴一覧'!$C:$C=G9)*('配当金履歴一覧'!$B:$B=$B9))"),874.0) -> 874 | I11: =IFERROR(__xludf.DUMMYFUNCTION("FILTER('配当金履歴一覧'!$G:$G,('配当金履歴一覧'!$C:$C=I9)*('配当金履歴一覧'!$B:$B=$B9))"),9.0) -> 9 | J11: =IFERROR(__xludf.DUMMYFUNCTION("FILTER('配当金履歴一覧'!$H:$H,('配当金履歴一覧'!$C:$C=I9)*('配当金履歴一覧'!$B:$B=$B9))"),1223.0) -> 1223 | K11: =IFERROR(__xludf.DUMMYFUNCTION("FILTER('配当金履歴一覧'!$G:$G,('配当金履歴一覧'!$C:$C=K9)*('配当金履歴一覧'!$B:$B=$B9))"),12.0) -> 12 | L11: =IFERROR(__xludf.DUMMYFUNCTION("FILTER('配当金履歴一覧'!$H:$H,('配当金履歴一覧'!$C:$C=K9)*('配当金履歴一覧'!$B:$B=$B9))"),1378.0) -> 1378 | M11: =IFERROR(__xludf.DUMMYFUNCTION("FILTER('配当金履歴一覧'!$G:$G,('配当金履歴一覧'!$C:$C=M9)*('配当金履歴一覧'!$B:$B=$B9))"),17.0) -> 17 | N11: =IFERROR(__xludf.DUMMYFUNCTION("FILTER('配当金履歴一覧'!$H:$H,('配当金履歴一覧'!$C:$C=M9)*('配当金履歴一覧'!$B:$B=$B9))"),1908.0) -> 1908 | O11: =IFERROR(__xludf.DUMMYFUNCTION("FILTER('配当金履歴一覧'!$G:$G,('配当金履歴一覧'!$C:$C=O9)*('配当金履歴一覧'!$B:$B=$B9))"),18.0) -> 18 | P11: =IFERROR(__xludf.DUMMYFUNCTION("FILTER('配当金履歴一覧'!$H:$H,('配当金履歴一覧'!$C:$C=O9)*('配当金履歴一覧'!$B:$B=$B9))"),2010.0) -> 2010 | Q11: =IFERROR(__xludf.DUMMYFUNCTION("FILTER('配当金履歴一覧'!$G:$G,('配当金履歴一覧'!$C:$C=Q9)*('配当金履歴一覧'!$B:$B=$B9))"),19.0) -> 19 | R11: =IFERROR(__xludf.DUMMYFUNCTION("FILTER('配当金履歴一覧'!$H:$H,('配当金履歴一覧'!$C:$C=Q9)*('配当金履歴一覧'!$B:$B=$B9))"),2524.0) -> 2524
A12: SPYD | B12: SPDRポートフォリオS&P 500高配当株式ETF | C12: 45352 | E12: 45444 | G12: 45536 | I12: 45627 | K12: 45717 | M12: 45809 | O12: 45901 | Q12: 45992
C13: =IFERROR(__xludf.DUMMYFUNCTION("FILTER('配当金履歴一覧'!$D:$D,('配当金履歴一覧'!$C:$C=C12)*('配当金履歴一覧'!$B:$B=$B12))"),"0.33USD") -> 0.33USD | E13: =IFERROR(__xludf.DUMMYFUNCTION("FILTER('配当金履歴一覧'!$D:$D,('配当金履歴一覧'!$C:$C=E12)*('配当金履歴一覧'!$B:$B=$B12))"),"0.43USD") -> 0.43USD | G13: =IFERROR(__xludf.DUMMYFUNCTION("FILTER('配当金履歴一覧'!$D:$D,('配当金履歴一覧'!$C:$C=G12)*('配当金履歴一覧'!$B:$B=$B12))"),"0.41USD") -> 0.41USD | I13: =IFERROR(__xludf.DUMMYFUNCTION("FILTER('配当金履歴一覧'!$D:$D,('配当金履歴一覧'!$C:$C=I12)*('配当金履歴一覧'!$B:$B=$B12))"),"0.49USD") -> 0.49USD | K13: =IFERROR(__xludf.DUMMYFUNCTION("FILTER('配当金履歴一覧'!$D:$D,('配当金履歴一覧'!$C:$C=K12)*('配当金履歴一覧'!$B:$B=$B12))"),"0.37USD") -> 0.37USD | M13: =IFERROR(__xludf.DUMMYFUNCTION("FILTER('配当金履歴一覧'!$D:$D,('配当金履歴一覧'!$C:$C=M12)*('配当金履歴一覧'!$B:$B=$B12))"),"0.45USD") -> 0.45USD | O13: =IFERROR(__xludf.DUMMYFUNCTION("FILTER('配当金履歴一覧'!$D:$D,('配当金履歴一覧'!$C:$C=O12)*('配当金履歴一覧'!$B:$B=$B12))"),"0.44USD") -> 0.44USD | Q13: =IFERROR(__xludf.DUMMYFUNCTION("FILTER('配当金履歴一覧'!$D:$D,('配当金履歴一覧'!$C:$C=Q12)*('配当金履歴一覧'!$B:$B=$B12))"),"0.49USD") -> 0.49USD
C14: =IFERROR(__xludf.DUMMYFUNCTION("FILTER('配当金履歴一覧'!$E:$E,('配当金履歴一覧'!$C:$C=C12)*('配当金履歴一覧'!$B:$B=$B12))"),191.0) -> 191 | D14: =IFERROR(__xludf.DUMMYFUNCTION("FILTER('配当金履歴一覧'!$F:$F,('配当金履歴一覧'!$C:$C=C12)*('配当金履歴一覧'!$B:$B=$B12))"),7580.0) -> 7580 | E14: =IFERROR(__xludf.DUMMYFUNCTION("FILTER('配当金履歴一覧'!$E:$E,('配当金履歴一覧'!$C:$C=E12)*('配当金履歴一覧'!$B:$B=$B12))"),191.0) -> 191 | F14: =IFERROR(__xludf.DUMMYFUNCTION("FILTER('配当金履歴一覧'!$F:$F,('配当金履歴一覧'!$C:$C=E12)*('配当金履歴一覧'!$B:$B=$B12))"),10578.0) -> 10578 | G14: =IFERROR(__xludf.DUMMYFUNCTION("FILTER('配当金履歴一覧'!$E:$E,('配当金履歴一覧'!$C:$C=G12)*('配当金履歴一覧'!$B:$B=$B12))"),191.0) -> 191 | H14: =IFERROR(__xludf.DUMMYFUNCTION("FILTER('配当金履歴一覧'!$F:$F,('配当金履歴一覧'!$C:$C=G12)*('配当金履歴一覧'!$B:$B=$B12))"),8928.0) -> 8928 | I14: =IFERROR(__xludf.DUMMYFUNCTION("FILTER('配当金履歴一覧'!$E:$E,('配当金履歴一覧'!$C:$C=I12)*('配当金履歴一覧'!$B:$B=$B12))"),191.0) -> 191 | J14: =IFERROR(__xludf.DUMMYFUNCTION("FILTER('配当金履歴一覧'!$F:$F,('配当金履歴一覧'!$C:$C=I12)*('配当金履歴一覧'!$B:$B=$B12))"),11720.0) -> 11720 | K14: =IFERROR(__xludf.DUMMYFUNCTION("FILTER('配当金履歴一覧'!$E:$E,('配当金履歴一覧'!$C:$C=K12)*('配当金履歴一覧'!$B:$B=$B12))"),191.0) -> 191 | L14: =IFERROR(__xludf.DUMMYFUNCTION("FILTER('配当金履歴一覧'!$F:$F,('配当金履歴一覧'!$C:$C=K12)*('配当金履歴一覧'!$B:$B=$B12))"),8562.0) -> 8562 | M14: =IFERROR(__xludf.DUMMYFUNCTION("FILTER('配当金履歴一覧'!$E:$E,('配当金履歴一覧'!$C:$C=M12)*('配当金履歴一覧'!$B:$B=$B12))"),191.0) -> 191 | N14: =IFERROR(__xludf.DUMMYFUNCTION("FILTER('配当金履歴一覧'!$F:$F,('配当金履歴一覧'!$C:$C=M12)*('配当金履歴一覧'!$B:$B=$B12))"),9858.0) -> 9858 | O14: =IFERROR(__xludf.DUMMYFUNCTION("FILTER('配当金履歴一覧'!$E:$E,('配当金履歴一覧'!$C:$C=O12)*('配当金履歴一覧'!$B:$B=$B12))"),191.0) -> 191 | P14: =IFERROR(__xludf.DUMMYFUNCTION("FILTER('配当金履歴一覧'!$F:$F,('配当金履歴一覧'!$C:$C=O12)*('配当金履歴一覧'!$B:$B=$B12))"),9842.0) -> 9842 | Q14: =IFERROR(__xludf.DUMMYFUNCTION("FILTER('配当金履歴一覧'!$E:$E,('配当金履歴一覧'!$C:$C=Q12)*('配当金履歴一覧'!$B:$B=$B12))"),191.0) -> 191 | R14: =IFERROR(__xludf.DUMMYFUNCTION("FILTER('配当金履歴一覧'!$F:$F,('配当金履歴一覧'!$C:$C=Q12)*('配当金履歴一覧'!$B:$B=$B12))"),11689.0) -> 11689
C15: =IFERROR(__xludf.DUMMYFUNCTION("FILTER('配当金履歴一覧'!$G:$G,('配当金履歴一覧'!$C:$C=C12)*('配当金履歴一覧'!$B:$B=$B12))"),5.0) -> 5 | D15: =IFERROR(__xludf.DUMMYFUNCTION("FILTER('配当金履歴一覧'!$H:$H,('配当金履歴一覧'!$C:$C=C12)*('配当金履歴一覧'!$B:$B=$B12))"),249.0) -> 249 | E15: =IFERROR(__xludf.DUMMYFUNCTION("FILTER('配当金履歴一覧'!$G:$G,('配当金履歴一覧'!$C:$C=E12)*('配当金履歴一覧'!$B:$B=$B12))"),6.0) -> 6 | F15: =IFERROR(__xludf.DUMMYFUNCTION("FILTER('配当金履歴一覧'!$H:$H,('配当金履歴一覧'!$C:$C=E12)*('配当金履歴一覧'!$B:$B=$B12))"),417.0) -> 417 | G15: =IFERROR(__xludf.DUMMYFUNCTION("FILTER('配当金履歴一覧'!$G:$G,('配当金履歴一覧'!$C:$C=G12)*('配当金履歴一覧'!$B:$B=$B12))"),6.0) -> 6 | H15: =IFERROR(__xludf.DUMMYFUNCTION("FILTER('配当金履歴一覧'!$H:$H,('配当金履歴一覧'!$C:$C=G12)*('配当金履歴一覧'!$B:$B=$B12))"),352.0) -> 352 | I15: =IFERROR(__xludf.DUMMYFUNCTION("FILTER('配当金履歴一覧'!$G:$G,('配当金履歴一覧'!$C:$C=I12)*('配当金履歴一覧'!$B:$B=$B12))"),8.0) -> 8 | J15: =IFERROR(__xludf.DUMMYFUNCTION("FILTER('配当金履歴一覧'!$H:$H,('配当金履歴一覧'!$C:$C=I12)*('配当金履歴一覧'!$B:$B=$B12))"),616.0) -> 616 | K15: =IFERROR(__xludf.DUMMYFUNCTION("FILTER('配当金履歴一覧'!$G:$G,('配当金履歴一覧'!$C:$C=K12)*('配当金履歴一覧'!$B:$B=$B12))"),8.0) -> 8 | L15: =IFERROR(__xludf.DUMMYFUNCTION("FILTER('配当金履歴一覧'!$H:$H,('配当金履歴一覧'!$C:$C=K12)*('配当金履歴一覧'!$B:$B=$B12))"),450.0) -> 450 | M15: =IFERROR(__xludf.DUMMYFUNCTION("FILTER('配当金履歴一覧'!$G:$G,('配当金履歴一覧'!$C:$C=M12)*('配当金履歴一覧'!$B:$B=$B12))"),9.0) -> 9 | N15: =IFERROR(__xludf.DUMMYFUNCTION("FILTER('配当金履歴一覧'!$H:$H,('配当金履歴一覧'!$C:$C=M12)*('配当金履歴一覧'!$B:$B=$B12))"),583.0) -> 583 | O15: =IFERROR(__xludf.DUMMYFUNCTION("FILTER('配当金履歴一覧'!$G:$G,('配当金履歴一覧'!$C:$C=O12)*('配当金履歴一覧'!$B:$B=$B12))"),9.0) -> 9 | P15: =IFERROR(__xludf.DUMMYFUNCTION("FILTER('配当金履歴一覧'!$H:$H,('配当金履歴一覧'!$C:$C=O12)*('配当金履歴一覧'!$B:$B=$B12))"),582.0) -> 582 | Q15: =IFERROR(__xludf.DUMMYFUNCTION("FILTER('配当金履歴一覧'!$G:$G,('配当金履歴一覧'!$C:$C=Q12)*('配当金履歴一覧'!$B:$B=$B12))"),10.0) -> 10 | R15: =IFERROR(__xludf.DUMMYFUNCTION("FILTER('配当金履歴一覧'!$H:$H,('配当金履歴一覧'!$C:$C=Q12)*('配当金履歴一覧'!$B:$B=$B12))"),768.0) -> 768
A16: 1605 | B16: INPEX | C16: 45536 | E16: 45717 | G16: 45901
C17: =IFERROR(__xludf.DUMMYFUNCTION("FILTER('配当金履歴一覧'!$D:$D,('配当金履歴一覧'!$C:$C=C16)*('配当金履歴一覧'!$B:$B=$B16))"),43.0) -> 43 | E17: =IFERROR(__xludf.DUMMYFUNCTION("FILTER('配当金履歴一覧'!$D:$D,('配当金履歴一覧'!$C:$C=E16)*('配当金履歴一覧'!$B:$B=$B16))"),43.0) -> 43 | G17: =IFERROR(__xludf.DUMMYFUNCTION("FILTER('配当金履歴一覧'!$D:$D,('配当金履歴一覧'!$C:$C=G16)*('配当金履歴一覧'!$B:$B=$B16))"),50.0) -> 50
C18: =IFERROR(__xludf.DUMMYFUNCTION("FILTER('配当金履歴一覧'!$G:$G,('配当金履歴一覧'!$C:$C=C16)*('配当金履歴一覧'!$B:$B=$B16))"),4.0) -> 4 | D18: =IFERROR(__xludf.DUMMYFUNCTION("FILTER('配当金履歴一覧'!$H:$H,('配当金履歴一覧'!$C:$C=C16)*('配当金履歴一覧'!$B:$B=$B16))"),172.0) -> 172 | E18: =IFERROR(__xludf.DUMMYFUNCTION("FILTER('配当金履歴一覧'!$G:$G,('配当金履歴一覧'!$C:$C=E16)*('配当金履歴一覧'!$B:$B=$B16))"),13.0) -> 13 | F18: =IFERROR(__xludf.DUMMYFUNCTION("FILTER('配当金履歴一覧'!$H:$H,('配当金履歴一覧'!$C:$C=E16)*('配当金履歴一覧'!$B:$B=$B16))"),559.0) -> 559 | G18: =IFERROR(__xludf.DUMMYFUNCTION("FILTER('配当金履歴一覧'!$G:$G,('配当金履歴一覧'!$C:$C=G16)*('配当金履歴一覧'!$B:$B=$B16))"),26.0) -> 26 | H18: =IFERROR(__xludf.DUMMYFUNCTION("FILTER('配当金履歴一覧'!$H:$H,('配当金履歴一覧'!$C:$C=G16)*('配当金履歴一覧'!$B:$B=$B16))"),1300.0) -> 1300
A19: 1808 | B19: 長谷工コーポレーション | C19: 45444 | E19: 45627 | G19: 45809 | I19: 45992
C20: =IFERROR(__xludf.DUMMYFUNCTION("FILTER('配当金履歴一覧'!$D:$D,('配当金履歴一覧'!$C:$C=C19)*('配当金履歴一覧'!$B:$B=$B19))"),45.0) -> 45 | E20: =IFERROR(__xludf.DUMMYFUNCTION("FILTER('配当金履歴一覧'!$D:$D,('配当金履歴一覧'!$C:$C=E19)*('配当金履歴一覧'!$B:$B=$B19))"),40.0) -> 40 | G20: =IFERROR(__xludf.DUMMYFUNCTION("FILTER('配当金履歴一覧'!$D:$D,('配当金履歴一覧'!$C:$C=G19)*('配当金履歴一覧'!$B:$B=$B19))"),45.0) -> 45 | I20: =IFERROR(__xludf.DUMMYFUNCTION("FILTER('配当金履歴一覧'!$D:$D,('配当金履歴一覧'!$C:$C=I19)*('配当金履歴一覧'!$B:$B=$B19))"),45.0) -> 45
C21: =IFERROR(__xludf.DUMMYFUNCTION("FILTER('配当金履歴一覧'!$E:$E,('配当金履歴一覧'!$C:$C=C19)*('配当金履歴一覧'!$B:$B=$B19))"),8.0) -> 8 | D21: =IFERROR(__xludf.DUMMYFUNCTION("FILTER('配当金履歴一覧'!$F:$F,('配当金履歴一覧'!$C:$C=C19)*('配当金履歴一覧'!$B:$B=$B19))"),287.0) -> 287 | E21: =IFERROR(__xludf.DUMMYFUNCTION("FILTER('配当金履歴一覧'!$E:$E,('配当金履歴一覧'!$C:$C=E19)*('配当金履歴一覧'!$B:$B=$B19))"),8.0) -> 8 | F21: =IFERROR(__xludf.DUMMYFUNCTION("FILTER('配当金履歴一覧'!$F:$F,('配当金履歴一覧'!$C:$C=E19)*('配当金履歴一覧'!$B:$B=$B19))"),255.0) -> 255 | G21: =IFERROR(__xludf.DUMMYFUNCTION("FILTER('配当金履歴一覧'!$E:$E,('配当金履歴一覧'!$C:$C=G19)*('配当金履歴一覧'!$B:$B=$B19))"),8.0) -> 8 | H21: =IFERROR(__xludf.DUMMYFUNCTION("FILTER('配当金履歴一覧'!$F:$F,('配当金履歴一覧'!$C:$C=G19)*('配当金履歴一覧'!$B:$B=$B19))"),287.0) -> 287 | I21: =IFERROR(__xludf.DUMMYFUNCTION("FILTER('配当金履歴一覧'!$E:$E,('配当金履歴一覧'!$C:$C=I19)*('配当金履歴一覧'!$B:$B=$B19))"),8.0) -> 8 | J21: =IFERROR(__xludf.DUMMYFUNCTION("FILTER('配当金履歴一覧'!$F:$F,('配当金履歴一覧'!$C:$C=I19)*('配当金履歴一覧'!$B:$B=$B19))"),287.0) -> 287
C22: =IFERROR(__xludf.DUMMYFUNCTION("FILTER('配当金履歴一覧'!$G:$G,('配当金履歴一覧'!$C:$C=C19)*('配当金履歴一覧'!$B:$B=$B19))"),0.0) -> 0 | D22: =IFERROR(__xludf.DUMMYFUNCTION("FILTER('配当金履歴一覧'!$H:$H,('配当金履歴一覧'!$C:$C=C19)*('配当金履歴一覧'!$B:$B=$B19))"),0.0) -> 0 | E22: =IFERROR(__xludf.DUMMYFUNCTION("FILTER('配当金履歴一覧'!$G:$G,('配当金履歴一覧'!$C:$C=E19)*('配当金履歴一覧'!$B:$B=$B19))"),4.0) -> 4 | F22: =IFERROR(__xludf.DUMMYFUNCTION("FILTER('配当金履歴一覧'!$H:$H,('配当金履歴一覧'!$C:$C=E19)*('配当金履歴一覧'!$B:$B=$B19))"),160.0) -> 160 | G22: =IFERROR(__xludf.DUMMYFUNCTION("FILTER('配当金履歴一覧'!$G:$G,('配当金履歴一覧'!$C:$C=G19)*('配当金履歴一覧'!$B:$B=$B19))"),6.0) -> 6 | H22: =IFERROR(__xludf.DUMMYFUNCTION("FILTER('配当金履歴一覧'!$H:$H,('配当金履歴一覧'!$C:$C=G19)*('配当金履歴一覧'!$B:$B=$B19))"),270.0) -> 270 | I22: =IFERROR(__xludf.DUMMYFUNCTION("FILTER('配当金履歴一覧'!$G:$G,('配当金履歴一覧'!$C:$C=I19)*('配当金履歴一覧'!$B:$B=$B19))"),6.0) -> 6 | J22: =IFERROR(__xludf.DUMMYFUNCTION("FILTER('配当金履歴一覧'!$H:$H,('配当金履歴一覧'!$C:$C=I19)*('配当金履歴一覧'!$B:$B=$B19))"),270.0) -> 270
A23: 1911 | B23: 住友林業 | C23: 45352 | E23: 45536 | G23: 45717 | I23: 45901
C24: =IFERROR(__xludf.DUMMYFUNCTION("FILTER('配当金履歴一覧'!$D:$D,('配当金履歴一覧'!$C:$C=C23)*('配当金履歴一覧'!$B:$B=$B23))"),65.0) -> 65 | E24: =IFERROR(__xludf.DUMMYFUNCTION("FILTER('配当金履歴一覧'!$D:$D,('配当金履歴一覧'!$C:$C=E23)*('配当金履歴一覧'!$B:$B=$B23))"),65.0) -> 65 | G24: =IFERROR(__xludf.DUMMYFUNCTION("FILTER('配当金履歴一覧'!$D:$D,('配当金履歴一覧'!$C:$C=G23)*('配当金履歴一覧'!$B:$B=$B23))"),80.0) -> 80 | I24: =IFERROR(__xludf.DUMMYFUNCTION("FILTER('配当金履歴一覧'!$D:$D,('配当金履歴一覧'!$C:$C=I23)*('配当金履歴一覧'!$B:$B=$B23))"),75.0) -> 75
C25: =IFERROR(__xludf.DUMMYFUNCTION("FILTER('配当金履歴一覧'!$E:$E,('配当金履歴一覧'!$C:$C=C23)*('配当金履歴一覧'!$B:$B=$B23))"),16.0) -> 16 | D25: =IFERROR(__xludf.DUMMYFUNCTION("FILTER('配当金履歴一覧'!$F:$F,('配当金履歴一覧'!$C:$C=C23)*('配当金履歴一覧'!$B:$B=$B23))"),829.0) -> 829 | E25: =IFERROR(__xludf.DUMMYFUNCTION("FILTER('配当金履歴一覧'!$E:$E,('配当金履歴一覧'!$C:$C=E23)*('配当金履歴一覧'!$B:$B=$B23))"),16.0) -> 16 | F25: =IFERROR(__xludf.DUMMYFUNCTION("FILTER('配当金履歴一覧'!$F:$F,('配当金履歴一覧'!$C:$C=E23)*('配当金履歴一覧'!$B:$B=$B23))"),829.0) -> 829 | G25: =IFERROR(__xludf.DUMMYFUNCTION("FILTER('配当金履歴一覧'!$E:$E,('配当金履歴一覧'!$C:$C=G23)*('配当金履歴一覧'!$B:$B=$B23))"),16.0) -> 16 | H25: =IFERROR(__xludf.DUMMYFUNCTION("FILTER('配当金履歴一覧'!$F:$F,('配当金履歴一覧'!$C:$C=G23)*('配当金履歴一覧'!$B:$B=$B23))"),1020.0) -> 1020 | I25: =IFERROR(__xludf.DUMMYFUNCTION("FILTER('配当金履歴一覧'!$E:$E,('配当金履歴一覧'!$C:$C=I23)*('配当金履歴一覧'!$B:$B=$B23))"),16.0) -> 16 | J25: =IFERROR(__xludf.DUMMYFUNCTION("FILTER('配当金履歴一覧'!$F:$F,('配当金履歴一覧'!$C:$C=I23)*('配当金履歴一覧'!$B:$B=$B23))"),957.0) -> 957
C26: =IFERROR(__xludf.DUMMYFUNCTION("FILTER('配当金履歴一覧'!$G:$G,('配当金履歴一覧'!$C:$C=C23)*('配当金履歴一覧'!$B:$B=$B23))"),0.0) -> 0 | D26: =IFERROR(__xludf.DUMMYFUNCTION("FILTER('配当金履歴一覧'!$H:$H,('配当金履歴一覧'!$C:$C=C23)*('配当金履歴一覧'!$B:$B=$B23))"),0.0) -> 0 | E26: =IFERROR(__xludf.DUMMYFUNCTION("FILTER('配当金履歴一覧'!$G:$G,('配当金履歴一覧'!$C:$C=E23)*('配当金履歴一覧'!$B:$B=$B23))"),5.0) -> 5 | F26: =IFERROR(__xludf.DUMMYFUNCTION("FILTER('配当金履歴一覧'!$H:$H,('配当金履歴一覧'!$C:$C=E23)*('配当金履歴一覧'!$B:$B=$B23))"),325.0) -> 325 | G26: =IFERROR(__xludf.DUMMYFUNCTION("FILTER('配当金履歴一覧'!$G:$G,('配当金履歴一覧'!$C:$C=G23)*('配当金履歴一覧'!$B:$B=$B23))"),6.0) -> 6 | H26: =IFERROR(__xludf.DUMMYFUNCTION("FILTER('配当金履歴一覧'!$H:$H,('配当金履歴一覧'!$C:$C=G23)*('配当金履歴一覧'!$B:$B=$B23))"),480.0) -> 480 | I26: =IFERROR(__xludf.DUMMYFUNCTION("FILTER('配当金履歴一覧'!$G:$G,('配当金履歴一覧'!$C:$C=I23)*('配当金履歴一覧'!$B:$B=$B23))"),9.0) -> 9 | J26: =IFERROR(__xludf.DUMMYFUNCTION("FILTER('配当金履歴一覧'!$H:$H,('配当金履歴一覧'!$C:$C=I23)*('配当金履歴一覧'!$B:$B=$B23))"),675.0) -> 675
A27: 1925 | B27: 大和ハウス工業 | C27: 45444 | E27: 45627 | G27: 45809 | I27: 45992
C28: =IFERROR(__xludf.DUMMYFUNCTION("FILTER('配当金履歴一覧'!$D:$D,('配当金履歴一覧'!$C:$C=C27)*('配当金履歴一覧'!$B:$B=$B27))"),80.0) -> 80 | E28: =IFERROR(__xludf.DUMMYFUNCTION("FILTER('配当金履歴一覧'!$D:$D,('配当金履歴一覧'!$C:$C=E27)*('配当金履歴一覧'!$B:$B=$B27))"),70.0) -> 70 | G28: =IFERROR(__xludf.DUMMYFUNCTION("FILTER('配当金履歴一覧'!$D:$D,('配当金履歴一覧'!$C:$C=G27)*('配当金履歴一覧'!$B:$B=$B27))"),80.0) -> 80 | I28: =IFERROR(__xludf.DUMMYFUNCTION("FILTER('配当金履歴一覧'!$D:$D,('配当金履歴一覧'!$C:$C=I27)*('配当金履歴一覧'!$B:$B=$B27))"),75.0) -> 75
C29: =IFERROR(__xludf.DUMMYFUNCTION("FILTER('配当金履歴一覧'!$E:$E,('配当金履歴一覧'!$C:$C=C27)*('配当金履歴一覧'!$B:$B=$B27))"),8.0) -> 8 | D29: =IFERROR(__xludf.DUMMYFUNCTION("FILTER('配当金履歴一覧'!$F:$F,('配当金履歴一覧'!$C:$C=C27)*('配当金履歴一覧'!$B:$B=$B27))"),510.0) -> 510 | E29: =IFERROR(__xludf.DUMMYFUNCTION("FILTER('配当金履歴一覧'!$E:$E,('配当金履歴一覧'!$C:$C=E27)*('配当金履歴一覧'!$B:$B=$B27))"),8.0) -> 8 | F29: =IFERROR(__xludf.DUMMYFUNCTION("FILTER('配当金履歴一覧'!$F:$F,('配当金履歴一覧'!$C:$C=E27)*('配当金履歴一覧'!$B:$B=$B27))"),447.0) -> 447 | G29: =IFERROR(__xludf.DUMMYFUNCTION("FILTER('配当金履歴一覧'!$E:$E,('配当金履歴一覧'!$C:$C=G27)*('配当金履歴一覧'!$B:$B=$B27))"),8.0) -> 8 | H29: =IFERROR(__xludf.DUMMYFUNCTION("FILTER('配当金履歴一覧'!$F:$F,('配当金履歴一覧'!$C:$C=G27)*('配当金履歴一覧'!$B:$B=$B27))"),510.0) -> 510 | I29: =IFERROR(__xludf.DUMMYFUNCTION("FILTER('配当金履歴一覧'!$E:$E,('配当金履歴一覧'!$C:$C=I27)*('配当金履歴一覧'!$B:$B=$B27))"),8.0) -> 8 | J29: =IFERROR(__xludf.DUMMYFUNCTION("FILTER('配当金履歴一覧'!$F:$F,('配当金履歴一覧'!$C:$C=I27)*('配当金履歴一覧'!$B:$B=$B27))"),479.0) -> 479
C30: =IFERROR(__xludf.DUMMYFUNCTION("FILTER('配当金履歴一覧'!$G:$G,('配当金履歴一覧'!$C:$C=C27)*('配当金履歴一覧'!$B:$B=$B27))"),1.0) -> 1 | D30: =IFERROR(__xludf.DUMMYFUNCTION("FILTER('配当金履歴一覧'!$H:$H,('配当金履歴一覧'!$C:$C=C27)*('配当金履歴一覧'!$B:$B=$B27))"),80.0) -> 80 | E30: =IFERROR(__xludf.DUMMYFUNCTION("FILTER('配当金履歴一覧'!$G:$G,('配当金履歴一覧'!$C:$C=E27)*('配当金履歴一覧'!$B:$B=$B27))"),5.0) -> 5 | F30: =IFERROR(__xludf.DUMMYFUNCTION("FILTER('配当金履歴一覧'!$H:$H,('配当金履歴一覧'!$C:$C=E27)*('配当金履歴一覧'!$B:$B=$B27))"),350.0) -> 350 | G30: =IFERROR(__xludf.DUMMYFUNCTION("FILTER('配当金履歴一覧'!$G:$G,('配当金履歴一覧'!$C:$C=G27)*('配当金履歴一覧'!$B:$B=$B27))"),5.0) -> 5 | H30: =IFERROR(__xludf.DUMMYFUNCTION("FILTER('配当金履歴一覧'!$H:$H,('配当金履歴一覧'!$C:$C=G27)*('配当金履歴一覧'!$B:$B=$B27))"),400.0) -> 400 | I30: =IFERROR(__xludf.DUMMYFUNCTION("FILTER('配当金履歴一覧'!$G:$G,('配当金履歴一覧'!$C:$C=I27)*('配当金履歴一覧'!$B:$B=$B27))"),5.0) -> 5 | J30: =IFERROR(__xludf.DUMMYFUNCTION("FILTER('配当金履歴一覧'!$H:$H,('配当金履歴一覧'!$C:$C=I27)*('配当金履歴一覧'!$B:$B=$B27))"),375.0) -> 375
A31: 1928 | B31: 積水ハウス | C31: 45383 | E31: 45536 | G31: 45748 | I31: 45901
C32: =IFERROR(__xludf.DUMMYFUNCTION("FILTER('配当金履歴一覧'!$D:$D,('配当金履歴一覧'!$C:$C=C31)*('配当金履歴一覧'!$B:$B=$B31))"),64.0) -> 64 | E32: =IFERROR(__xludf.DUMMYFUNCTION("FILTER('配当金履歴一覧'!$D:$D,('配当金履歴一覧'!$C:$C=E31)*('配当金履歴一覧'!$B:$B=$B31))"),64.0) -> 64 | G32: =IFERROR(__xludf.DUMMYFUNCTION("FILTER('配当金履歴一覧'!$D:$D,('配当金履歴一覧'!$C:$C=G31)*('配当金履歴一覧'!$B:$B=$B31))"),71.0) -> 71 | I32: =IFERROR(__xludf.DUMMYFUNCTION("FILTER('配当金履歴一覧'!$D:$D,('配当金履歴一覧'!$C:$C=I31)*('配当金履歴一覧'!$B:$B=$B31))"),72.0) -> 72
C33: =IFERROR(__xludf.DUMMYFUNCTION("FILTER('配当金履歴一覧'!$E:$E,('配当金履歴一覧'!$C:$C=C31)*('配当金履歴一覧'!$B:$B=$B31))"),15.0) -> 15 | D33: =IFERROR(__xludf.DUMMYFUNCTION("FILTER('配当金履歴一覧'!$F:$F,('配当金履歴一覧'!$C:$C=C31)*('配当金履歴一覧'!$B:$B=$B31))"),765.0) -> 765 | E33: =IFERROR(__xludf.DUMMYFUNCTION("FILTER('配当金履歴一覧'!$E:$E,('配当金履歴一覧'!$C:$C=E31)*('配当金履歴一覧'!$B:$B=$B31))"),15.0) -> 15 | F33: =IFERROR(__xludf.DUMMYFUNCTION("FILTER('配当金履歴一覧'!$F:$F,('配当金履歴一覧'!$C:$C=E31)*('配当金履歴一覧'!$B:$B=$B31))"),765.0) -> 765 | G33: =IFERROR(__xludf.DUMMYFUNCTION("FILTER('配当金履歴一覧'!$E:$E,('配当金履歴一覧'!$C:$C=G31)*('配当金履歴一覧'!$B:$B=$B31))"),15.0) -> 15 | H33: =IFERROR(__xludf.DUMMYFUNCTION("FILTER('配当金履歴一覧'!$F:$F,('配当金履歴一覧'!$C:$C=G31)*('配当金履歴一覧'!$B:$B=$B31))"),849.0) -> 849 | I33: =IFERROR(__xludf.DUMMYFUNCTION("FILTER('配当金履歴一覧'!$E:$E,('配当金履歴一覧'!$C:$C=I31)*('配当金履歴一覧'!$B:$B=$B31))"),15.0) -> 15 | J33: =IFERROR(__xludf.DUMMYFUNCTION("FILTER('配当金履歴一覧'!$F:$F,('配当金履歴一覧'!$C:$C=I31)*('配当金履歴一覧'!$B:$B=$B31))"),861.0) -> 861
C34: =IFERROR(__xludf.DUMMYFUNCTION("FILTER('配当金履歴一覧'!$G:$G,('配当金履歴一覧'!$C:$C=C31)*('配当金履歴一覧'!$B:$B=$B31))"),0.0) -> 0 | D34: =IFERROR(__xludf.DUMMYFUNCTION("FILTER('配当金履歴一覧'!$H:$H,('配当金履歴一覧'!$C:$C=C31)*('配当金履歴一覧'!$B:$B=$B31))"),0.0) -> 0 | E34: =IFERROR(__xludf.DUMMYFUNCTION("FILTER('配当金履歴一覧'!$G:$G,('配当金履歴一覧'!$C:$C=E31)*('配当金履歴一覧'!$B:$B=$B31))"),2.0) -> 2 | F34: =IFERROR(__xludf.DUMMYFUNCTION("FILTER('配当金履歴一覧'!$H:$H,('配当金履歴一覧'!$C:$C=E31)*('配当金履歴一覧'!$B:$B=$B31))"),128.0) -> 128 | G34: =IFERROR(__xludf.DUMMYFUNCTION("FILTER('配当金履歴一覧'!$G:$G,('配当金履歴一覧'!$C:$C=G31)*('配当金履歴一覧'!$B:$B=$B31))"),4.0) -> 4 | H34: =IFERROR(__xludf.DUMMYFUNCTION("FILTER('配当金履歴一覧'!$H:$H,('配当金履歴一覧'!$C:$C=G31)*('配当金履歴一覧'!$B:$B=$B31))"),284.0) -> 284 | I34: =IFERROR(__xludf.DUMMYFUNCTION("FILTER('配当金履歴一覧'!$G:$G,('配当金履歴一覧'!$C:$C=I31)*('配当金履歴一覧'!$B:$B=$B31))"),9.0) -> 9 | J34: =IFERROR(__xludf.DUMMYFUNCTION("FILTER('配当金履歴一覧'!$H:$H,('配当金履歴一覧'!$C:$C=I31)*('配当金履歴一覧'!$B:$B=$B31))"),648.0) -> 648
A35: 2124 | B35: ジェイエイシーリクルートメント | C35: 45352 | E35: 45717
C36: =IFERROR(__xludf.DUMMYFUNCTION("FILTER('配当金履歴一覧'!$D:$D,('配当金履歴一覧'!$C:$C=C35)*('配当金履歴一覧'!$B:$B=$B35))"),90.0) -> 90 | E36: =IFERROR(__xludf.DUMMYFUNCTION("FILTER('配当金履歴一覧'!$D:$D,('配当金履歴一覧'!$C:$C=E35)*('配当金履歴一覧'!$B:$B=$B35))"),26.0) -> 26
C37: =IFERROR(__xludf.DUMMYFUNCTION("FILTER('配当金履歴一覧'!$E:$E,('配当金履歴一覧'!$C:$C=C35)*('配当金履歴一覧'!$B:$B=$B35))"),16.0) -> 16 | D37: =IFERROR(__xludf.DUMMYFUNCTION("FILTER('配当金履歴一覧'!$F:$F,('配当金履歴一覧'!$C:$C=C35)*('配当金履歴一覧'!$B:$B=$B35))"),1148.0) -> 1148 | E37: =IFERROR(__xludf.DUMMYFUNCTION("FILTER('配当金履歴一覧'!$E:$E,('配当金履歴一覧'!$C:$C=E35)*('配当金履歴一覧'!$B:$B=$B35))"),64.0) -> 64 | F37: =IFERROR(__xludf.DUMMYFUNCTION("FILTER('配当金履歴一覧'!$F:$F,('配当金履歴一覧'!$C:$C=E35)*('配当金履歴一覧'!$B:$B=$B35))"),1327.0) -> 1327
C38: =IFERROR(__xludf.DUMMYFUNCTION("FILTER('配当金履歴一覧'!$G:$G,('配当金履歴一覧'!$C:$C=C35)*('配当金履歴一覧'!$B:$B=$B35))"),0.0) -> 0 | D38: =IFERROR(__xludf.DUMMYFUNCTION("FILTER('配当金履歴一覧'!$H:$H,('配当金履歴一覧'!$C:$C=C35)*('配当金履歴一覧'!$B:$B=$B35))"),0.0) -> 0 | E38: =IFERROR(__xludf.DUMMYFUNCTION("FILTER('配当金履歴一覧'!$G:$G,('配当金履歴一覧'!$C:$C=E35)*('配当金履歴一覧'!$B:$B=$B35))"),10.0) -> 10 | F38: =IFERROR(__xludf.DUMMYFUNCTION("FILTER('配当金履歴一覧'!$H:$H,('配当金履歴一覧'!$C:$C=E35)*('配当金履歴一覧'!$B:$B=$B35))"),260.0) -> 260
A39: 2503 | B39: キリンホールディングス | C39: 45352 | E39: 45536 | G39: 45717 | I39: 45901
C40: =IFERROR(__xludf.DUMMYFUNCTION("FILTER('配当金履歴一覧'!$D:$D,('配当金履歴一覧'!$C:$C=C39)*('配当金履歴一覧'!$B:$B=$B39))"),36.5) -> 36.5 | E40: =IFERROR(__xludf.DUMMYFUNCTION("FILTER('配当金履歴一覧'!$D:$D,('配当金履歴一覧'!$C:$C=E39)*('配当金履歴一覧'!$B:$B=$B39))"),35.5) -> 35.5 | G40: =IFERROR(__xludf.DUMMYFUNCTION("FILTER('配当金履歴一覧'!$D:$D,('配当金履歴一覧'!$C:$C=G39)*('配当金履歴一覧'!$B:$B=$B39))"),35.5) -> 35.5 | I40: =IFERROR(__xludf.DUMMYFUNCTION("FILTER('配当金履歴一覧'!$D:$D,('配当金履歴一覧'!$C:$C=I39)*('配当金履歴一覧'!$B:$B=$B39))"),37.0) -> 37
C41: =IFERROR(__xludf.DUMMYFUNCTION("FILTER('配当金履歴一覧'!$E:$E,('配当金履歴一覧'!$C:$C=C39)*('配当金履歴一覧'!$B:$B=$B39))"),9.0) -> 9 | D41: =IFERROR(__xludf.DUMMYFUNCTION("FILTER('配当金履歴一覧'!$F:$F,('配当金履歴一覧'!$C:$C=C39)*('配当金履歴一覧'!$B:$B=$B39))"),262.0) -> 262 | E41: =IFERROR(__xludf.DUMMYFUNCTION("FILTER('配当金履歴一覧'!$E:$E,('配当金履歴一覧'!$C:$C=E39)*('配当金履歴一覧'!$B:$B=$B39))"),9.0) -> 9 | F41: =IFERROR(__xludf.DUMMYFUNCTION("FILTER('配当金履歴一覧'!$F:$F,('配当金履歴一覧'!$C:$C=E39)*('配当金履歴一覧'!$B:$B=$B39))"),256.0) -> 256 | G41: =IFERROR(__xludf.DUMMYFUNCTION("FILTER('配当金履歴一覧'!$E:$E,('配当金履歴一覧'!$C:$C=G39)*('配当金履歴一覧'!$B:$B=$B39))"),9.0) -> 9 | H41: =IFERROR(__xludf.DUMMYFUNCTION("FILTER('配当金履歴一覧'!$F:$F,('配当金履歴一覧'!$C:$C=G39)*('配当金履歴一覧'!$B:$B=$B39))"),256.0) -> 256 | I41: =IFERROR(__xludf.DUMMYFUNCTION("FILTER('配当金履歴一覧'!$E:$E,('配当金履歴一覧'!$C:$C=I39)*('配当金履歴一覧'!$B:$B=$B39))"),9.0) -> 9 | J41: =IFERROR(__xludf.DUMMYFUNCTION("FILTER('配当金履歴一覧'!$F:$F,('配当金履歴一覧'!$C:$C=I39)*('配当金履歴一覧'!$B:$B=$B39))"),267.0) -> 267
C42: =IFERROR(__xludf.DUMMYFUNCTION("FILTER('配当金履歴一覧'!$G:$G,('配当金履歴一覧'!$C:$C=C39)*('配当金履歴一覧'!$B:$B=$B39))"),0.0) -> 0 | D42: =IFERROR(__xludf.DUMMYFUNCTION("FILTER('配当金履歴一覧'!$H:$H,('配当金履歴一覧'!$C:$C=C39)*('配当金履歴一覧'!$B:$B=$B39))"),0.0) -> 0 | E42: =IFERROR(__xludf.DUMMYFUNCTION("FILTER('配当金履歴一覧'!$G:$G,('配当金履歴一覧'!$C:$C=E39)*('配当金履歴一覧'!$B:$B=$B39))"),2.0) -> 2 | F42: =IFERROR(__xludf.DUMMYFUNCTION("FILTER('配当金履歴一覧'!$H:$H,('配当金履歴一覧'!$C:$C=E39)*('配当金履歴一覧'!$B:$B=$B39))"),72.0) -> 72 | G42: =IFERROR(__xludf.DUMMYFUNCTION("FILTER('配当金履歴一覧'!$G:$G,('配当金履歴一覧'!$C:$C=G39)*('配当金履歴一覧'!$B:$B=$B39))"),2.0) -> 2 | H42: =IFERROR(__xludf.DUMMYFUNCTION("FILTER('配当金履歴一覧'!$H:$H,('配当金履歴一覧'!$C:$C=G39)*('配当金履歴一覧'!$B:$B=$B39))"),72.0) -> 72 | I42: =IFERROR(__xludf.DUMMYFUNCTION("FILTER('配当金履歴一覧'!$G:$G,('配当金履歴一覧'!$C:$C=I39)*('配当金履歴一覧'!$B:$B=$B39))"),4.0) -> 4 | J42: =IFERROR(__xludf.DUMMYFUNCTION("FILTER('配当金履歴一覧'!$H:$H,('配当金履歴一覧'!$C:$C=I39)*('配当金履歴一覧'!$B:$B=$B39))"),148.0) -> 148
A43: 2768 | B43: 双日 | C43: 45444 | E43: 45627 | G43: 45809 | I43: 45992
C44: =IFERROR(__xludf.DUMMYFUNCTION("FILTER('配当金履歴一覧'!$D:$D,('配当金履歴一覧'!$C:$C=C43)*('配当金履歴一覧'!$B:$B=$B43))"),70.0) -> 70 | E44: =IFERROR(__xludf.DUMMYFUNCTION("FILTER('配当金履歴一覧'!$D:$D,('配当金履歴一覧'!$C:$C=E43)*('配当金履歴一覧'!$B:$B=$B43))"),75.0) -> 75 | G44: =IFERROR(__xludf.DUMMYFUNCTION("FILTER('配当金履歴一覧'!$D:$D,('配当金履歴一覧'!$C:$C=G43)*('配当金履歴一覧'!$B:$B=$B43))"),75.0) -> 75 | I44: =IFERROR(__xludf.DUMMYFUNCTION("FILTER('配当金履歴一覧'!$D:$D,('配当金履歴一覧'!$C:$C=I43)*('配当金履歴一覧'!$B:$B=$B43))"),82.5) -> 82.5
C45: =IFERROR(__xludf.DUMMYFUNCTION("FILTER('配当金履歴一覧'!$E:$E,('配当金履歴一覧'!$C:$C=C43)*('配当金履歴一覧'!$B:$B=$B43))"),17.0) -> 17 | D45: =IFERROR(__xludf.DUMMYFUNCTION("FILTER('配当金履歴一覧'!$F:$F,('配当金履歴一覧'!$C:$C=C43)*('配当金履歴一覧'!$B:$B=$B43))"),949.0) -> 949 | E45: =IFERROR(__xludf.DUMMYFUNCTION("FILTER('配当金履歴一覧'!$E:$E,('配当金履歴一覧'!$C:$C=E43)*('配当金履歴一覧'!$B:$B=$B43))"),17.0) -> 17 | F45: =IFERROR(__xludf.DUMMYFUNCTION("FILTER('配当金履歴一覧'!$F:$F,('配当金履歴一覧'!$C:$C=E43)*('配当金履歴一覧'!$B:$B=$B43))"),1017.0) -> 1017 | G45: =IFERROR(__xludf.DUMMYFUNCTION("FILTER('配当金履歴一覧'!$E:$E,('配当金履歴一覧'!$C:$C=G43)*('配当金履歴一覧'!$B:$B=$B43))"),17.0) -> 17 | H45: =IFERROR(__xludf.DUMMYFUNCTION("FILTER('配当金履歴一覧'!$F:$F,('配当金履歴一覧'!$C:$C=G43)*('配当金履歴一覧'!$B:$B=$B43))"),1017.0) -> 1017 | I45: =IFERROR(__xludf.DUMMYFUNCTION("FILTER('配当金履歴一覧'!$E:$E,('配当金履歴一覧'!$C:$C=I43)*('配当金履歴一覧'!$B:$B=$B43))"),17.0) -> 17 | J45: =IFERROR(__xludf.DUMMYFUNCTION("FILTER('配当金履歴一覧'!$F:$F,('配当金履歴一覧'!$C:$C=I43)*('配当金履歴一覧'!$B:$B=$B43))"),1118.0) -> 1118
C46: =IFERROR(__xludf.DUMMYFUNCTION("FILTER('配当金履歴一覧'!$G:$G,('配当金履歴一覧'!$C:$C=C43)*('配当金履歴一覧'!$B:$B=$B43))"),0.0) -> 0 | D46: =IFERROR(__xludf.DUMMYFUNCTION("FILTER('配当金履歴一覧'!$H:$H,('配当金履歴一覧'!$C:$C=C43)*('配当金履歴一覧'!$B:$B=$B43))"),0.0) -> 0 | E46: =IFERROR(__xludf.DUMMYFUNCTION("FILTER('配当金履歴一覧'!$G:$G,('配当金履歴一覧'!$C:$C=E43)*('配当金履歴一覧'!$B:$B=$B43))"),7.0) -> 7 | F46: =IFERROR(__xludf.DUMMYFUNCTION("FILTER('配当金履歴一覧'!$H:$H,('配当金履歴一覧'!$C:$C=E43)*('配当金履歴一覧'!$B:$B=$B43))"),525.0) -> 525 | G46: =IFERROR(__xludf.DUMMYFUNCTION("FILTER('配当金履歴一覧'!$G:$G,('配当金履歴一覧'!$C:$C=G43)*('配当金履歴一覧'!$B:$B=$B43))"),10.0) -> 10 | H46: =IFERROR(__xludf.DUMMYFUNCTION("FILTER('配当金履歴一覧'!$H:$H,('配当金履歴一覧'!$C:$C=G43)*('配当金履歴一覧'!$B:$B=$B43))"),750.0) -> 750 | I46: =IFERROR(__xludf.DUMMYFUNCTION("FILTER('配当金履歴一覧'!$G:$G,('配当金履歴一覧'!$C:$C=I43)*('配当金履歴一覧'!$B:$B=$B43))"),13.0) -> 13 | J46: =IFERROR(__xludf.DUMMYFUNCTION("FILTER('配当金履歴一覧'!$H:$H,('配当金履歴一覧'!$C:$C=I43)*('配当金履歴一覧'!$B:$B=$B43))"),1073.0) -> 1073
A47: 2914 | B47: 日本たばこ産業 | C47: 45536 | E47: 45717 | G47: 45901
C48: =IFERROR(__xludf.DUMMYFUNCTION("FILTER('配当金履歴一覧'!$D:$D,('配当金履歴一覧'!$C:$C=C47)*('配当金履歴一覧'!$B:$B=$B47))"),97.0) -> 97 | E48: =IFERROR(__xludf.DUMMYFUNCTION("FILTER('配当金履歴一覧'!$D:$D,('配当金履歴一覧'!$C:$C=E47)*('配当金履歴一覧'!$B:$B=$B47))"),97.0) -> 97 | G48: =IFERROR(__xludf.DUMMYFUNCTION("FILTER('配当金履歴一覧'!$D:$D,('配当金履歴一覧'!$C:$C=G47)*('配当金履歴一覧'!$B:$B=$B47))"),104.0) -> 104
C49: =IFERROR(__xludf.DUMMYFUNCTION("FILTER('配当金履歴一覧'!$G:$G,('配当金履歴一覧'!$C:$C=C47)*('配当金履歴一覧'!$B:$B=$B47))"),3.0) -> 3 | D49: =IFERROR(__xludf.DUMMYFUNCTION("FILTER('配当金履歴一覧'!$H:$H,('配当金履歴一覧'!$C:$C=C47)*('配当金履歴一覧'!$B:$B=$B47))"),291.0) -> 291 | E49: =IFERROR(__xludf.DUMMYFUNCTION("FILTER('配当金履歴一覧'!$G:$G,('配当金履歴一覧'!$C:$C=E47)*('配当金履歴一覧'!$B:$B=$B47))"),5.0) -> 5 | F49: =IFERROR(__xludf.DUMMYFUNCTION("FILTER('配当金履歴一覧'!$H:$H,('配当金履歴一覧'!$C:$C=E47)*('配当金履歴一覧'!$B:$B=$B47))"),485.0) -> 485 | G49: =IFERROR(__xludf.DUMMYFUNCTION("FILTER('配当金履歴一覧'!$G:$G,('配当金履歴一覧'!$C:$C=G47)*('配当金履歴一覧'!$B:$B=$B47))"),6.0) -> 6 | H49: =IFERROR(__xludf.DUMMYFUNCTION("FILTER('配当金履歴一覧'!$H:$H,('配当金履歴一覧'!$C:$C=G47)*('配当金履歴一覧'!$B:$B=$B47))"),624.0) -> 624
A50: 3003 | B50: ヒューリック | C50: 45536 | E50: 45717 | G50: 45901
C51: =IFERROR(__xludf.DUMMYFUNCTION("FILTER('配当金履歴一覧'!$D:$D,('配当金履歴一覧'!$C:$C=C50)*('配当金履歴一覧'!$B:$B=$B50))"),26.0) -> 26 | E51: =IFERROR(__xludf.DUMMYFUNCTION("FILTER('配当金履歴一覧'!$D:$D,('配当金履歴一覧'!$C:$C=E50)*('配当金履歴一覧'!$B:$B=$B50))"),28.0) -> 28 | G51: =IFERROR(__xludf.DUMMYFUNCTION("FILTER('配当金履歴一覧'!$D:$D,('配当金履歴一覧'!$C:$C=G50)*('配当金履歴一覧'!$B:$B=$B50))"),28.5) -> 28.5
C52: =IFERROR(__xludf.DUMMYFUNCTION("FILTER('配当金履歴一覧'!$G:$G,('配当金履歴一覧'!$C:$C=C50)*('配当金履歴一覧'!$B:$B=$B50))"),4.0) -> 4 | D52: =IFERROR(__xludf.DUMMYFUNCTION("FILTER('配当金履歴一覧'!$H:$H,('配当金履歴一覧'!$C:$C=C50)*('配当金履歴一覧'!$B:$B=$B50))"),104.0) -> 104 | E52: =IFERROR(__xludf.DUMMYFUNCTION("FILTER('配当金履歴一覧'!$G:$G,('配当金履歴一覧'!$C:$C=E50)*('配当金履歴一覧'!$B:$B=$B50))"),10.0) -> 10 | F52: =IFERROR(__xludf.DUMMYFUNCTION("FILTER('配当金履歴一覧'!$H:$H,('配当金履歴一覧'!$C:$C=E50)*('配当金履歴一覧'!$B:$B=$B50))"),280.0) -> 280 | G52: =IFERROR(__xludf.DUMMYFUNCTION("FILTER('配当金履歴一覧'!$G:$G,('配当金履歴一覧'!$C:$C=G50)*('配当金履歴一覧'!$B:$B=$B50))"),12.0) -> 12 | H52: =IFERROR(__xludf.DUMMYFUNCTION("FILTER('配当金履歴一覧'!$H:$H,('配当金履歴一覧'!$C:$C=G50)*('配当金履歴一覧'!$B:$B=$B50))"),342.0) -> 342
A53: 4042 | B53: 東ソー
A56: 4452 | B56: 花王 | C56: 45536 | E56: 45717 | G56: 45901
C57: =IFERROR(__xludf.DUMMYFUNCTION("FILTER('配当金履歴一覧'!$D:$D,('配当金履歴一覧'!$C:$C=C56)*('配当金履歴一覧'!$B:$B=$B56))"),76.0) -> 76 | E57: =IFERROR(__xludf.DUMMYFUNCTION("FILTER('配当金履歴一覧'!$D:$D,('配当金履歴一覧'!$C:$C=E56)*('配当金履歴一覧'!$B:$B=$B56))"),76.0) -> 76 | G57: =IFERROR(__xludf.DUMMYFUNCTION("FILTER('配当金履歴一覧'!$D:$D,('配当金履歴一覧'!$C:$C=G56)*('配当金履歴一覧'!$B:$B=$B56))"),77.0) -> 77
C58: =IFERROR(__xludf.DUMMYFUNCTION("FILTER('配当金履歴一覧'!$G:$G,('配当金履歴一覧'!$C:$C=C56)*('配当金履歴一覧'!$B:$B=$B56))"),2.0) -> 2 | D58: =IFERROR(__xludf.DUMMYFUNCTION("FILTER('配当金履歴一覧'!$H:$H,('配当金履歴一覧'!$C:$C=C56)*('配当金履歴一覧'!$B:$B=$B56))"),152.0) -> 152 | E58: =IFERROR(__xludf.DUMMYFUNCTION("FILTER('配当金履歴一覧'!$G:$G,('配当金履歴一覧'!$C:$C=E56)*('配当金履歴一覧'!$B:$B=$B56))"),4.0) -> 4 | F58: =IFERROR(__xludf.DUMMYFUNCTION("FILTER('配当金履歴一覧'!$H:$H,('配当金履歴一覧'!$C:$C=E56)*('配当金履歴一覧'!$B:$B=$B56))"),304.0) -> 304 | G58: =IFERROR(__xludf.DUMMYFUNCTION("FILTER('配当金履歴一覧'!$G:$G,('配当金履歴一覧'!$C:$C=G56)*('配当金履歴一覧'!$B:$B=$B56))"),5.0) -> 5 | H58: =IFERROR(__xludf.DUMMYFUNCTION("FILTER('配当金履歴一覧'!$H:$H,('配当金履歴一覧'!$C:$C=G56)*('配当金履歴一覧'!$B:$B=$B56))"),385.0) -> 385
A59: 4502 | B59: 武田薬品工業 | C59: 45444 | E59: 45627 | G59: 45809 | I59: 45992
C60: =IFERROR(__xludf.DUMMYFUNCTION("FILTER('配当金履歴一覧'!$D:$D,('配当金履歴一覧'!$C:$C=C59)*('配当金履歴一覧'!$B:$B=$B59))"),94.0) -> 94 | E60: =IFERROR(__xludf.DUMMYFUNCTION("FILTER('配当金履歴一覧'!$D:$D,('配当金履歴一覧'!$C:$C=E59)*('配当金履歴一覧'!$B:$B=$B59))"),98.0) -> 98 | G60: =IFERROR(__xludf.DUMMYFUNCTION("FILTER('配当金履歴一覧'!$D:$D,('配当金履歴一覧'!$C:$C=G59)*('配当金履歴一覧'!$B:$B=$B59))"),98.0) -> 98 | I60: =IFERROR(__xludf.DUMMYFUNCTION("FILTER('配当金履歴一覧'!$D:$D,('配当金履歴一覧'!$C:$C=I59)*('配当金履歴一覧'!$B:$B=$B59))"),100.0) -> 100
C61: =IFERROR(__xludf.DUMMYFUNCTION("FILTER('配当金履歴一覧'!$E:$E,('配当金履歴一覧'!$C:$C=C59)*('配当金履歴一覧'!$B:$B=$B59))"),26.0) -> 26 | D61: =IFERROR(__xludf.DUMMYFUNCTION("FILTER('配当金履歴一覧'!$F:$F,('配当金履歴一覧'!$C:$C=C59)*('配当金履歴一覧'!$B:$B=$B59))"),1948.0) -> 1948 | E61: =IFERROR(__xludf.DUMMYFUNCTION("FILTER('配当金履歴一覧'!$E:$E,('配当金履歴一覧'!$C:$C=E59)*('配当金履歴一覧'!$B:$B=$B59))"),26.0) -> 26 | F61: =IFERROR(__xludf.DUMMYFUNCTION("FILTER('配当金履歴一覧'!$F:$F,('配当金履歴一覧'!$C:$C=E59)*('配当金履歴一覧'!$B:$B=$B59))"),2031.0) -> 2031 | G61: =IFERROR(__xludf.DUMMYFUNCTION("FILTER('配当金履歴一覧'!$E:$E,('配当金履歴一覧'!$C:$C=G59)*('配当金履歴一覧'!$B:$B=$B59))"),26.0) -> 26 | H61: =IFERROR(__xludf.DUMMYFUNCTION("FILTER('配当金履歴一覧'!$F:$F,('配当金履歴一覧'!$C:$C=G59)*('配当金履歴一覧'!$B:$B=$B59))"),2031.0) -> 2031 | I61: =IFERROR(__xludf.DUMMYFUNCTION("FILTER('配当金履歴一覧'!$E:$E,('配当金履歴一覧'!$C:$C=I59)*('配当金履歴一覧'!$B:$B=$B59))"),26.0) -> 26 | J61: =IFERROR(__xludf.DUMMYFUNCTION("FILTER('配当金履歴一覧'!$F:$F,('配当金履歴一覧'!$C:$C=I59)*('配当金履歴一覧'!$B:$B=$B59))"),2072.0) -> 2072
C62: =IFERROR(__xludf.DUMMYFUNCTION("FILTER('配当金履歴一覧'!$G:$G,('配当金履歴一覧'!$C:$C=C59)*('配当金履歴一覧'!$B:$B=$B59))"),0.0) -> 0 | D62: =IFERROR(__xludf.DUMMYFUNCTION("FILTER('配当金履歴一覧'!$H:$H,('配当金履歴一覧'!$C:$C=C59)*('配当金履歴一覧'!$B:$B=$B59))"),0.0) -> 0 | E62: =IFERROR(__xludf.DUMMYFUNCTION("FILTER('配当金履歴一覧'!$G:$G,('配当金履歴一覧'!$C:$C=E59)*('配当金履歴一覧'!$B:$B=$B59))"),3.0) -> 3 | F62: =IFERROR(__xludf.DUMMYFUNCTION("FILTER('配当金履歴一覧'!$H:$H,('配当金履歴一覧'!$C:$C=E59)*('配当金履歴一覧'!$B:$B=$B59))"),294.0) -> 294 | G62: =IFERROR(__xludf.DUMMYFUNCTION("FILTER('配当金履歴一覧'!$G:$G,('配当金履歴一覧'!$C:$C=G59)*('配当金履歴一覧'!$B:$B=$B59))"),5.0) -> 5 | H62: =IFERROR(__xludf.DUMMYFUNCTION("FILTER('配当金履歴一覧'!$H:$H,('配当金履歴一覧'!$C:$C=G59)*('配当金履歴一覧'!$B:$B=$B59))"),490.0) -> 490 | I62: =IFERROR(__xludf.DUMMYFUNCTION("FILTER('配当金履歴一覧'!$G:$G,('配当金履歴一覧'!$C:$C=I59)*('配当金履歴一覧'!$B:$B=$B59))"),7.0) -> 7 | J62: =IFERROR(__xludf.DUMMYFUNCTION("FILTER('配当金履歴一覧'!$H:$H,('配当金履歴一覧'!$C:$C=I59)*('配当金履歴一覧'!$B:$B=$B59))"),700.0) -> 700
A63: 5020 | B63: ENEOSホールディングス | C63: 45444 | E63: 45597 | G63: 45809 | I63: 45992
C64: =IFERROR(__xludf.DUMMYFUNCTION("FILTER('配当金履歴一覧'!$D:$D,('配当金履歴一覧'!$C:$C=C63)*('配当金履歴一覧'!$B:$B=$B63))"),11.0) -> 11 | E64: =IFERROR(__xludf.DUMMYFUNCTION("FILTER('配当金履歴一覧'!$D:$D,('配当金履歴一覧'!$C:$C=E63)*('配当金履歴一覧'!$B:$B=$B63))"),13.0) -> 13 | G64: =IFERROR(__xludf.DUMMYFUNCTION("FILTER('配当金履歴一覧'!$D:$D,('配当金履歴一覧'!$C:$C=G63)*('配当金履歴一覧'!$B:$B=$B63))"),13.0) -> 13 | I64: =IFERROR(__xludf.DUMMYFUNCTION("FILTER('配当金履歴一覧'!$D:$D,('配当金履歴一覧'!$C:$C=I63)*('配当金履歴一覧'!$B:$B=$B63))"),17.0) -> 17
C65: =IFERROR(__xludf.DUMMYFUNCTION("FILTER('配当金履歴一覧'!$G:$G,('配当金履歴一覧'!$C:$C=C63)*('配当金履歴一覧'!$B:$B=$B63))"),2.0) -> 2 | D65: =IFERROR(__xludf.DUMMYFUNCTION("FILTER('配当金履歴一覧'!$H:$H,('配当金履歴一覧'!$C:$C=C63)*('配当金履歴一覧'!$B:$B=$B63))"),22.0) -> 22 | E65: =IFERROR(__xludf.DUMMYFUNCTION("FILTER('配当金履歴一覧'!$G:$G,('配当金履歴一覧'!$C:$C=E63)*('配当金履歴一覧'!$B:$B=$B63))"),4.0) -> 4 | F65: =IFERROR(__xludf.DUMMYFUNCTION("FILTER('配当金履歴一覧'!$H:$H,('配当金履歴一覧'!$C:$C=E63)*('配当金履歴一覧'!$B:$B=$B63))"),52.0) -> 52 | G65: =IFERROR(__xludf.DUMMYFUNCTION("FILTER('配当金履歴一覧'!$G:$G,('配当金履歴一覧'!$C:$C=G63)*('配当金履歴一覧'!$B:$B=$B63))"),4.0) -> 4 | H65: =IFERROR(__xludf.DUMMYFUNCTION("FILTER('配当金履歴一覧'!$H:$H,('配当金履歴一覧'!$C:$C=G63)*('配当金履歴一覧'!$B:$B=$B63))"),52.0) -> 52 | I65: =IFERROR(__xludf.DUMMYFUNCTION("FILTER('配当金履歴一覧'!$G:$G,('配当金履歴一覧'!$C:$C=I63)*('配当金履歴一覧'!$B:$B=$B63))"),14.0) -> 14 | J65: =IFERROR(__xludf.DUMMYFUNCTION("FILTER('配当金履歴一覧'!$H:$H,('配当金履歴一覧'!$C:$C=I63)*('配当金履歴一覧'!$B:$B=$B63))"),238.0) -> 238
A66: 5108 | B66: ブリヂストン | C66: 45901
C67: =IFERROR(__xludf.DUMMYFUNCTION("FILTER('配当金履歴一覧'!$D:$D,('配当金履歴一覧'!$C:$C=C66)*('配当金履歴一覧'!$B:$B=$B66))"),115.0) -> 115
C68: =IFERROR(__xludf.DUMMYFUNCTION("FILTER('配当金履歴一覧'!$G:$G,('配当金履歴一覧'!$C:$C=C66)*('配当金履歴一覧'!$B:$B=$B66))"),4.0) -> 4 | D68: =IFERROR(__xludf.DUMMYFUNCTION("FILTER('配当金履歴一覧'!$H:$H,('配当金履歴一覧'!$C:$C=C66)*('配当金履歴一覧'!$B:$B=$B66))"),460.0) -> 460
A69: 5401 | B69: 日本製鉄
A72: 6301 | B72: 小松製作所 | C72: 45809 | E72: 45992
C73: =IFERROR(__xludf.DUMMYFUNCTION("FILTER('配当金履歴一覧'!$D:$D,('配当金履歴一覧'!$C:$C=C72)*('配当金履歴一覧'!$B:$B=$B72))"),107.0) -> 107 | E73: =IFERROR(__xludf.DUMMYFUNCTION("FILTER('配当金履歴一覧'!$D:$D,('配当金履歴一覧'!$C:$C=E72)*('配当金履歴一覧'!$B:$B=$B72))"),95.0) -> 95
C74: =IFERROR(__xludf.DUMMYFUNCTION("FILTER('配当金履歴一覧'!$G:$G,('配当金履歴一覧'!$C:$C=C72)*('配当金履歴一覧'!$B:$B=$B72))"),2.0) -> 2 | D74: =IFERROR(__xludf.DUMMYFUNCTION("FILTER('配当金履歴一覧'!$H:$H,('配当金履歴一覧'!$C:$C=C72)*('配当金履歴一覧'!$B:$B=$B72))"),214.0) -> 214 | E74: =IFERROR(__xludf.DUMMYFUNCTION("FILTER('配当金履歴一覧'!$G:$G,('配当金履歴一覧'!$C:$C=E72)*('配当金履歴一覧'!$B:$B=$B72))"),9.0) -> 9 | F74: =IFERROR(__xludf.DUMMYFUNCTION("FILTER('配当金履歴一覧'!$H:$H,('配当金履歴一覧'!$C:$C=E72)*('配当金履歴一覧'!$B:$B=$B72))"),855.0) -> 855
A75: 7177 | B75: GMOフィナンシャルホールディングス | C75: 45352 | E75: 45444 | G75: 45536 | I75: 45627 | K75: 45717 | M75: 45809 | O75: 45901 | Q75: 45992
C76: =IFERROR(__xludf.DUMMYFUNCTION("FILTER('配当金履歴一覧'!$D:$D,('配当金履歴一覧'!$C:$C=C75)*('配当金履歴一覧'!$B:$B=$B75))"),7.2) -> 7.2 | E76: =IFERROR(__xludf.DUMMYFUNCTION("FILTER('配当金履歴一覧'!$D:$D,('配当金履歴一覧'!$C:$C=E75)*('配当金履歴一覧'!$B:$B=$B75))"),11.87) -> 11.87 | G76: =IFERROR(__xludf.DUMMYFUNCTION("FILTER('配当金履歴一覧'!$D:$D,('配当金履歴一覧'!$C:$C=G75)*('配当金履歴一覧'!$B:$B=$B75))"),2.0) -> 2 | I76: =IFERROR(__xludf.DUMMYFUNCTION("FILTER('配当金履歴一覧'!$D:$D,('配当金履歴一覧'!$C:$C=I75)*('配当金履歴一覧'!$B:$B=$B75))"),8.27) -> 8.27 | K76: =IFERROR(__xludf.DUMMYFUNCTION("FILTER('配当金履歴一覧'!$D:$D,('配当金履歴一覧'!$C:$C=K75)*('配当金履歴一覧'!$B:$B=$B75))"),5.24) -> 5.24 | M76: =IFERROR(__xludf.DUMMYFUNCTION("FILTER('配当金履歴一覧'!$D:$D,('配当金履歴一覧'!$C:$C=M75)*('配当金履歴一覧'!$B:$B=$B75))"),13.8) -> 13.8 | O76: =IFERROR(__xludf.DUMMYFUNCTION("FILTER('配当金履歴一覧'!$D:$D,('配当金履歴一覧'!$C:$C=O75)*('配当金履歴一覧'!$B:$B=$B75))"),20.43) -> 20.43 | Q76: =IFERROR(__xludf.DUMMYFUNCTION("FILTER('配当金履歴一覧'!$D:$D,('配当金履歴一覧'!$C:$C=Q75)*('配当金履歴一覧'!$B:$B=$B75))"),14.87) -> 14.87
C77: =IFERROR(__xludf.DUMMYFUNCTION("FILTER('配当金履歴一覧'!$E:$E,('配当金履歴一覧'!$C:$C=C75)*('配当金履歴一覧'!$B:$B=$B75))"),20.0) -> 20 | D77: =IFERROR(__xludf.DUMMYFUNCTION("FILTER('配当金履歴一覧'!$F:$F,('配当金履歴一覧'!$C:$C=C75)*('配当金履歴一覧'!$B:$B=$B75))"),115.0) -> 115 | E77: =IFERROR(__xludf.DUMMYFUNCTION("FILTER('配当金履歴一覧'!$E:$E,('配当金履歴一覧'!$C:$C=E75)*('配当金履歴一覧'!$B:$B=$B75))"),0.0) -> 0 | F77: =IFERROR(__xludf.DUMMYFUNCTION("FILTER('配当金履歴一覧'!$F:$F,('配当金履歴一覧'!$C:$C=E75)*('配当金履歴一覧'!$B:$B=$B75))"),0.0) -> 0 | G77: =IFERROR(__xludf.DUMMYFUNCTION("FILTER('配当金履歴一覧'!$E:$E,('配当金履歴一覧'!$C:$C=G75)*('配当金履歴一覧'!$B:$B=$B75))"),0.0) -> 0 | H77: =IFERROR(__xludf.DUMMYFUNCTION("FILTER('配当金履歴一覧'!$F:$F,('配当金履歴一覧'!$C:$C=G75)*('配当金履歴一覧'!$B:$B=$B75))"),0.0) -> 0 | I77: =IFERROR(__xludf.DUMMYFUNCTION("FILTER('配当金履歴一覧'!$E:$E,('配当金履歴一覧'!$C:$C=I75)*('配当金履歴一覧'!$B:$B=$B75))"),0.0) -> 0 | J77: =IFERROR(__xludf.DUMMYFUNCTION("FILTER('配当金履歴一覧'!$F:$F,('配当金履歴一覧'!$C:$C=I75)*('配当金履歴一覧'!$B:$B=$B75))"),0.0) -> 0 | K77: =IFERROR(__xludf.DUMMYFUNCTION("FILTER('配当金履歴一覧'!$E:$E,('配当金履歴一覧'!$C:$C=K75)*('配当金履歴一覧'!$B:$B=$B75))"),0.0) -> 0 | L77: =IFERROR(__xludf.DUMMYFUNCTION("FILTER('配当金履歴一覧'!$F:$F,('配当金履歴一覧'!$C:$C=K75)*('配当金履歴一覧'!$B:$B=$B75))"),0.0) -> 0 | M77: =IFERROR(__xludf.DUMMYFUNCTION("FILTER('配当金履歴一覧'!$E:$E,('配当金履歴一覧'!$C:$C=M75)*('配当金履歴一覧'!$B:$B=$B75))"),0.0) -> 0 | N77: =IFERROR(__xludf.DUMMYFUNCTION("FILTER('配当金履歴一覧'!$F:$F,('配当金履歴一覧'!$C:$C=M75)*('配当金履歴一覧'!$B:$B=$B75))"),0.0) -> 0 | O77: =IFERROR(__xludf.DUMMYFUNCTION("FILTER('配当金履歴一覧'!$E:$E,('配当金履歴一覧'!$C:$C=O75)*('配当金履歴一覧'!$B:$B=$B75))"),0.0) -> 0 | P77: =IFERROR(__xludf.DUMMYFUNCTION("FILTER('配当金履歴一覧'!$F:$F,('配当金履歴一覧'!$C:$C=O75)*('配当金履歴一覧'!$B:$B=$B75))"),0.0) -> 0 | Q77: =IFERROR(__xludf.DUMMYFUNCTION("FILTER('配当金履歴一覧'!$E:$E,('配当金履歴一覧'!$C:$C=Q75)*('配当金履歴一覧'!$B:$B=$B75))"),0.0) -> 0 | R77: =IFERROR(__xludf.DUMMYFUNCTION("FILTER('配当金履歴一覧'!$F:$F,('配当金履歴一覧'!$C:$C=Q75)*('配当金履歴一覧'!$B:$B=$B75))"),0.0) -> 0
C78: =IFERROR(__xludf.DUMMYFUNCTION("FILTER('配当金履歴一覧'!$G:$G,('配当金履歴一覧'!$C:$C=C75)*('配当金履歴一覧'!$B:$B=$B75))"),0.0) -> 0 | D78: =IFERROR(__xludf.DUMMYFUNCTION("FILTER('配当金履歴一覧'!$H:$H,('配当金履歴一覧'!$C:$C=C75)*('配当金履歴一覧'!$B:$B=$B75))"),0.0) -> 0 | E78: =IFERROR(__xludf.DUMMYFUNCTION("FILTER('配当金履歴一覧'!$G:$G,('配当金履歴一覧'!$C:$C=E75)*('配当金履歴一覧'!$B:$B=$B75))"),20.0) -> 20 | F78: =IFERROR(__xludf.DUMMYFUNCTION("FILTER('配当金履歴一覧'!$H:$H,('配当金履歴一覧'!$C:$C=E75)*('配当金履歴一覧'!$B:$B=$B75))"),238.0) -> 238 | G78: =IFERROR(__xludf.DUMMYFUNCTION("FILTER('配当金履歴一覧'!$G:$G,('配当金履歴一覧'!$C:$C=G75)*('配当金履歴一覧'!$B:$B=$B75))"),20.0) -> 20 | H78: =IFERROR(__xludf.DUMMYFUNCTION("FILTER('配当金履歴一覧'!$H:$H,('配当金履歴一覧'!$C:$C=G75)*('配当金履歴一覧'!$B:$B=$B75))"),40.0) -> 40 | I78: =IFERROR(__xludf.DUMMYFUNCTION("FILTER('配当金履歴一覧'!$G:$G,('配当金履歴一覧'!$C:$C=I75)*('配当金履歴一覧'!$B:$B=$B75))"),20.0) -> 20 | J78: =IFERROR(__xludf.DUMMYFUNCTION("FILTER('配当金履歴一覧'!$H:$H,('配当金履歴一覧'!$C:$C=I75)*('配当金履歴一覧'!$B:$B=$B75))"),166.0) -> 166 | K78: =IFERROR(__xludf.DUMMYFUNCTION("FILTER('配当金履歴一覧'!$G:$G,('配当金履歴一覧'!$C:$C=K75)*('配当金履歴一覧'!$B:$B=$B75))"),20.0) -> 20 | L78: =IFERROR(__xludf.DUMMYFUNCTION("FILTER('配当金履歴一覧'!$H:$H,('配当金履歴一覧'!$C:$C=K75)*('配当金履歴一覧'!$B:$B=$B75))"),105.0) -> 105 | M78: =IFERROR(__xludf.DUMMYFUNCTION("FILTER('配当金履歴一覧'!$G:$G,('配当金履歴一覧'!$C:$C=M75)*('配当金履歴一覧'!$B:$B=$B75))"),20.0) -> 20 | N78: =IFERROR(__xludf.DUMMYFUNCTION("FILTER('配当金履歴一覧'!$H:$H,('配当金履歴一覧'!$C:$C=M75)*('配当金履歴一覧'!$B:$B=$B75))"),276.0) -> 276 | O78: =IFERROR(__xludf.DUMMYFUNCTION("FILTER('配当金履歴一覧'!$G:$G,('配当金履歴一覧'!$C:$C=O75)*('配当金履歴一覧'!$B:$B=$B75))"),20.0) -> 20 | P78: =IFERROR(__xludf.DUMMYFUNCTION("FILTER('配当金履歴一覧'!$H:$H,('配当金履歴一覧'!$C:$C=O75)*('配当金履歴一覧'!$B:$B=$B75))"),409.0) -> 409 | Q78: =IFERROR(__xludf.DUMMYFUNCTION("FILTER('配当金履歴一覧'!$G:$G,('配当金履歴一覧'!$C:$C=Q75)*('配当金履歴一覧'!$B:$B=$B75))"),20.0) -> 20 | R78: =IFERROR(__xludf.DUMMYFUNCTION("FILTER('配当金履歴一覧'!$H:$H,('配当金履歴一覧'!$C:$C=Q75)*('配当金履歴一覧'!$B:$B=$B75))"),298.0) -> 298
A79: 7751 | B79: キヤノン | C79: 45352 | E79: 45505 | G79: 45717 | I79: 45870
C80: =IFERROR(__xludf.DUMMYFUNCTION("FILTER('配当金履歴一覧'!$D:$D,('配当金履歴一覧'!$C:$C=C79)*('配当金履歴一覧'!$B:$B=$B79))"),70.0) -> 70 | E80: =IFERROR(__xludf.DUMMYFUNCTION("FILTER('配当金履歴一覧'!$D:$D,('配当金履歴一覧'!$C:$C=E79)*('配当金履歴一覧'!$B:$B=$B79))"),75.0) -> 75 | G80: =IFERROR(__xludf.DUMMYFUNCTION("FILTER('配当金履歴一覧'!$D:$D,('配当金履歴一覧'!$C:$C=G79)*('配当金履歴一覧'!$B:$B=$B79))"),80.0) -> 80 | I80: =IFERROR(__xludf.DUMMYFUNCTION("FILTER('配当金履歴一覧'!$D:$D,('配当金履歴一覧'!$C:$C=I79)*('配当金履歴一覧'!$B:$B=$B79))"),80.0) -> 80
C81: =IFERROR(__xludf.DUMMYFUNCTION("FILTER('配当金履歴一覧'!$E:$E,('配当金履歴一覧'!$C:$C=C79)*('配当金履歴一覧'!$B:$B=$B79))"),2.0) -> 2 | D81: =IFERROR(__xludf.DUMMYFUNCTION("FILTER('配当金履歴一覧'!$F:$F,('配当金履歴一覧'!$C:$C=C79)*('配当金履歴一覧'!$B:$B=$B79))"),112.0) -> 112 | E81: =IFERROR(__xludf.DUMMYFUNCTION("FILTER('配当金履歴一覧'!$E:$E,('配当金履歴一覧'!$C:$C=E79)*('配当金履歴一覧'!$B:$B=$B79))"),2.0) -> 2 | F81: =IFERROR(__xludf.DUMMYFUNCTION("FILTER('配当金履歴一覧'!$F:$F,('配当金履歴一覧'!$C:$C=E79)*('配当金履歴一覧'!$B:$B=$B79))"),121.0) -> 121 | G81: =IFERROR(__xludf.DUMMYFUNCTION("FILTER('配当金履歴一覧'!$E:$E,('配当金履歴一覧'!$C:$C=G79)*('配当金履歴一覧'!$B:$B=$B79))"),2.0) -> 2 | H81: =IFERROR(__xludf.DUMMYFUNCTION("FILTER('配当金履歴一覧'!$F:$F,('配当金履歴一覧'!$C:$C=G79)*('配当金履歴一覧'!$B:$B=$B79))"),128.0) -> 128 | I81: =IFERROR(__xludf.DUMMYFUNCTION("FILTER('配当金履歴一覧'!$E:$E,('配当金履歴一覧'!$C:$C=I79)*('配当金履歴一覧'!$B:$B=$B79))"),2.0) -> 2 | J81: =IFERROR(__xludf.DUMMYFUNCTION("FILTER('配当金履歴一覧'!$F:$F,('配当金履歴一覧'!$C:$C=I79)*('配当金履歴一覧'!$B:$B=$B79))"),128.0) -> 128
C82: =IFERROR(__xludf.DUMMYFUNCTION("FILTER('配当金履歴一覧'!$G:$G,('配当金履歴一覧'!$C:$C=C79)*('配当金履歴一覧'!$B:$B=$B79))"),0.0) -> 0 | D82: =IFERROR(__xludf.DUMMYFUNCTION("FILTER('配当金履歴一覧'!$H:$H,('配当金履歴一覧'!$C:$C=C79)*('配当金履歴一覧'!$B:$B=$B79))"),0.0) -> 0 | E82: =IFERROR(__xludf.DUMMYFUNCTION("FILTER('配当金履歴一覧'!$G:$G,('配当金履歴一覧'!$C:$C=E79)*('配当金履歴一覧'!$B:$B=$B79))"),3.0) -> 3 | F82: =IFERROR(__xludf.DUMMYFUNCTION("FILTER('配当金履歴一覧'!$H:$H,('配当金履歴一覧'!$C:$C=E79)*('配当金履歴一覧'!$B:$B=$B79))"),225.0) -> 225 | G82: =IFERROR(__xludf.DUMMYFUNCTION("FILTER('配当金履歴一覧'!$G:$G,('配当金履歴一覧'!$C:$C=G79)*('配当金履歴一覧'!$B:$B=$B79))"),3.0) -> 3 | H82: =IFERROR(__xludf.DUMMYFUNCTION("FILTER('配当金履歴一覧'!$H:$H,('配当金履歴一覧'!$C:$C=G79)*('配当金履歴一覧'!$B:$B=$B79))"),240.0) -> 240 | I82: =IFERROR(__xludf.DUMMYFUNCTION("FILTER('配当金履歴一覧'!$G:$G,('配当金履歴一覧'!$C:$C=I79)*('配当金履歴一覧'!$B:$B=$B79))"),5.0) -> 5 | J82: =IFERROR(__xludf.DUMMYFUNCTION("FILTER('配当金履歴一覧'!$H:$H,('配当金履歴一覧'!$C:$C=I79)*('配当金履歴一覧'!$B:$B=$B79))"),400.0) -> 400
A83: 8001 | B83: 伊藤忠商事 | C83: 45444 | E83: 45627 | G83: 45809 | I83: 45992
C84: =IFERROR(__xludf.DUMMYFUNCTION("FILTER('配当金履歴一覧'!$D:$D,('配当金履歴一覧'!$C:$C=C83)*('配当金履歴一覧'!$B:$B=$B83))"),80.0) -> 80 | E84: =IFERROR(__xludf.DUMMYFUNCTION("FILTER('配当金履歴一覧'!$D:$D,('配当金履歴一覧'!$C:$C=E83)*('配当金履歴一覧'!$B:$B=$B83))"),100.0) -> 100 | G84: =IFERROR(__xludf.DUMMYFUNCTION("FILTER('配当金履歴一覧'!$D:$D,('配当金履歴一覧'!$C:$C=G83)*('配当金履歴一覧'!$B:$B=$B83))"),100.0) -> 100 | I84: =IFERROR(__xludf.DUMMYFUNCTION("FILTER('配当金履歴一覧'!$D:$D,('配当金履歴一覧'!$C:$C=I83)*('配当金履歴一覧'!$B:$B=$B83))"),100.0) -> 100
C85: =IFERROR(__xludf.DUMMYFUNCTION("FILTER('配当金履歴一覧'!$E:$E,('配当金履歴一覧'!$C:$C=C83)*('配当金履歴一覧'!$B:$B=$B83))"),6.0) -> 6 | D85: =IFERROR(__xludf.DUMMYFUNCTION("FILTER('配当金履歴一覧'!$F:$F,('配当金履歴一覧'!$C:$C=C83)*('配当金履歴一覧'!$B:$B=$B83))"),383.0) -> 383 | E85: =IFERROR(__xludf.DUMMYFUNCTION("FILTER('配当金履歴一覧'!$E:$E,('配当金履歴一覧'!$C:$C=E83)*('配当金履歴一覧'!$B:$B=$B83))"),6.0) -> 6 | F85: =IFERROR(__xludf.DUMMYFUNCTION("FILTER('配当金履歴一覧'!$F:$F,('配当金履歴一覧'!$C:$C=E83)*('配当金履歴一覧'!$B:$B=$B83))"),479.0) -> 479 | G85: =IFERROR(__xludf.DUMMYFUNCTION("FILTER('配当金履歴一覧'!$E:$E,('配当金履歴一覧'!$C:$C=G83)*('配当金履歴一覧'!$B:$B=$B83))"),6.0) -> 6 | H85: =IFERROR(__xludf.DUMMYFUNCTION("FILTER('配当金履歴一覧'!$F:$F,('配当金履歴一覧'!$C:$C=G83)*('配当金履歴一覧'!$B:$B=$B83))"),479.0) -> 479 | I85: =IFERROR(__xludf.DUMMYFUNCTION("FILTER('配当金履歴一覧'!$E:$E,('配当金履歴一覧'!$C:$C=I83)*('配当金履歴一覧'!$B:$B=$B83))"),6.0) -> 6 | J85: =IFERROR(__xludf.DUMMYFUNCTION("FILTER('配当金履歴一覧'!$F:$F,('配当金履歴一覧'!$C:$C=I83)*('配当金履歴一覧'!$B:$B=$B83))"),479.0) -> 479
C86: =IFERROR(__xludf.DUMMYFUNCTION("FILTER('配当金履歴一覧'!$G:$G,('配当金履歴一覧'!$C:$C=C83)*('配当金履歴一覧'!$B:$B=$B83))"),0.0) -> 0 | D86: =IFERROR(__xludf.DUMMYFUNCTION("FILTER('配当金履歴一覧'!$H:$H,('配当金履歴一覧'!$C:$C=C83)*('配当金履歴一覧'!$B:$B=$B83))"),0.0) -> 0 | E86: =IFERROR(__xludf.DUMMYFUNCTION("FILTER('配当金履歴一覧'!$G:$G,('配当金履歴一覧'!$C:$C=E83)*('配当金履歴一覧'!$B:$B=$B83))"),1.0) -> 1 | F86: =IFERROR(__xludf.DUMMYFUNCTION("FILTER('配当金履歴一覧'!$H:$H,('配当金履歴一覧'!$C:$C=E83)*('配当金履歴一覧'!$B:$B=$B83))"),100.0) -> 100 | G86: =IFERROR(__xludf.DUMMYFUNCTION("FILTER('配当金履歴一覧'!$G:$G,('配当金履歴一覧'!$C:$C=G83)*('配当金履歴一覧'!$B:$B=$B83))"),3.0) -> 3 | H86: =IFERROR(__xludf.DUMMYFUNCTION("FILTER('配当金履歴一覧'!$H:$H,('配当金履歴一覧'!$C:$C=G83)*('配当金履歴一覧'!$B:$B=$B83))"),300.0) -> 300 | I86: =IFERROR(__xludf.DUMMYFUNCTION("FILTER('配当金履歴一覧'!$G:$G,('配当金履歴一覧'!$C:$C=I83)*('配当金履歴一覧'!$B:$B=$B83))"),3.0) -> 3 | J86: =IFERROR(__xludf.DUMMYFUNCTION("FILTER('配当金履歴一覧'!$H:$H,('配当金履歴一覧'!$C:$C=I83)*('配当金履歴一覧'!$B:$B=$B83))"),300.0) -> 300
A87: 8002 | B87: 丸紅 | C87: 45444 | E87: 45627 | G87: 45809 | I87: 45992
C88: =IFERROR(__xludf.DUMMYFUNCTION("FILTER('配当金履歴一覧'!$D:$D,('配当金履歴一覧'!$C:$C=C87)*('配当金履歴一覧'!$B:$B=$B87))"),43.5) -> 43.5 | E88: =IFERROR(__xludf.DUMMYFUNCTION("FILTER('配当金履歴一覧'!$D:$D,('配当金履歴一覧'!$C:$C=E87)*('配当金履歴一覧'!$B:$B=$B87))"),45.0) -> 45 | G88: =IFERROR(__xludf.DUMMYFUNCTION("FILTER('配当金履歴一覧'!$D:$D,('配当金履歴一覧'!$C:$C=G87)*('配当金履歴一覧'!$B:$B=$B87))"),50.0) -> 50 | I88: =IFERROR(__xludf.DUMMYFUNCTION("FILTER('配当金履歴一覧'!$D:$D,('配当金履歴一覧'!$C:$C=I87)*('配当金履歴一覧'!$B:$B=$B87))"),50.0) -> 50
C89: =IFERROR(__xludf.DUMMYFUNCTION("FILTER('配当金履歴一覧'!$E:$E,('配当金履歴一覧'!$C:$C=C87)*('配当金履歴一覧'!$B:$B=$B87))"),9.0) -> 9 | D89: =IFERROR(__xludf.DUMMYFUNCTION("FILTER('配当金履歴一覧'!$F:$F,('配当金履歴一覧'!$C:$C=C87)*('配当金履歴一覧'!$B:$B=$B87))"),313.0) -> 313 | E89: =IFERROR(__xludf.DUMMYFUNCTION("FILTER('配当金履歴一覧'!$E:$E,('配当金履歴一覧'!$C:$C=E87)*('配当金履歴一覧'!$B:$B=$B87))"),9.0) -> 9 | F89: =IFERROR(__xludf.DUMMYFUNCTION("FILTER('配当金履歴一覧'!$F:$F,('配当金履歴一覧'!$C:$C=E87)*('配当金履歴一覧'!$B:$B=$B87))"),323.0) -> 323 | G89: =IFERROR(__xludf.DUMMYFUNCTION("FILTER('配当金履歴一覧'!$E:$E,('配当金履歴一覧'!$C:$C=G87)*('配当金履歴一覧'!$B:$B=$B87))"),9.0) -> 9 | H89: =IFERROR(__xludf.DUMMYFUNCTION("FILTER('配当金履歴一覧'!$F:$F,('配当金履歴一覧'!$C:$C=G87)*('配当金履歴一覧'!$B:$B=$B87))"),360.0) -> 360 | I89: =IFERROR(__xludf.DUMMYFUNCTION("FILTER('配当金履歴一覧'!$E:$E,('配当金履歴一覧'!$C:$C=I87)*('配当金履歴一覧'!$B:$B=$B87))"),9.0) -> 9 | J89: =IFERROR(__xludf.DUMMYFUNCTION("FILTER('配当金履歴一覧'!$F:$F,('配当金履歴一覧'!$C:$C=I87)*('配当金履歴一覧'!$B:$B=$B87))"),360.0) -> 360
C90: =IFERROR(__xludf.DUMMYFUNCTION("FILTER('配当金履歴一覧'!$G:$G,('配当金履歴一覧'!$C:$C=C87)*('配当金履歴一覧'!$B:$B=$B87))"),3.0) -> 3 | D90: =IFERROR(__xludf.DUMMYFUNCTION("FILTER('配当金履歴一覧'!$H:$H,('配当金履歴一覧'!$C:$C=C87)*('配当金履歴一覧'!$B:$B=$B87))"),131.0) -> 131 | E90: =IFERROR(__xludf.DUMMYFUNCTION("FILTER('配当金履歴一覧'!$G:$G,('配当金履歴一覧'!$C:$C=E87)*('配当金履歴一覧'!$B:$B=$B87))"),5.0) -> 5 | F90: =IFERROR(__xludf.DUMMYFUNCTION("FILTER('配当金履歴一覧'!$H:$H,('配当金履歴一覧'!$C:$C=E87)*('配当金履歴一覧'!$B:$B=$B87))"),225.0) -> 225 | G90: =IFERROR(__xludf.DUMMYFUNCTION("FILTER('配当金履歴一覧'!$G:$G,('配当金履歴一覧'!$C:$C=G87)*('配当金履歴一覧'!$B:$B=$B87))"),7.0) -> 7 | H90: =IFERROR(__xludf.DUMMYFUNCTION("FILTER('配当金履歴一覧'!$H:$H,('配当金履歴一覧'!$C:$C=G87)*('配当金履歴一覧'!$B:$B=$B87))"),350.0) -> 350 | I90: =IFERROR(__xludf.DUMMYFUNCTION("FILTER('配当金履歴一覧'!$G:$G,('配当金履歴一覧'!$C:$C=I87)*('配当金履歴一覧'!$B:$B=$B87))"),9.0) -> 9 | J90: =IFERROR(__xludf.DUMMYFUNCTION("FILTER('配当金履歴一覧'!$H:$H,('配当金履歴一覧'!$C:$C=I87)*('配当金履歴一覧'!$B:$B=$B87))"),450.0) -> 450
A91: 8031 | B91: 三井物産 | C91: 45444 | E91: 45627 | G91: 45809 | I91: 45992
C92: =IFERROR(__xludf.DUMMYFUNCTION("FILTER('配当金履歴一覧'!$D:$D,('配当金履歴一覧'!$C:$C=C91)*('配当金履歴一覧'!$B:$B=$B91))"),85.0) -> 85 | E92: =IFERROR(__xludf.DUMMYFUNCTION("FILTER('配当金履歴一覧'!$D:$D,('配当金履歴一覧'!$C:$C=E91)*('配当金履歴一覧'!$B:$B=$B91))"),50.0) -> 50 | G92: =IFERROR(__xludf.DUMMYFUNCTION("FILTER('配当金履歴一覧'!$D:$D,('配当金履歴一覧'!$C:$C=G91)*('配当金履歴一覧'!$B:$B=$B91))"),50.0) -> 50 | I92: =IFERROR(__xludf.DUMMYFUNCTION("FILTER('配当金履歴一覧'!$D:$D,('配当金履歴一覧'!$C:$C=I91)*('配当金履歴一覧'!$B:$B=$B91))"),55.0) -> 55
C93: =IFERROR(__xludf.DUMMYFUNCTION("FILTER('配当金履歴一覧'!$E:$E,('配当金履歴一覧'!$C:$C=C91)*('配当金履歴一覧'!$B:$B=$B91))"),12.0) -> 12 | D93: =IFERROR(__xludf.DUMMYFUNCTION("FILTER('配当金履歴一覧'!$F:$F,('配当金履歴一覧'!$C:$C=C91)*('配当金履歴一覧'!$B:$B=$B91))"),813.0) -> 813 | E93: =IFERROR(__xludf.DUMMYFUNCTION("FILTER('配当金履歴一覧'!$E:$E,('配当金履歴一覧'!$C:$C=E91)*('配当金履歴一覧'!$B:$B=$B91))"),24.0) -> 24 | F93: =IFERROR(__xludf.DUMMYFUNCTION("FILTER('配当金履歴一覧'!$F:$F,('配当金履歴一覧'!$C:$C=E91)*('配当金履歴一覧'!$B:$B=$B91))"),957.0) -> 957 | G93: =IFERROR(__xludf.DUMMYFUNCTION("FILTER('配当金履歴一覧'!$E:$E,('配当金履歴一覧'!$C:$C=G91)*('配当金履歴一覧'!$B:$B=$B91))"),24.0) -> 24 | H93: =IFERROR(__xludf.DUMMYFUNCTION("FILTER('配当金履歴一覧'!$F:$F,('配当金履歴一覧'!$C:$C=G91)*('配当金履歴一覧'!$B:$B=$B91))"),957.0) -> 957 | I93: =IFERROR(__xludf.DUMMYFUNCTION("FILTER('配当金履歴一覧'!$E:$E,('配当金履歴一覧'!$C:$C=I91)*('配当金履歴一覧'!$B:$B=$B91))"),24.0) -> 24 | J93: =IFERROR(__xludf.DUMMYFUNCTION("FILTER('配当金履歴一覧'!$F:$F,('配当金履歴一覧'!$C:$C=I91)*('配当金履歴一覧'!$B:$B=$B91))"),1052.0) -> 1052
C94: =IFERROR(__xludf.DUMMYFUNCTION("FILTER('配当金履歴一覧'!$G:$G,('配当金履歴一覧'!$C:$C=C91)*('配当金履歴一覧'!$B:$B=$B91))"),1.0) -> 1 | D94: =IFERROR(__xludf.DUMMYFUNCTION("FILTER('配当金履歴一覧'!$H:$H,('配当金履歴一覧'!$C:$C=C91)*('配当金履歴一覧'!$B:$B=$B91))"),85.0) -> 85 | E94: =IFERROR(__xludf.DUMMYFUNCTION("FILTER('配当金履歴一覧'!$G:$G,('配当金履歴一覧'!$C:$C=E91)*('配当金履歴一覧'!$B:$B=$B91))"),3.0) -> 3 | F94: =IFERROR(__xludf.DUMMYFUNCTION("FILTER('配当金履歴一覧'!$H:$H,('配当金履歴一覧'!$C:$C=E91)*('配当金履歴一覧'!$B:$B=$B91))"),150.0) -> 150 | G94: =IFERROR(__xludf.DUMMYFUNCTION("FILTER('配当金履歴一覧'!$G:$G,('配当金履歴一覧'!$C:$C=G91)*('配当金履歴一覧'!$B:$B=$B91))"),6.0) -> 6 | H94: =IFERROR(__xludf.DUMMYFUNCTION("FILTER('配当金履歴一覧'!$H:$H,('配当金履歴一覧'!$C:$C=G91)*('配当金履歴一覧'!$B:$B=$B91))"),300.0) -> 300 | I94: =IFERROR(__xludf.DUMMYFUNCTION("FILTER('配当金履歴一覧'!$G:$G,('配当金履歴一覧'!$C:$C=I91)*('配当金履歴一覧'!$B:$B=$B91))"),7.0) -> 7 | J94: =IFERROR(__xludf.DUMMYFUNCTION("FILTER('配当金履歴一覧'!$H:$H,('配当金履歴一覧'!$C:$C=I91)*('配当金履歴一覧'!$B:$B=$B91))"),385.0) -> 385
A95: 8053 | B95: 住友商事 | C95: 45444 | E95: 45627 | G95: 45809 | I95: 45992
C96: =IFERROR(__xludf.DUMMYFUNCTION("FILTER('配当金履歴一覧'!$D:$D,('配当金履歴一覧'!$C:$C=C95)*('配当金履歴一覧'!$B:$B=$B95))"),62.5) -> 62.5 | E96: =IFERROR(__xludf.DUMMYFUNCTION("FILTER('配当金履歴一覧'!$D:$D,('配当金履歴一覧'!$C:$C=E95)*('配当金履歴一覧'!$B:$B=$B95))"),65.0) -> 65 | G96: =IFERROR(__xludf.DUMMYFUNCTION("FILTER('配当金履歴一覧'!$D:$D,('配当金履歴一覧'!$C:$C=G95)*('配当金履歴一覧'!$B:$B=$B95))"),65.0) -> 65 | I96: =IFERROR(__xludf.DUMMYFUNCTION("FILTER('配当金履歴一覧'!$D:$D,('配当金履歴一覧'!$C:$C=I95)*('配当金履歴一覧'!$B:$B=$B95))"),70.0) -> 70
C97: =IFERROR(__xludf.DUMMYFUNCTION("FILTER('配当金履歴一覧'!$E:$E,('配当金履歴一覧'!$C:$C=C95)*('配当金履歴一覧'!$B:$B=$B95))"),9.0) -> 9 | D97: =IFERROR(__xludf.DUMMYFUNCTION("FILTER('配当金履歴一覧'!$F:$F,('配当金履歴一覧'!$C:$C=C95)*('配当金履歴一覧'!$B:$B=$B95))"),448.0) -> 448 | E97: =IFERROR(__xludf.DUMMYFUNCTION("FILTER('配当金履歴一覧'!$E:$E,('配当金履歴一覧'!$C:$C=E95)*('配当金履歴一覧'!$B:$B=$B95))"),9.0) -> 9 | F97: =IFERROR(__xludf.DUMMYFUNCTION("FILTER('配当金履歴一覧'!$F:$F,('配当金履歴一覧'!$C:$C=E95)*('配当金履歴一覧'!$B:$B=$B95))"),467.0) -> 467 | G97: =IFERROR(__xludf.DUMMYFUNCTION("FILTER('配当金履歴一覧'!$E:$E,('配当金履歴一覧'!$C:$C=G95)*('配当金履歴一覧'!$B:$B=$B95))"),9.0) -> 9 | H97: =IFERROR(__xludf.DUMMYFUNCTION("FILTER('配当金履歴一覧'!$F:$F,('配当金履歴一覧'!$C:$C=G95)*('配当金履歴一覧'!$B:$B=$B95))"),467.0) -> 467 | I97: =IFERROR(__xludf.DUMMYFUNCTION("FILTER('配当金履歴一覧'!$E:$E,('配当金履歴一覧'!$C:$C=I95)*('配当金履歴一覧'!$B:$B=$B95))"),9.0) -> 9 | J97: =IFERROR(__xludf.DUMMYFUNCTION("FILTER('配当金履歴一覧'!$F:$F,('配当金履歴一覧'!$C:$C=I95)*('配当金履歴一覧'!$B:$B=$B95))"),503.0) -> 503
C98: =IFERROR(__xludf.DUMMYFUNCTION("FILTER('配当金履歴一覧'!$G:$G,('配当金履歴一覧'!$C:$C=C95)*('配当金履歴一覧'!$B:$B=$B95))"),2.0) -> 2 | D98: =IFERROR(__xludf.DUMMYFUNCTION("FILTER('配当金履歴一覧'!$H:$H,('配当金履歴一覧'!$C:$C=C95)*('配当金履歴一覧'!$B:$B=$B95))"),125.0) -> 125 | E98: =IFERROR(__xludf.DUMMYFUNCTION("FILTER('配当金履歴一覧'!$G:$G,('配当金履歴一覧'!$C:$C=E95)*('配当金履歴一覧'!$B:$B=$B95))"),3.0) -> 3 | F98: =IFERROR(__xludf.DUMMYFUNCTION("FILTER('配当金履歴一覧'!$H:$H,('配当金履歴一覧'!$C:$C=E95)*('配当金履歴一覧'!$B:$B=$B95))"),195.0) -> 195 | G98: =IFERROR(__xludf.DUMMYFUNCTION("FILTER('配当金履歴一覧'!$G:$G,('配当金履歴一覧'!$C:$C=G95)*('配当金履歴一覧'!$B:$B=$B95))"),5.0) -> 5 | H98: =IFERROR(__xludf.DUMMYFUNCTION("FILTER('配当金履歴一覧'!$H:$H,('配当金履歴一覧'!$C:$C=G95)*('配当金履歴一覧'!$B:$B=$B95))"),325.0) -> 325 | I98: =IFERROR(__xludf.DUMMYFUNCTION("FILTER('配当金履歴一覧'!$G:$G,('配当金履歴一覧'!$C:$C=I95)*('配当金履歴一覧'!$B:$B=$B95))"),8.0) -> 8 | J98: =IFERROR(__xludf.DUMMYFUNCTION("FILTER('配当金履歴一覧'!$H:$H,('配当金履歴一覧'!$C:$C=I95)*('配当金履歴一覧'!$B:$B=$B95))"),560.0) -> 560
A99: 8058 | B99: 三菱商事 | C99: 45444 | E99: 45627 | G99: 45809 | I99: 45992
C100: =IFERROR(__xludf.DUMMYFUNCTION("FILTER('配当金履歴一覧'!$D:$D,('配当金履歴一覧'!$C:$C=C99)*('配当金履歴一覧'!$B:$B=$B99))"),35.0) -> 35 | E100: =IFERROR(__xludf.DUMMYFUNCTION("FILTER('配当金履歴一覧'!$D:$D,('配当金履歴一覧'!$C:$C=E99)*('配当金履歴一覧'!$B:$B=$B99))"),50.0) -> 50 | G100: =IFERROR(__xludf.DUMMYFUNCTION("FILTER('配当金履歴一覧'!$D:$D,('配当金履歴一覧'!$C:$C=G99)*('配当金履歴一覧'!$B:$B=$B99))"),50.0) -> 50 | I100: =IFERROR(__xludf.DUMMYFUNCTION("FILTER('配当金履歴一覧'!$D:$D,('配当金履歴一覧'!$C:$C=I99)*('配当金履歴一覧'!$B:$B=$B99))"),55.0) -> 55
C101: =IFERROR(__xludf.DUMMYFUNCTION("FILTER('配当金履歴一覧'!$E:$E,('配当金履歴一覧'!$C:$C=C99)*('配当金履歴一覧'!$B:$B=$B99))"),15.0) -> 15 | D101: =IFERROR(__xludf.DUMMYFUNCTION("FILTER('配当金履歴一覧'!$F:$F,('配当金履歴一覧'!$C:$C=C99)*('配当金履歴一覧'!$B:$B=$B99))"),419.0) -> 419 | E101: =IFERROR(__xludf.DUMMYFUNCTION("FILTER('配当金履歴一覧'!$E:$E,('配当金履歴一覧'!$C:$C=E99)*('配当金履歴一覧'!$B:$B=$B99))"),15.0) -> 15 | F101: =IFERROR(__xludf.DUMMYFUNCTION("FILTER('配当金履歴一覧'!$F:$F,('配当金履歴一覧'!$C:$C=E99)*('配当金履歴一覧'!$B:$B=$B99))"),599.0) -> 599 | G101: =IFERROR(__xludf.DUMMYFUNCTION("FILTER('配当金履歴一覧'!$E:$E,('配当金履歴一覧'!$C:$C=G99)*('配当金履歴一覧'!$B:$B=$B99))"),15.0) -> 15 | H101: =IFERROR(__xludf.DUMMYFUNCTION("FILTER('配当金履歴一覧'!$F:$F,('配当金履歴一覧'!$C:$C=G99)*('配当金履歴一覧'!$B:$B=$B99))"),599.0) -> 599 | I101: =IFERROR(__xludf.DUMMYFUNCTION("FILTER('配当金履歴一覧'!$E:$E,('配当金履歴一覧'!$C:$C=I99)*('配当金履歴一覧'!$B:$B=$B99))"),15.0) -> 15 | J101: =IFERROR(__xludf.DUMMYFUNCTION("FILTER('配当金履歴一覧'!$F:$F,('配当金履歴一覧'!$C:$C=I99)*('配当金履歴一覧'!$B:$B=$B99))"),658.0) -> 658
C102: =IFERROR(__xludf.DUMMYFUNCTION("FILTER('配当金履歴一覧'!$G:$G,('配当金履歴一覧'!$C:$C=C99)*('配当金履歴一覧'!$B:$B=$B99))"),0.0) -> 0 | D102: =IFERROR(__xludf.DUMMYFUNCTION("FILTER('配当金履歴一覧'!$H:$H,('配当金履歴一覧'!$C:$C=C99)*('配当金履歴一覧'!$B:$B=$B99))"),0.0) -> 0 | E102: =IFERROR(__xludf.DUMMYFUNCTION("FILTER('配当金履歴一覧'!$G:$G,('配当金履歴一覧'!$C:$C=E99)*('配当金履歴一覧'!$B:$B=$B99))"),0.0) -> 0 | F102: =IFERROR(__xludf.DUMMYFUNCTION("FILTER('配当金履歴一覧'!$H:$H,('配当金履歴一覧'!$C:$C=E99)*('配当金履歴一覧'!$B:$B=$B99))"),0.0) -> 0 | G102: =IFERROR(__xludf.DUMMYFUNCTION("FILTER('配当金履歴一覧'!$G:$G,('配当金履歴一覧'!$C:$C=G99)*('配当金履歴一覧'!$B:$B=$B99))"),6.0) -> 6 | H102: =IFERROR(__xludf.DUMMYFUNCTION("FILTER('配当金履歴一覧'!$H:$H,('配当金履歴一覧'!$C:$C=G99)*('配当金履歴一覧'!$B:$B=$B99))"),300.0) -> 300 | I102: =IFERROR(__xludf.DUMMYFUNCTION("FILTER('配当金履歴一覧'!$G:$G,('配当金履歴一覧'!$C:$C=I99)*('配当金履歴一覧'!$B:$B=$B99))"),9.0) -> 9 | J102: =IFERROR(__xludf.DUMMYFUNCTION("FILTER('配当金履歴一覧'!$H:$H,('配当金履歴一覧'!$C:$C=I99)*('配当金履歴一覧'!$B:$B=$B99))"),495.0) -> 495
A103: 8304 | B103: あおぞら銀行 | C103: 45536 | E103: 45627 | G103: 45717 | I103: 45809 | K103: 45901 | M103: 45992
C104: =IFERROR(__xludf.DUMMYFUNCTION("FILTER('配当金履歴一覧'!$D:$D,('配当金履歴一覧'!$C:$C=C103)*('配当金履歴一覧'!$B:$B=$B103))"),19.0) -> 19 | E104: =IFERROR(__xludf.DUMMYFUNCTION("FILTER('配当金履歴一覧'!$D:$D,('配当金履歴一覧'!$C:$C=E103)*('配当金履歴一覧'!$B:$B=$B103))"),19.0) -> 19 | G104: =IFERROR(__xludf.DUMMYFUNCTION("FILTER('配当金履歴一覧'!$D:$D,('配当金履歴一覧'!$C:$C=G103)*('配当金履歴一覧'!$B:$B=$B103))"),19.0) -> 19 | I104: =IFERROR(__xludf.DUMMYFUNCTION("FILTER('配当金履歴一覧'!$D:$D,('配当金履歴一覧'!$C:$C=I103)*('配当金履歴一覧'!$B:$B=$B103))"),22.0) -> 22 | K104: =IFERROR(__xludf.DUMMYFUNCTION("FILTER('配当金履歴一覧'!$D:$D,('配当金履歴一覧'!$C:$C=K103)*('配当金履歴一覧'!$B:$B=$B103))"),22.0) -> 22 | M104: =IFERROR(__xludf.DUMMYFUNCTION("FILTER('配当金履歴一覧'!$D:$D,('配当金履歴一覧'!$C:$C=M103)*('配当金履歴一覧'!$B:$B=$B103))"),22.0) -> 22
...

Sheet 年間配当金総額
A1: 2024年間配当金総額 | C1: 45292 | D1: 45323 | E1: 45352 | F1: 45383 | G1: 45413 | H1: 45444 | I1: 45474 | J1: 45505 | K1: 45536 | L1: 45566 | M1: 45597 | N1: 45627
A2: =SUM(B2:N2) -> 110785.3 | C2: =SUMIF('配当金履歴一覧'!$C:$C,C1,'配当金履歴一覧'!$F:$F)+SUMIF('配当金履歴一覧'!$C:$C,C1,'配当金履歴一覧'!$H:$H) -> 0 | D2: =SUMIF('配当金履歴一覧'!$C:$C,D1,'配当金履歴一覧'!$F:$F)+SUMIF('配当金履歴一覧'!$C:$C,D1,'配当金履歴一覧'!$H:$H) -> 0 | E2: =SUMIF('配当金履歴一覧'!$C:$C,E1,'配当金履歴一覧'!$F:$F)+SUMIF('配当金履歴一覧'!$C:$C,E1,'配当金履歴一覧'!$H:$H) -> 15187.3 | F2: =SUMIF('配当金履歴一覧'!$C:$C,F1,'配当金履歴一覧'!$F:$F)+SUMIF('配当金履歴一覧'!$C:$C,F1,'配当金履歴一覧'!$H:$H) -> 765 | G2: =SUMIF('配当金履歴一覧'!$C:$C,G1,'配当金履歴一覧'!$F:$F)+SUMIF('配当金履歴一覧'!$C:$C,G1,'配当金履歴一覧'!$H:$H) -> 0 | H2: =SUMIF('配当金履歴一覧'!$C:$C,H1,'配当金履歴一覧'!$F:$F)+SUMIF('配当金履歴一覧'!$C:$C,H1,'配当金履歴一覧'!$H:$H) -> 33569 | I2: =SUMIF('配当金履歴一覧'!$C:$C,I1,'配当金履歴一覧'!$F:$F)+SUMIF('配当金履歴一覧'!$C:$C,I1,'配当金履歴一覧'!$H:$H) -> 0 | J2: =SUMIF('配当金履歴一覧'!$C:$C,J1,'配当金履歴一覧'!$F:$F)+SUMIF('配当金履歴一覧'!$C:$C,J1,'配当金履歴一覧'!$H:$H) -> 346 | ... N2: =SUMIF('配当金履歴一覧'!$C:$C,N1,'配当金履歴一覧'!$F:$F)+SUMIF('配当金履歴一覧'!$C:$C,N1,'配当金履歴一覧'!$H:$H) -> 38962
A4: 2025年間配当金総額 | C4: 45658 | D4: 45689 | E4: 45717 | F4: 45748 | G4: 45778 | H4: 45809 | I4: 45839 | J4: 45870 | K4: 45901 | L4: 45931 | M4: 45962 | N4: 45992
A5: =SUM(B5:N5) -> 148195 | C5: =SUMIF('配当金履歴一覧'!$C:$C,C4,'配当金履歴一覧'!$F:$F)+SUMIF('配当金履歴一覧'!$C:$C,C4,'配当金履歴一覧'!$H:$H) -> 0 | D5: =SUMIF('配当金履歴一覧'!$C:$C,D4,'配当金履歴一覧'!$F:$F)+SUMIF('配当金履歴一覧'!$C:$C,D4,'配当金履歴一覧'!$H:$H) -> 0 | E5: =SUMIF('配当金履歴一覧'!$C:$C,E4,'配当金履歴一覧'!$F:$F)+SUMIF('配当金履歴一覧'!$C:$C,E4,'配当金履歴一覧'!$H:$H) -> 21710 | F5: =SUMIF('配当金履歴一覧'!$C:$C,F4,'配当金履歴一覧'!$F:$F)+SUMIF('配当金履歴一覧'!$C:$C,F4,'配当金履歴一覧'!$H:$H) -> 1133 | G5: =SUMIF('配当金履歴一覧'!$C:$C,G4,'配当金履歴一覧'!$F:$F)+SUMIF('配当金履歴一覧'!$C:$C,G4,'配当金履歴一覧'!$H:$H) -> 0 | H5: =SUMIF('配当金履歴一覧'!$C:$C,H4,'配当金履歴一覧'!$F:$F)+SUMIF('配当金履歴一覧'!$C:$C,H4,'配当金履歴一覧'!$H:$H) -> 42431 | I5: =SUMIF('配当金履歴一覧'!$C:$C,I4,'配当金履歴一覧'!$F:$F)+SUMIF('配当金履歴一覧'!$C:$C,I4,'配当金履歴一覧'!$H:$H) -> 1731 | J5: =SUMIF('配当金履歴一覧'!$C:$C,J4,'配当金履歴一覧'!$F:$F)+SUMIF('配当金履歴一覧'!$C:$C,J4,'配当金履歴一覧'!$H:$H) -> 528 | ... N5: =SUMIF('配当金履歴一覧'!$C:$C,N4,'配当金履歴一覧'!$F:$F)+SUMIF('配当金履歴一覧'!$C:$C,N4,'配当金履歴一覧'!$H:$H) -> 52154
A7: 2026年間配当金総額 | C7: 46023 | D7: 46054 | E7: 46082 | F7: 46113 | G7: 46143 | H7: 46174 | I7: 46204 | J7: 46235 | K7: 46266 | L7: 46296 | M7: 46327 | N7: 46357
A8: =SUM(B8:N8) -> 0 | C8: =SUMIF('配当金履歴一覧'!$C:$C,C7,'配当金履歴一覧'!$F:$F)+SUMIF('配当金履歴一覧'!$C:$C,C7,'配当金履歴一覧'!$H:$H) -> 0 | D8: =SUMIF('配当金履歴一覧'!$C:$C,D7,'配当金履歴一覧'!$F:$F)+SUMIF('配当金履歴一覧'!$C:$C,D7,'配当金履歴一覧'!$H:$H) -> 0 | E8: =SUMIF('配当金履歴一覧'!$C:$C,E7,'配当金履歴一覧'!$F:$F)+SUMIF('配当金履歴一覧'!$C:$C,E7,'配当金履歴一覧'!$H:$H) -> 0 | F8: =SUMIF('配当金履歴一覧'!$C:$C,F7,'配当金履歴一覧'!$F:$F)+SUMIF('配当金履歴一覧'!$C:$C,F7,'配当金履歴一覧'!$H:$H) -> 0 | G8: =SUMIF('配当金履歴一覧'!$C:$C,G7,'配当金履歴一覧'!$F:$F)+SUMIF('配当金履歴一覧'!$C:$C,G7,'配当金履歴一覧'!$H:$H) -> 0 | H8: =SUMIF('配当金履歴一覧'!$C:$C,H7,'配当金履歴一覧'!$F:$F)+SUMIF('配当金履歴一覧'!$C:$C,H7,'配当金履歴一覧'!$H:$H) -> 0 | I8: =SUMIF('配当金履歴一覧'!$C:$C,I7,'配当金履歴一覧'!$F:$F)+SUMIF('配当金履歴一覧'!$C:$C,I7,'配当金履歴一覧'!$H:$H) -> 0 | J8: =SUMIF('配当金履歴一覧'!$C:$C,J7,'配当金履歴一覧'!$F:$F)+SUMIF('配当金履歴一覧'!$C:$C,J7,'配当金履歴一覧'!$H:$H) -> 0 | ... N8: =SUMIF('配当金履歴一覧'!$C:$C,N7,'配当金履歴一覧'!$F:$F)+SUMIF('配当金履歴一覧'!$C:$C,N7,'配当金履歴一覧'!$H:$H) -> 0
A10: コード | B10: 銘柄名 | C10: 銘柄別年間配当金総額
C11: 2024年 | D11: 2025年 | E11: 2026年
A12: 米国株 | C12: =SUM(C14:C16) -> 69733.3 | D12: =SUM(D14:D16) -> 80052 | E12: =SUM(E14:E16) -> 0
A14: HDV | B14: iシェアーズ コア 米国高配当株 ETF | C14: =SUMIFS('配当金履歴一覧'!$F:F,'配当金履歴一覧'!$C:$C,">=2024/1",'配当金履歴一覧'!$C:$C,"<=2024/12",'配当金履歴一覧'!$B:$B,$B14)+SUMIFS('配当金履歴一覧'!$H:H,'配当金履歴一覧'!$C:$C,">=2024/1",'配当金履歴一覧'!$C:$C,"<=2024/12",'配当金履歴一覧'!$B:$B,$B14) -> 25852.3 | D14: =SUMIFS('配当金履歴一覧'!$F:F,'配当金履歴一覧'!$C:$C,">=2025/1",'配当金履歴一覧'!$C:$C,"<=2025/12",'配当金履歴一覧'!$B:$B,$B14)+SUMIFS('配当金履歴一覧'!$H:H,'配当金履歴一覧'!$C:$C,">=2025/1",'配当金履歴一覧'!$C:$C,"<=2025/12",'配当金履歴一覧'!$B:$B,$B14) -> 29898 | E14: =SUMIFS('配当金履歴一覧'!$F:F,'配当金履歴一覧'!$C:$C,">=2026/1",'配当金履歴一覧'!$C:$C,"<=2026/12",'配当金履歴一覧'!$B:$B,$B14)+SUMIFS('配当金履歴一覧'!$H:H,'配当金履歴一覧'!$C:$C,">=2026/1",'配当金履歴一覧'!$C:$C,"<=2026/12",'配当金履歴一覧'!$B:$B,$B14) -> 0
A15: VYM | B15: バンガード 米国高配当株式ETF | C15: =SUMIFS('配当金履歴一覧'!$F:F,'配当金履歴一覧'!$C:$C,">=2024/1",'配当金履歴一覧'!$C:$C,"<=2024/12",'配当金履歴一覧'!$B:$B,$B15)+SUMIFS('配当金履歴一覧'!$H:H,'配当金履歴一覧'!$C:$C,">=2024/1",'配当金履歴一覧'!$C:$C,"<=2024/12",'配当金履歴一覧'!$B:$B,$B15) -> 3441 | D15: =SUMIFS('配当金履歴一覧'!$F:F,'配当金履歴一覧'!$C:$C,">=2025/1",'配当金履歴一覧'!$C:$C,"<=2025/12",'配当金履歴一覧'!$B:$B,$B15)+SUMIFS('配当金履歴一覧'!$H:H,'配当金履歴一覧'!$C:$C,">=2025/1",'配当金履歴一覧'!$C:$C,"<=2025/12",'配当金履歴一覧'!$B:$B,$B15) -> 7820 | E15: =SUMIFS('配当金履歴一覧'!$F:F,'配当金履歴一覧'!$C:$C,">=2026/1",'配当金履歴一覧'!$C:$C,"<=2026/12",'配当金履歴一覧'!$B:$B,$B15)+SUMIFS('配当金履歴一覧'!$H:H,'配当金履歴一覧'!$C:$C,">=2026/1",'配当金履歴一覧'!$C:$C,"<=2026/12",'配当金履歴一覧'!$B:$B,$B15) -> 0
A16: SPYD | B16: SPDRポートフォリオS&P 500高配当株式ETF | C16: =SUMIFS('配当金履歴一覧'!$F:F,'配当金履歴一覧'!$C:$C,">=2024/1",'配当金履歴一覧'!$C:$C,"<=2024/12",'配当金履歴一覧'!$B:$B,$B16)+SUMIFS('配当金履歴一覧'!$H:H,'配当金履歴一覧'!$C:$C,">=2024/1",'配当金履歴一覧'!$C:$C,"<=2024/12",'配当金履歴一覧'!$B:$B,$B16) -> 40440 | D16: =SUMIFS('配当金履歴一覧'!$F:F,'配当金履歴一覧'!$C:$C,">=2025/1",'配当金履歴一覧'!$C:$C,"<=2025/12",'配当金履歴一覧'!$B:$B,$B16)+SUMIFS('配当金履歴一覧'!$H:H,'配当金履歴一覧'!$C:$C,">=2025/1",'配当金履歴一覧'!$C:$C,"<=2025/12",'配当金履歴一覧'!$B:$B,$B16) -> 42334 | E16: =SUMIFS('配当金履歴一覧'!$F:F,'配当金履歴一覧'!$C:$C,">=2026/1",'配当金履歴一覧'!$C:$C,"<=2026/12",'配当金履歴一覧'!$B:$B,$B16)+SUMIFS('配当金履歴一覧'!$H:H,'配当金履歴一覧'!$C:$C,">=2026/1",'配当金履歴一覧'!$C:$C,"<=2026/12",'配当金履歴一覧'!$B:$B,$B16) -> 0
A17: 日本株 | C17: =SUM(C19:C56) -> 41052 | D17: =SUM(D19:D56) -> 68143 | E17: =SUM(E19:E56) -> 0
A19: 1605 | B19: INPEX | C19: =SUMIFS('配当金履歴一覧'!$F:F,'配当金履歴一覧'!$C:$C,">=2024/1",'配当金履歴一覧'!$C:$C,"<=2024/12",'配当金履歴一覧'!$B:$B,$B19)+SUMIFS('配当金履歴一覧'!$H:H,'配当金履歴一覧'!$C:$C,">=2024/1",'配当金履歴一覧'!$C:$C,"<=2024/12",'配当金履歴一覧'!$B:$B,$B19) -> 172 | D19: =SUMIFS('配当金履歴一覧'!$F:F,'配当金履歴一覧'!$C:$C,">=2025/1",'配当金履歴一覧'!$C:$C,"<=2025/12",'配当金履歴一覧'!$B:$B,$B19)+SUMIFS('配当金履歴一覧'!$H:H,'配当金履歴一覧'!$C:$C,">=2025/1",'配当金履歴一覧'!$C:$C,"<=2025/12",'配当金履歴一覧'!$B:$B,$B19) -> 1859 | E19: =SUMIFS('配当金履歴一覧'!$F:F,'配当金履歴一覧'!$C:$C,">=2026/1",'配当金履歴一覧'!$C:$C,"<=2026/12",'配当金履歴一覧'!$B:$B,$B19)+SUMIFS('配当金履歴一覧'!$H:H,'配当金履歴一覧'!$C:$C,">=2026/1",'配当金履歴一覧'!$C:$C,"<=2026/12",'配当金履歴一覧'!$B:$B,$B19) -> 0
A20: 1801 | B20: 長谷工コーポレーション | C20: =SUMIFS('配当金履歴一覧'!$F:F,'配当金履歴一覧'!$C:$C,">=2024/1",'配当金履歴一覧'!$C:$C,"<=2024/12",'配当金履歴一覧'!$B:$B,$B20)+SUMIFS('配当金履歴一覧'!$H:H,'配当金履歴一覧'!$C:$C,">=2024/1",'配当金履歴一覧'!$C:$C,"<=2024/12",'配当金履歴一覧'!$B:$B,$B20) -> 702 | D20: =SUMIFS('配当金履歴一覧'!$F:F,'配当金履歴一覧'!$C:$C,">=2025/1",'配当金履歴一覧'!$C:$C,"<=2025/12",'配当金履歴一覧'!$B:$B,$B20)+SUMIFS('配当金履歴一覧'!$H:H,'配当金履歴一覧'!$C:$C,">=2025/1",'配当金履歴一覧'!$C:$C,"<=2025/12",'配当金履歴一覧'!$B:$B,$B20) -> 1114 | E20: =SUMIFS('配当金履歴一覧'!$F:F,'配当金履歴一覧'!$C:$C,">=2026/1",'配当金履歴一覧'!$C:$C,"<=2026/12",'配当金履歴一覧'!$B:$B,$B20)+SUMIFS('配当金履歴一覧'!$H:H,'配当金履歴一覧'!$C:$C,">=2026/1",'配当金履歴一覧'!$C:$C,"<=2026/12",'配当金履歴一覧'!$B:$B,$B20) -> 0
A21: 1911 | B21: 住友林業 | C21: =SUMIFS('配当金履歴一覧'!$F:F,'配当金履歴一覧'!$C:$C,">=2024/1",'配当金履歴一覧'!$C:$C,"<=2024/12",'配当金履歴一覧'!$B:$B,$B21)+SUMIFS('配当金履歴一覧'!$H:H,'配当金履歴一覧'!$C:$C,">=2024/1",'配当金履歴一覧'!$C:$C,"<=2024/12",'配当金履歴一覧'!$B:$B,$B21) -> 1983 | D21: =SUMIFS('配当金履歴一覧'!$F:F,'配当金履歴一覧'!$C:$C,">=2025/1",'配当金履歴一覧'!$C:$C,"<=2025/12",'配当金履歴一覧'!$B:$B,$B21)+SUMIFS('配当金履歴一覧'!$H:H,'配当金履歴一覧'!$C:$C,">=2025/1",'配当金履歴一覧'!$C:$C,"<=2025/12",'配当金履歴一覧'!$B:$B,$B21) -> 3132 | E21: =SUMIFS('配当金履歴一覧'!$F:F,'配当金履歴一覧'!$C:$C,">=2026/1",'配当金履歴一覧'!$C:$C,"<=2026/12",'配当金履歴一覧'!$B:$B,$B21)+SUMIFS('配当金履歴一覧'!$H:H,'配当金履歴一覧'!$C:$C,">=2026/1",'配当金履歴一覧'!$C:$C,"<=2026/12",'配当金履歴一覧'!$B:$B,$B21) -> 0
A22: 1925 | B22: 大和ハウス工業 | C22: =SUMIFS('配当金履歴一覧'!$F:F,'配当金履歴一覧'!$C:$C,">=2024/1",'配当金履歴一覧'!$C:$C,"<=2024/12",'配当金履歴一覧'!$B:$B,$B22)+SUMIFS('配当金履歴一覧'!$H:H,'配当金履歴一覧'!$C:$C,">=2024/1",'配当金履歴一覧'!$C:$C,"<=2024/12",'配当金履歴一覧'!$B:$B,$B22) -> 1387 | D22: =SUMIFS('配当金履歴一覧'!$F:F,'配当金履歴一覧'!$C:$C,">=2025/1",'配当金履歴一覧'!$C:$C,"<=2025/12",'配当金履歴一覧'!$B:$B,$B22)+SUMIFS('配当金履歴一覧'!$H:H,'配当金履歴一覧'!$C:$C,">=2025/1",'配当金履歴一覧'!$C:$C,"<=2025/12",'配当金履歴一覧'!$B:$B,$B22) -> 1764 | E22: =SUMIFS('配当金履歴一覧'!$F:F,'配当金履歴一覧'!$C:$C,">=2026/1",'配当金履歴一覧'!$C:$C,"<=2026/12",'配当金履歴一覧'!$B:$B,$B22)+SUMIFS('配当金履歴一覧'!$H:H,'配当金履歴一覧'!$C:$C,">=2026/1",'配当金履歴一覧'!$C:$C,"<=2026/12",'配当金履歴一覧'!$B:$B,$B22) -> 0
A23: 1928 | B23: 積水ハウス | C23: =SUMIFS('配当金履歴一覧'!$F:F,'配当金履歴一覧'!$C:$C,">=2024/1",'配当金履歴一覧'!$C:$C,"<=2024/12",'配当金履歴一覧'!$B:$B,$B23)+SUMIFS('配当金履歴一覧'!$H:H,'配当金履歴一覧'!$C:$C,">=2024/1",'配当金履歴一覧'!$C:$C,"<=2024/12",'配当金履歴一覧'!$B:$B,$B23) -> 1658 | D23: =SUMIFS('配当金履歴一覧'!$F:F,'配当金履歴一覧'!$C:$C,">=2025/1",'配当金履歴一覧'!$C:$C,"<=2025/12",'配当金履歴一覧'!$B:$B,$B23)+SUMIFS('配当金履歴一覧'!$H:H,'配当金履歴一覧'!$C:$C,">=2025/1",'配当金履歴一覧'!$C:$C,"<=2025/12",'配当金履歴一覧'!$B:$B,$B23) -> 2642 | E23: =SUMIFS('配当金履歴一覧'!$F:F,'配当金履歴一覧'!$C:$C,">=2026/1",'配当金履歴一覧'!$C:$C,"<=2026/12",'配当金履歴一覧'!$B:$B,$B23)+SUMIFS('配当金履歴一覧'!$H:H,'配当金履歴一覧'!$C:$C,">=2026/1",'配当金履歴一覧'!$C:$C,"<=2026/12",'配当金履歴一覧'!$B:$B,$B23) -> 0
A24: 2124 | B24: ジェイエイシーリクルートメント | C24: =SUMIFS('配当金履歴一覧'!$F:F,'配当金履歴一覧'!$C:$C,">=2024/1",'配当金履歴一覧'!$C:$C,"<=2024/12",'配当金履歴一覧'!$B:$B,$B24)+SUMIFS('配当金履歴一覧'!$H:H,'配当金履歴一覧'!$C:$C,">=2024/1",'配当金履歴一覧'!$C:$C,"<=2024/12",'配当金履歴一覧'!$B:$B,$B24) -> 1148 | D24: =SUMIFS('配当金履歴一覧'!$F:F,'配当金履歴一覧'!$C:$C,">=2025/1",'配当金履歴一覧'!$C:$C,"<=2025/12",'配当金履歴一覧'!$B:$B,$B24)+SUMIFS('配当金履歴一覧'!$H:H,'配当金履歴一覧'!$C:$C,">=2025/1",'配当金履歴一覧'!$C:$C,"<=2025/12",'配当金履歴一覧'!$B:$B,$B24) -> 1587 | E24: =SUMIFS('配当金履歴一覧'!$F:F,'配当金履歴一覧'!$C:$C,">=2026/1",'配当金履歴一覧'!$C:$C,"<=2026/12",'配当金履歴一覧'!$B:$B,$B24)+SUMIFS('配当金履歴一覧'!$H:H,'配当金履歴一覧'!$C:$C,">=2026/1",'配当金履歴一覧'!$C:$C,"<=2026/12",'配当金履歴一覧'!$B:$B,$B24) -> 0
A25: 2503 | B25: キリンホールディングス | C25: =SUMIFS('配当金履歴一覧'!$F:F,'配当金履歴一覧'!$C:$C,">=2024/1",'配当金履歴一覧'!$C:$C,"<=2024/12",'配当金履歴一覧'!$B:$B,$B25)+SUMIFS('配当金履歴一覧'!$H:H,'配当金履歴一覧'!$C:$C,">=2024/1",'配当金履歴一覧'!$C:$C,"<=2024/12",'配当金履歴一覧'!$B:$B,$B25) -> 590 | D25: =SUMIFS('配当金履歴一覧'!$F:F,'配当金履歴一覧'!$C:$C,">=2025/1",'配当金履歴一覧'!$C:$C,"<=2025/12",'配当金履歴一覧'!$B:$B,$B25)+SUMIFS('配当金履歴一覧'!$H:H,'配当金履歴一覧'!$C:$C,">=2025/1",'配当金履歴一覧'!$C:$C,"<=2025/12",'配当金履歴一覧'!$B:$B,$B25) -> 743 | E25: =SUMIFS('配当金履歴一覧'!$F:F,'配当金履歴一覧'!$C:$C,">=2026/1",'配当金履歴一覧'!$C:$C,"<=2026/12",'配当金履歴一覧'!$B:$B,$B25)+SUMIFS('配当金履歴一覧'!$H:H,'配当金履歴一覧'!$C:$C,">=2026/1",'配当金履歴一覧'!$C:$C,"<=2026/12",'配当金履歴一覧'!$B:$B,$B25) -> 0
A26: 2768 | B26: 双日 | C26: =SUMIFS('配当金履歴一覧'!$F:F,'配当金履歴一覧'!$C:$C,">=2024/1",'配当金履歴一覧'!$C:$C,"<=2024/12",'配当金履歴一覧'!$B:$B,$B26)+SUMIFS('配当金履歴一覧'!$H:H,'配当金履歴一覧'!$C:$C,">=2024/1",'配当金履歴一覧'!$C:$C,"<=2024/12",'配当金履歴一覧'!$B:$B,$B26) -> 2491 | D26: =SUMIFS('配当金履歴一覧'!$F:F,'配当金履歴一覧'!$C:$C,">=2025/1",'配当金履歴一覧'!$C:$C,"<=2025/12",'配当金履歴一覧'!$B:$B,$B26)+SUMIFS('配当金履歴一覧'!$H:H,'配当金履歴一覧'!$C:$C,">=2025/1",'配当金履歴一覧'!$C:$C,"<=2025/12",'配当金履歴一覧'!$B:$B,$B26) -> 3958 | E26: =SUMIFS('配当金履歴一覧'!$F:F,'配当金履歴一覧'!$C:$C,">=2026/1",'配当金履歴一覧'!$C:$C,"<=2026/12",'配当金履歴一覧'!$B:$B,$B26)+SUMIFS('配当金履歴一覧'!$H:H,'配当金履歴一覧'!$C:$C,">=2026/1",'配当金履歴一覧'!$C:$C,"<=2026/12",'配当金履歴一覧'!$B:$B,$B26) -> 0
A27: 2914 | B27: 日本たばこ産業 | C27: =SUMIFS('配当金履歴一覧'!$F:F,'配当金履歴一覧'!$C:$C,">=2024/1",'配当金履歴一覧'!$C:$C,"<=2024/12",'配当金履歴一覧'!$B:$B,$B27)+SUMIFS('配当金履歴一覧'!$H:H,'配当金履歴一覧'!$C:$C,">=2024/1",'配当金履歴一覧'!$C:$C,"<=2024/12",'配当金履歴一覧'!$B:$B,$B27) -> 291 | D27: =SUMIFS('配当金履歴一覧'!$F:F,'配当金履歴一覧'!$C:$C,">=2025/1",'配当金履歴一覧'!$C:$C,"<=2025/12",'配当金履歴一覧'!$B:$B,$B27)+SUMIFS('配当金履歴一覧'!$H:H,'配当金履歴一覧'!$C:$C,">=2025/1",'配当金履歴一覧'!$C:$C,"<=2025/12",'配当金履歴一覧'!$B:$B,$B27) -> 1109 | E27: =SUMIFS('配当金履歴一覧'!$F:F,'配当金履歴一覧'!$C:$C,">=2026/1",'配当金履歴一覧'!$C:$C,"<=2026/12",'配当金履歴一覧'!$B:$B,$B27)+SUMIFS('配当金履歴一覧'!$H:H,'配当金履歴一覧'!$C:$C,">=2026/1",'配当金履歴一覧'!$C:$C,"<=2026/12",'配当金履歴一覧'!$B:$B,$B27) -> 0
A28: 3003 | B28: ヒューリック | C28: =SUMIFS('配当金履歴一覧'!$F:F,'配当金履歴一覧'!$C:$C,">=2024/1",'配当金履歴一覧'!$C:$C,"<=2024/12",'配当金履歴一覧'!$B:$B,$B28)+SUMIFS('配当金履歴一覧'!$H:H,'配当金履歴一覧'!$C:$C,">=2024/1",'配当金履歴一覧'!$C:$C,"<=2024/12",'配当金履歴一覧'!$B:$B,$B28) -> 104 | D28: =SUMIFS('配当金履歴一覧'!$F:F,'配当金履歴一覧'!$C:$C,">=2025/1",'配当金履歴一覧'!$C:$C,"<=2025/12",'配当金履歴一覧'!$B:$B,$B28)+SUMIFS('配当金履歴一覧'!$H:H,'配当金履歴一覧'!$C:$C,">=2025/1",'配当金履歴一覧'!$C:$C,"<=2025/12",'配当金履歴一覧'!$B:$B,$B28) -> 622 | E28: =SUMIFS('配当金履歴一覧'!$F:F,'配当金履歴一覧'!$C:$C,">=2026/1",'配当金履歴一覧'!$C:$C,"<=2026/12",'配当金履歴一覧'!$B:$B,$B28)+SUMIFS('配当金履歴一覧'!$H:H,'配当金履歴一覧'!$C:$C,">=2026/1",'配当金履歴一覧'!$C:$C,"<=2026/12",'配当金履歴一覧'!$B:$B,$B28) -> 0
A29: 4042 | B29: 東ソー | C29: =SUMIFS('配当金履歴一覧'!$F:F,'配当金履歴一覧'!$C:$C,">=2024/1",'配当金履歴一覧'!$C:$C,"<=2024/12",'配当金履歴一覧'!$B:$B,$B29)+SUMIFS('配当金履歴一覧'!$H:H,'配当金履歴一覧'!$C:$C,">=2024/1",'配当金履歴一覧'!$C:$C,"<=2024/12",'配当金履歴一覧'!$B:$B,$B29) -> 0 | D29: =SUMIFS('配当金履歴一覧'!$F:F,'配当金履歴一覧'!$C:$C,">=2025/1",'配当金履歴一覧'!$C:$C,"<=2025/12",'配当金履歴一覧'!$B:$B,$B29)+SUMIFS('配当金履歴一覧'!$H:H,'配当金履歴一覧'!$C:$C,">=2025/1",'配当金履歴一覧'!$C:$C,"<=2025/12",'配当金履歴一覧'!$B:$B,$B29) -> 0 | E29: =SUMIFS('配当金履歴一覧'!$F:F,'配当金履歴一覧'!$C:$C,">=2026/1",'配当金履歴一覧'!$C:$C,"<=2026/12",'配当金履歴一覧'!$B:$B,$B29)+SUMIFS('配当金履歴一覧'!$H:H,'配当金履歴一覧'!$C:$C,">=2026/1",'配当金履歴一覧'!$C:$C,"<=2026/12",'配当金履歴一覧'!$B:$B,$B29) -> 0
A30: 4452 | B30: 花王 | C30: =SUMIFS('配当金履歴一覧'!$F:F,'配当金履歴一覧'!$C:$C,">=2024/1",'配当金履歴一覧'!$C:$C,"<=2024/12",'配当金履歴一覧'!$B:$B,$B30)+SUMIFS('配当金履歴一覧'!$H:H,'配当金履歴一覧'!$C:$C,">=2024/1",'配当金履歴一覧'!$C:$C,"<=2024/12",'配当金履歴一覧'!$B:$B,$B30) -> 152 | D30: =SUMIFS('配当金履歴一覧'!$F:F,'配当金履歴一覧'!$C:$C,">=2025/1",'配当金履歴一覧'!$C:$C,"<=2025/12",'配当金履歴一覧'!$B:$B,$B30)+SUMIFS('配当金履歴一覧'!$H:H,'配当金履歴一覧'!$C:$C,">=2025/1",'配当金履歴一覧'!$C:$C,"<=2025/12",'配当金履歴一覧'!$B:$B,$B30) -> 689 | E30: =SUMIFS('配当金履歴一覧'!$F:F,'配当金履歴一覧'!$C:$C,">=2026/1",'配当金履歴一覧'!$C:$C,"<=2026/12",'配当金履歴一覧'!$B:$B,$B30)+SUMIFS('配当金履歴一覧'!$H:H,'配当金履歴一覧'!$C:$C,">=2026/1",'配当金履歴一覧'!$C:$C,"<=2026/12",'配当金履歴一覧'!$B:$B,$B30) -> 0
... A56: 9513 | B56: 電源開発 | C56: =SUMIFS('配当金履歴一覧'!$F:F,'配当金履歴一覧'!$C:$C,">=2024/1",'配当金履歴一覧'!$C:$C,"<=2024/12",'配当金履歴一覧'!$B:$B,$B56)+SUMIFS('配当金履歴一覧'!$H:H,'配当金履歴一覧'!$C:$C,">=2024/1",'配当金履歴一覧'!$C:$C,"<=2024/12",'配当金履歴一覧'!$B:$B,$B56) -> 1655 | D56: =SUMIFS('配当金履歴一覧'!$F:F,'配当金履歴一覧'!$C:$C,">=2025/1",'配当金履歴一覧'!$C:$C,"<=2025/12",'配当金履歴一覧'!$B:$B,$B56)+SUMIFS('配当金履歴一覧'!$H:H,'配当金履歴一覧'!$C:$C,">=2025/1",'配当金履歴一覧'!$C:$C,"<=2025/12",'配当金履歴一覧'!$B:$B,$B56) -> 2288 | E56: =SUMIFS('配当金履歴一覧'!$F:F,'配当金履歴一覧'!$C:$C,">=2026/1",'配当金履歴一覧'!$C:$C,"<=2026/12",'配当金履歴一覧'!$B:$B,$B56)+SUMIFS('配当金履歴一覧'!$H:H,'配当金履歴一覧'!$C:$C,">=2026/1",'配当金履歴一覧'!$C:$C,"<=2026/12",'配当金履歴一覧'!$B:$B,$B56) -> 0

Sheet 配当金履歴一覧
A1: No. | B1: 銘柄名 | C1: 配当金分配年月 | D1: 配当金単価 （税引き後） | E1: 保有数 （特定） | F1: 受取金額 （特定） | G1: 保有数 （NISA） | H1: 受取金額 （NISA）
A2: =row()-1 -> 1 | B2: バンガード 米国高配当株式ETF | C2: 45352 | D2: 0.59USD | E2: 0 | F2: 0 | G2: 2 | H2: 174
A3: =row()-1 -> 2 | B3: SPDRポートフォリオS&P 500高配当株式ETF | C3: 45352 | D3: 0.33USD | E3: 191 | F3: 7580 | G3: 5 | H3: 249
A4: =row()-1 -> 3 | B4: GMOフィナンシャルホールディングス | C4: 45352 | D4: 7.2 | E4: 20 | F4: 115 | G4: 0 | H4: 0
A5: =row()-1 -> 4 | B5: iシェアーズ コア 米国高配当株 ETF | C5: 45352 | D5: 0.75USD | E5: 51 | F5: 4605 | G5: 3 | H5: 113.3
A6: =row()-1 -> 5 | B6: ジェイエイシーリクルートメント | C6: 45352 | D6: 90 | E6: 16 | F6: 1148 | G6: 0 | H6: 0
A7: =row()-1 -> 6 | B7: キヤノン | C7: 45352 | D7: 70 | E7: 2 | F7: 112 | G7: 0 | H7: 0
A8: =row()-1 -> 7 | B8: キリンホールディングス | C8: 45352 | D8: 36.5 | E8: 9 | F8: 262 | G8: 0 | H8: 0
A9: =row()-1 -> 8 | B9: 住友林業 | C9: 45352 | D9: 65 | E9: 16 | F9: 829 | G9: 0 | H9: 0
A10: =row()-1 -> 9 | B10: 積水ハウス | C10: 45383 | D10: 64 | E10: 15 | F10: 765 | G10: 0 | H10: 0
A11: =row()-1 -> 10 | B11: セブン銀行 | C11: 45444 | D11: 5.5 | E11: 0 | F11: 0 | G11: 50 | H11: 275
A12: =row()-1 -> 11 | B12: 丸紅 | C12: 45444 | D12: 43.5 | E12: 9 | F12: 313 | G12: 3 | H12: 131
A13: =row()-1 -> 12 | B13: オリックス | C13: 45444 | D13: 55.8 | E13: 14 | F13: 624 | G13: 0 | H13: 0
A14: =row()-1 -> 13 | B14: ソフトバンク | C14: 45444 | D14: 43 | E14: 10 | F14: 344 | G14: 0 | H14: 0
A15: =row()-1 -> 14 | B15: 三菱HCキャピタル | C15: 45444 | D15: 10 | E15: 19 | F15: 152 | G15: 0 | H15: 0
A16: =row()-1 -> 15 | B16: SBIホールディングス | C16: 45444 | D16: 130 | E16: 11 | F16: 1140 | G16: 2 | H16: 260
A17: =row()-1 -> 16 | B17: iシェアーズ コア 米国高配当株 ETF | C17: 45444 | D17: 0.83USD | E17: 51 | F17: 5316 | G17: 6 | H17: 785
A18: =row()-1 -> 17 | B18: 双日 | C18: 45444 | D18: 70 | E18: 17 | F18: 949 | G18: 0 | H18: 0
A19: =row()-1 -> 18 | B19: KDDI | C19: 45444 | D19: 70 | E19: 8 | F19: 447 | G19: 2 | H19: 140
A20: =row()-1 -> 19 | B20: 三井物産 | C20: 45444 | D20: 85 | E20: 12 | F20: 813 | G20: 1 | H20: 85
A21: =row()-1 -> 20 | B21: GMOフィナンシャルホールディングス | C21: 45444 | D21: 11.87 | E21: 0 | F21: 0 | G21: 20 | H21: 238
A22: =row()-1 -> 21 | B22: NTT | C22: 45444 | D22: 2.6 | E22: 125 | F22: 260 | G22: 0 | H22: 0
A23: =row()-1 -> 22 | B23: 三菱商事 | C23: 45444 | D23: 35 | E23: 15 | F23: 419 | G23: 0 | H23: 0
A24: =row()-1 -> 23 | B24: 住友商事 | C24: 45444 | D24: 62.5 | E24: 9 | F24: 448 | G24: 2 | H24: 125
A25: =row()-1 -> 24 | B25: 伊藤忠商事 | C25: 45444 | D25: 80 | E25: 6 | F25: 383 | G25: 0 | H25: 0
A26: =row()-1 -> 25 | B26: 東京海上ホールディングス | C26: 45444 | D26: 62.5 | E26: 26 | F26: 1296 | G26: 2 | H26: 125
A27: =row()-1 -> 26 | B27: SOMPOホールディングス | C27: 45444 | D27: 150 | E27: 11 | F27: 1316 | G27: 0 | H27: 0
A28: =row()-1 -> 27 | B28: バンガード 米国高配当株式ETF | C28: 45444 | D28: 0.92USD | E28: 0 | F28: 0 | G28: 8 | H28: 1170
A29: =row()-1 -> 28 | B29: SPDRポートフォリオS&P 500高配当株式ETF | C29: 45444 | D29: 0.43USD | E29: 191 | F29: 10578 | G29: 6 | H29: 417
A30: =row()-1 -> 29 | B30: 電源開発 | C30: 45444 | D30: 55 | E30: 13 | F30: 571 | G30: 3 | H30: 165
A31: =row()-1 -> 30 | B31: ENEOSホールディングス | C31: 45444 | D31: 11 | E31: 0 | F31: 0 | G31: 2 | H31: 22
A32: =row()-1 -> 31 | B32: 武田薬品工業 | C32: 45444 | D32: 94 | E32: 26 | F32: 1948 | G32: 0 | H32: 0
A33: =row()-1 -> 32 | B33: 三井住友フィナンシャルグループ | C33: 45444 | D33: 135 | E33: 10 | F33: 1077 | G33: 0 | H33: 0
A34: =row()-1 -> 33 | B34: 三菱UFJフィナンシャル・グループ | C34: 45444 | D34: 20.5 | E34: 22 | F34: 360 | G34: 0 | H34: 0
A35: =row()-1 -> 34 | B35: 大和ハウス工業 | C35: 45444 | D35: 80 | E35: 8 | F35: 510 | G35: 1 | H35: 80
A36: =row()-1 -> 35 | B36: 長谷工コーポレーション | C36: 45444 | D36: 45 | E36: 8 | F36: 287 | G36: 0 | H36: 0
A37: =row()-1 -> 36 | B37: キヤノン | C37: 45505 | D37: 75 | E37: 2 | F37: 121 | G37: 3 | H37: 225
A38: =row()-1 -> 37 | B38: 花王 | C38: 45536 | D38: 76 | E38: 0 | F38: 0 | G38: 2 | H38: 152
A39: =row()-1 -> 38 | B39: INPEX | C39: 45536 | D39: 43 | E39: 0 | F39: 0 | G39: 4 | H39: 172
A40: =row()-1 -> 39 | B40: ヒューリック | C40: 45536 | D40: 26 | E40: 0 | F40: 0 | G40: 4 | H40: 104
A41: =row()-1 -> 40 | B41: 日本たばこ産業 | C41: 45536 | D41: 97 | E41: 0 | F41: 0 | G41: 3 | H41: 291
... A45: =row()-1 -> 44 | B45: GMOフィナンシャルホールディングス | C45: 45536 | D45: 2 | E45: 0 | F45: 0 | G45: 20 | H45: 40
A46: =row()-1 -> 45 | B46: バンガード 米国高配当株式ETF | C46: 45536 | D46: 0.76USD | E46: 0 | F46: 0 | G46: 8 | H46: 874
A47: =row()-1 -> 46 | B47: SPDRポートフォリオS&P 500高配当株式ETF | C47: 45536 | D47: 0.41USD | E47: 191 | F47: 8928 | G47: 6 | H47: 352
A48: =row()-1 -> 47 | B48: 積水ハウス | C48: 45536 | D48: 64 | E48: 15 | F48: 765 | G48: 2 | H48: 128
A49: =row()-1 -> 48 | B49: iシェアーズ コア 米国高配当株 ETF | C49: 45566 | D49: 1.1USD | E49: 51 | F49: 6381 | G49: 6 | H49: 942
A50: =row()-1 -> 49 | B50: 電源開発 | C50: 45597 | D50: 50 | E50: 13 | F50: 519 | G50: 8 | H50: 400
A51: =row()-1 -> 50 | B51: NTT | C51: 45597 | D51: 2.6 | E51: 125 | F51: 260 | G51: 0 | H51: 0
A52: =row()-1 -> 51 | B52: ENEOSホールディングス | C52: 45597 | D52: 13 | E52: 0 | F52: 0 | G52: 4 | H52: 52
A53: =row()-1 -> 52 | B53: セブン銀行 | C53: 45627 | D53: 5.5 | E53: 0 | F53: 0 | G53: 50 | H53: 275
A54: =row()-1 -> 53 | B54: 三菱商事 | C54: 45627 | D54: 50 | E54: 15 | F54: 599 | G54: 0 | H54: 0
A55: =row()-1 -> 54 | B55: 住友商事 | C55: 45627 | D55: 65 | E55: 9 | F55: 467 | G55: 3 | H55: 195
A56: =row()-1 -> 55 | B56: 丸紅 | C56: 45627 | D56: 45 | E56: 9 | F56: 323 | G56: 5 | H56: 225
A57: =row()-1 -> 56 | B57: 伊藤忠商事 | C57: 45627 | D57: 100 | E57: 6 | F57: 479 | G57: 1 | H57: 100
A58: =row()-1 -> 57 | B58: 武田薬品工業 | C58: 45627 | D58: 98 | E58: 26 | F58: 2031 | G58: 3 | H58: 294
A59: =row()-1 -> 58 | B59: 双日 | C59: 45627 | D59: 75 | E59: 17 | F59: 1017 | G59: 7 | H59: 525
A60: =row()-1 -> 59 | B60: KDDI | C60: 45627 | D60: 70 | E60: 8 | F60: 447 | G60: 5 | H60: 350
A61: =row()-1 -> 60 | B61: 三井住友フィナンシャルグループ | C61: 45627 | D61: 180 | E61: 10 | F61: 1435 | G61: 1 | H61: 180
... A73: =row()-1 -> 72 | B73: GMOフィナンシャルホールディングス | C73: 45627 | D73: 8.27 | E73: 0 | F73: 0 | G73: 20 | H73: 166
A74: =row()-1 -> 73 | B74: iシェアーズ コア 米国高配当株 ETF | C74: 45627 | D74: 1.01USD | E74: 51 | F74: 6442 | G74: 8 | H74: 1268
A75: =row()-1 -> 74 | B75: バンガード 米国高配当株式ETF | C75: 45627 | D75: 0.86USD | E75: 0 | F75: 0 | G75: 9 | H75: 1223
A76: =row()-1 -> 75 | B76: SPDRポートフォリオS&P 500高配当株式ETF | C76: 45627 | D76: 0.49USD | E76: 191 | F76: 11720 | G76: 8 | H76: 616
A77: =row()-1 -> 76 | B77: あおぞら銀行 | C77: 45717 | D77: 19 | E77: 0 | F77: 0 | G77: 6 | H77: 114
A78: =row()-1 -> 77 | B78: iシェアーズ コア 米国高配当株 ETF | C78: 45717 | D78: 0.71USD | E78: 51 | F78: 4311 | G78: 13 | H78: 1379
A79: =row()-1 -> 78 | B79: GMOフィナンシャルホールディングス | C79: 45717 | D79: 5.24 | E79: 0 | F79: 0 | G79: 20 | H79: 105
A80: =row()-1 -> 79 | B80: 花王 | C80: 45717 | D80: 76 | E80: 0 | F80: 0 | G80: 4 | H80: 304
A81: =row()-1 -> 80 | B81: バンガード 米国高配当株式ETF | C81: 45717 | D81: 0.76USD | E81: 0 | F81: 0 | G81: 12 | H81: 1378
A82: =row()-1 -> 81 | B82: SPDRポートフォリオS&P 500高配当株式ETF | C82: 45717 | D82: 0.37USD | E82: 191 | F82: 8562 | G82: 8 | H82: 450
A83: =row()-1 -> 82 | B83: ヒューリック | C83: 45717 | D83: 28 | E83: 0 | F83: 0 | G83: 10 | H83: 280
A84: =row()-1 -> 83 | B84: 日本たばこ産業 | C84: 45717 | D84: 97 | E84: 0 | F84: 0 | G84: 5 | H84: 485
A85: =row()-1 -> 84 | B85: ジェイエイシーリクルートメント | C85: 45717 | D85: 26 | E85: 64 | F85: 1327 | G85: 10 | H85: 260
A86: =row()-1 -> 85 | B86: キヤノン | C86: 45717 | D86: 80 | E86: 2 | F86: 128 | G86: 3 | H86: 240
A87: =row()-1 -> 86 | B87: キリンホールディングス | C87: 45717 | D87: 35.5 | E87: 9 | F87: 256 | G87: 2 | H87: 72
A88: =row()-1 -> 87 | B88: 住友林業 | C88: 45717 | D88: 80 | E88: 16 | F88: 1020 | G88: 6 | H88: 480
A89: =row()-1 -> 88 | B89: INPEX | C89: 45717 | D89: 43 | E89: 0 | F89: 0 | G89: 13 | H89: 559
A90: =row()-1 -> 89 | B90: 積水ハウス | C90: 45748 | D90: 71 | E90: 15 | F90: 849 | G90: 4 | H90: 284
A91: =row()-1 -> 90 | B91: 丸紅 | C91: 45809 | D91: 50 | E91: 9 | F91: 360 | G91: 7 | H91: 350
A92: =row()-1 -> 91 | B92: 双日 | C92: 45809 | D92: 75 | E92: 17 | F92: 1017 | G92: 10 | H92: 750
A93: =row()-1 -> 92 | B93: オリックス | C93: 45809 | D93: 57.84 | E93: 14 | F93: 646 | G93: 2 | H93: 117
A94: =row()-1 -> 93 | B94: 三菱HCキャピタル | C94: 45809 | D94: 20 | E94: 10 | F94: 160 | G94: 6 | H94: 120
... A103: =row()-1 -> 102 | B103: 小松製作所 | C103: 45809 | D103: 107 | E103: 0 | F103: 0 | G103: 2 | H103: 214
A104: =row()-1 -> 103 | B104: iシェアーズ コア 米国高配当株 ETF | C104: 45809 | D104: 0.82USD | E104: 51 | F104: 4821 | G104: 16 | H104: 1898
A105: =row()-1 -> 104 | B105: 三菱商事 | C105: 45809 | D105: 50 | E105: 15 | F105: 599 | G105: 6 | H105: 300
A106: =row()-1 -> 105 | B106: 住友商事 | C106: 45809 | D106: 65 | E106: 9 | F106: 467 | G106: 5 | H106: 325
A107: =row()-1 -> 106 | B107: 伊藤忠商事 | C107: 45809 | D107: 100 | E107: 6 | F107: 479 | G107: 3 | H107: 300
A108: =row()-1 -> 107 | B108: 東京海上ホールディングス | C108: 45809 | D108: 91 | E108: 26 | F108: 1886 | G108: 5 | H108: 455
A109: =row()-1 -> 108 | B109: SOMPOホールディングス | C109: 45809 | D109: 76 | E109: 33 | F109: 1999 | G109: 5 | H109: 380
A110: =row()-1 -> 109 | B110: バンガード 米国高配当株式ETF | C110: 45809 | D110: 0.77USD | E110: 0 | F110: 0 | G110: 17 | H110: 1908
A111: =row()-1 -> 110 | B111: あおぞら銀行 | C111: 45809 | D111: 22 | E111: 0 | F111: 0 | G111: 7 | H111: 154
A112: =row()-1 -> 111 | B112: SPDRポートフォリオS&P 500高配当株式ETF | C112: 45809 | D112: 0.45USD | E112: 191 | F112: 9858 | G112: 9 | H112: 583
A113: =row()-1 -> 112 | B113: 武田薬品工業 | C113: 45809 | D113: 98 | E113: 26 | F113: 2031 | G113: 5 | H113: 490
A114: =row()-1 -> 113 | B114: 電源開発 | C114: 45809 | D114: 50 | E114: 13 | F114: 519 | G114: 11 | H114: 550
A115: =row()-1 -> 114 | B115: ENEOSホールディングス | C115: 45809 | D115: 13 | E115: 0 | F115: 0 | G115: 4 | H115: 52
A116: =row()-1 -> 115 | B116: 三菱UFJフィナンシャル・グループ | C116: 45809 | D116: 39 | E116: 22 | F116: 685 | G116: 7 | H116: 273
A117: =row()-1 -> 116 | B117: 大和ハウス工業 | C117: 45809 | D117: 80 | E117: 8 | F117: 510 | G117: 5 | H117: 400
A118: =row()-1 -> 117 | B118: 長谷工コーポレーション | C118: 45809 | D118: 45 | E118: 8 | F118: 287 | G118: 6 | H118: 270
A119: =row()-1 -> 118 | B119: 三井住友フィナンシャルグループ | C119: 45839 | D119: 62 | E119: 30 | F119: 1483 | G119: 4 | H119: 248
A120: =row()-1 -> 119 | B120: キヤノン | C120: 45870 | D120: 80 | E120: 2 | F120: 128 | G120: 5 | H120: 400
A121: =row()-1 -> 120 | B121: ブリヂストン | C121: 45901 | D121: 115 | E121: 0 | F121: 0 | G121: 4 | H121: 460
A122: =row()-1 -> 121 | B122: 花王 | C122: 45901 | D122: 77 | E122: 0 | F122: 0 | G122: 5 | H122: 385
...

Sheet 配当金履歴一覧 のコピー
A1: No. | B1: 銘柄コード | C1: 銘柄名 | D1: 年月 | E1: 単価 | F1: 特定口座（保有株数） | G1: 特定口座（受取金額） | H1: NISA口座（保有株数） | I1: NISA口座（受取金額）
A2: =row()-1 -> 1 | C2: バンガード 米国高配当株式ETF | D2: 45352 | E2: 0.59USD | F2: 0 | G2: 0 | H2: 2 | I2: 174
A3: =row()-1 -> 2 | C3: SPDRポートフォリオS&P 500高配当株式ETF | D3: 45352 | E3: 0.33USD | F3: 191 | G3: 7580 | H3: 5 | I3: 249
A4: =row()-1 -> 3 | C4: GMOフィナンシャルホールディングス | D4: 45352 | E4: 7.2 | F4: 20 | G4: 115 | H4: 0 | I4: 0
A5: =row()-1 -> 4 | C5: iシェアーズ コア 米国高配当株 ETF | D5: 45352 | E5: 0.75USD | F5: 51 | G5: 4605 | H5: 3 | I5: 113.3
A6: =row()-1 -> 5 | C6: ジェイエイシーリクルートメント | D6: 45352 | E6: 90 | F6: 16 | G6: 1148 | H6: 0 | I6: 0
A7: =row()-1 -> 6 | C7: キヤノン | D7: 45352 | E7: 70 | F7: 2 | G7: 112 | H7: 0 | I7: 0
A8: =row()-1 -> 7 | C8: キリンホールディングス | D8: 45352 | E8: 36.5 | F8: 9 | G8: 262 | H8: 0 | I8: 0
A9: =row()-1 -> 8 | C9: 住友林業 | D9: 45352 | E9: 65 | F9: 16 | G9: 829 | H9: 0 | I9: 0
A10: =row()-1 -> 9 | C10: 積水ハウス | D10: 45383 | E10: 64 | F10: 15 | G10: 765 | H10: 0 | I10: 0
A11: =row()-1 -> 10 | C11: セブン銀行 | D11: 45444 | E11: 5.5 | F11: 0 | G11: 0 | H11: 50 | I11: 275
A12: =row()-1 -> 11 | C12: 丸紅 | D12: 45444 | E12: 43.5 | F12: 9 | G12: 313 | H12: 3 | I12: 131
A13: =row()-1 -> 12 | C13: オリックス | D13: 45444 | E13: 55.8 | F13: 14 | G13: 624 | H13: 0 | I13: 0
A14: =row()-1 -> 13 | C14: ソフトバンク | D14: 45444 | E14: 43 | F14: 10 | G14: 344 | H14: 0 | I14: 0
A15: =row()-1 -> 14 | C15: 三菱HCキャピタル | D15: 45444 | E15: 10 | F15: 19 | G15: 152 | H15: 0 | I15: 0
A16: =row()-1 -> 15 | C16: SBIホールディングス | D16: 45444 | E16: 130 | F16: 11 | G16: 1140 | H16: 2 | I16: 260
A17: =row()-1 -> 16 | C17: iシェアーズ コア 米国高配当株 ETF | D17: 45444 | E17: 0.83USD | F17: 51 | G17: 5316 | H17: 6 | I17: 785
A18: =row()-1 -> 17 | C18: 双日 | D18: 45444 | E18: 70 | F18: 17 | G18: 949 | H18: 0 | I18: 0
A19: =row()-1 -> 18 | C19: KDDI | D19: 45444 | E19: 70 | F19: 8 | G19: 447 | H19: 2 | I19: 140
A20: =row()-1 -> 19 | C20: 三井物産 | D20: 45444 | E20: 85 | F20: 12 | G20: 813 | H20: 1 | I20: 85
A21: =row()-1 -> 20 | C21: GMOフィナンシャルホールディングス | D21: 45444 | E21: 11.87 | F21: 0 | G21: 0 | H21: 20 | I21: 238
A22: =row()-1 -> 21 | C22: NTT | D22: 45444 | E22: 2.6 | F22: 125 | G22: 260 | H22: 0 | I22: 0
A23: =row()-1 -> 22 | C23: 三菱商事 | D23: 45444 | E23: 35 | F23: 15 | G23: 419 | H23: 0 | I23: 0
A24: =row()-1 -> 23 | C24: 住友商事 | D24: 45444 | E24: 62.5 | F24: 9 | G24: 448 | H24: 2 | I24: 125
A25: =row()-1 -> 24 | C25: 伊藤忠商事 | D25: 45444 | E25: 80 | F25: 6 | G25: 383 | H25: 0 | I25: 0
A26: =row()-1 -> 25 | C26: 東京海上ホールディングス | D26: 45444 | E26: 62.5 | F26: 26 | G26: 1296 | H26: 2 | I26: 125
A27: =row()-1 -> 26 | C27: SOMPOホールディングス | D27: 45444 | E27: 150 | F27: 11 | G27: 1316 | H27: 0 | I27: 0
A28: =row()-1 -> 27 | C28: バンガード 米国高配当株式ETF | D28: 45444 | E28: 0.92USD | F28: 0 | G28: 0 | H28: 8 | I28: 1170
A29: =row()-1 -> 28 | C29: SPDRポートフォリオS&P 500高配当株式ETF | D29: 45444 | E29: 0.43USD | F29: 191 | G29: 10578 | H29: 6 | I29: 417
A30: =row()-1 -> 29 | C30: 電源開発 | D30: 45444 | E30: 55 | F30: 13 | G30: 571 | H30: 3 | I30: 165
A31: =row()-1 -> 30 | C31: ENEOSホールディングス | D31: 45444 | E31: 11 | F31: 0 | G31: 0 | H31: 2 | I31: 22
A32: =row()-1 -> 31 | C32: 武田薬品工業 | D32: 45444 | E32: 94 | F32: 26 | G32: 1948 | H32: 0 | I32: 0
A33: =row()-1 -> 32 | C33: 三井住友フィナンシャルグループ | D33: 45444 | E33: 135 | F33: 10 | G33: 1077 | H33: 0 | I33: 0
A34: =row()-1 -> 33 | C34: 三菱UFJフィナンシャル・グループ | D34: 45444 | E34: 20.5 | F34: 22 | G34: 360 | H34: 0 | I34: 0
A35: =row()-1 -> 34 | C35: 大和ハウス工業 | D35: 45444 | E35: 80 | F35: 8 | G35: 510 | H35: 1 | I35: 80
A36: =row()-1 -> 35 | C36: 長谷工コーポレーション | D36: 45444 | E36: 45 | F36: 8 | G36: 287 | H36: 0 | I36: 0
A37: =row()-1 -> 36 | C37: キヤノン | D37: 45505 | E37: 75 | F37: 2 | G37: 121 | H37: 3 | I37: 225
A38: =row()-1 -> 37 | C38: 花王 | D38: 45536 | E38: 76 | F38: 0 | G38: 0 | H38: 2 | I38: 152
A39: =row()-1 -> 38 | C39: INPEX | D39: 45536 | E39: 43 | F39: 0 | G39: 0 | H39: 4 | I39: 172
A40: =row()-1 -> 39 | C40: ヒューリック | D40: 45536 | E40: 26 | F40: 0 | G40: 0 | H40: 4 | I40: 104
A41: =row()-1 -> 40 | C41: 日本たばこ産業 | D41: 45536 | E41: 97 | F41: 0 | G41: 0 | H41: 3 | I41: 291
... A45: =row()-1 -> 44 | C45: GMOフィナンシャルホールディングス | D45: 45536 | E45: 2 | F45: 0 | G45: 0 | H45: 20 | I45: 40
A46: =row()-1 -> 45 | C46: バンガード 米国高配当株式ETF | D46: 45536 | E46: 0.76USD | F46: 0 | G46: 0 | H46: 8 | I46: 874
A47: =row()-1 -> 46 | C47: SPDRポートフォリオS&P 500高配当株式ETF | D47: 45536 | E47: 0.41USD | F47: 191 | G47: 8928 | H47: 6 | I47: 352
A48: =row()-1 -> 47 | C48: 積水ハウス | D48: 45536 | E48: 64 | F48: 15 | G48: 765 | H48: 2 | I48: 128
A49: =row()-1 -> 48 | C49: iシェアーズ コア 米国高配当株 ETF | D49: 45566 | E49: 1.1USD | F49: 51 | G49: 6381 | H49: 6 | I49: 942
A50: =row()-1 -> 49 | C50: 電源開発 | D50: 45597 | E50: 50 | F50: 13 | G50: 519 | H50: 8 | I50: 400
A51: =row()-1 -> 50 | C51: NTT | D51: 45597 | E51: 2.6 | F51: 125 | G51: 260 | H51: 0 | I51: 0
A52: =row()-1 -> 51 | C52: ENEOSホールディングス | D52: 45597 | E52: 13 | F52: 0 | G52: 0 | H52: 4 | I52: 52
A53: =row()-1 -> 52 | C53: セブン銀行 | D53: 45627 | E53: 5.5 | F53: 0 | G53: 0 | H53: 50 | I53: 275
A54: =row()-1 -> 53 | C54: 三菱商事 | D54: 45627 | E54: 50 | F54: 15 | G54: 599 | H54: 0 | I54: 0
A55: =row()-1 -> 54 | C55: 住友商事 | D55: 45627 | E55: 65 | F55: 9 | G55: 467 | H55: 3 | I55: 195
A56: =row()-1 -> 55 | C56: 丸紅 | D56: 45627 | E56: 45 | F56: 9 | G56: 323 | H56: 5 | I56: 225
A57: =row()-1 -> 56 | C57: 伊藤忠商事 | D57: 45627 | E57: 100 | F57: 6 | G57: 479 | H57: 1 | I57: 100
A58: =row()-1 -> 57 | C58: 武田薬品工業 | D58: 45627 | E58: 98 | F58: 26 | G58: 2031 | H58: 3 | I58: 294
A59: =row()-1 -> 58 | C59: 双日 | D59: 45627 | E59: 75 | F59: 17 | G59: 1017 | H59: 7 | I59: 525
A60: =row()-1 -> 59 | C60: KDDI | D60: 45627 | E60: 70 | F60: 8 | G60: 447 | H60: 5 | I60: 350
A61: =row()-1 -> 60 | C61: 三井住友フィナンシャルグループ | D61: 45627 | E61: 180 | F61: 10 | G61: 1435 | H61: 1 | I61: 180
... A73: =row()-1 -> 72 | C73: GMOフィナンシャルホールディングス | D73: 45627 | E73: 8.27 | F73: 0 | G73: 0 | H73: 20 | I73: 166
A74: =row()-1 -> 73 | C74: iシェアーズ コア 米国高配当株 ETF | D74: 45627 | E74: 1.01USD | F74: 51 | G74: 6442 | H74: 8 | I74: 1268
A75: =row()-1 -> 74 | C75: バンガード 米国高配当株式ETF | D75: 45627 | E75: 0.86USD | F75: 0 | G75: 0 | H75: 9 | I75: 1223
A76: =row()-1 -> 75 | C76: SPDRポートフォリオS&P 500高配当株式ETF | D76: 45627 | E76: 0.49USD | F76: 191 | G76: 11720 | H76: 8 | I76: 616
A77: =row()-1 -> 76 | C77: あおぞら銀行 | D77: 45717 | E77: 19 | F77: 0 | G77: 0 | H77: 6 | I77: 114
A78: =row()-1 -> 77 | C78: iシェアーズ コア 米国高配当株 ETF | D78: 45717 | E78: 0.71USD | F78: 51 | G78: 4311 | H78: 13 | I78: 1379
A79: =row()-1 -> 78 | C79: GMOフィナンシャルホールディングス | D79: 45717 | E79: 5.24 | F79: 0 | G79: 0 | H79: 20 | I79: 105
A80: =row()-1 -> 79 | C80: 花王 | D80: 45717 | E80: 76 | F80: 0 | G80: 0 | H80: 4 | I80: 304
A81: =row()-1 -> 80 | C81: バンガード 米国高配当株式ETF | D81: 45717 | E81: 0.76USD | F81: 0 | G81: 0 | H81: 12 | I81: 1378
A82: =row()-1 -> 81 | C82: SPDRポートフォリオS&P 500高配当株式ETF | D82: 45717 | E82: 0.37USD | F82: 191 | G82: 8562 | H82: 8 | I82: 450
A83: =row()-1 -> 82 | C83: ヒューリック | D83: 45717 | E83: 28 | F83: 0 | G83: 0 | H83: 10 | I83: 280
A84: =row()-1 -> 83 | C84: 日本たばこ産業 | D84: 45717 | E84: 97 | F84: 0 | G84: 0 | H84: 5 | I84: 485
A85: =row()-1 -> 84 | C85: ジェイエイシーリクルートメント | D85: 45717 | E85: 26 | F85: 64 | G85: 1327 | H85: 10 | I85: 260
A86: =row()-1 -> 85 | C86: キヤノン | D86: 45717 | E86: 80 | F86: 2 | G86: 128 | H86: 3 | I86: 240
A87: =row()-1 -> 86 | C87: キリンホールディングス | D87: 45717 | E87: 35.5 | F87: 9 | G87: 256 | H87: 2 | I87: 72
A88: =row()-1 -> 87 | C88: 住友林業 | D88: 45717 | E88: 80 | F88: 16 | G88: 1020 | H88: 6 | I88: 480
A89: =row()-1 -> 88 | C89: INPEX | D89: 45717 | E89: 43 | F89: 0 | G89: 0 | H89: 13 | I89: 559
A90: =row()-1 -> 89 | C90: 積水ハウス | D90: 45748 | E90: 71 | F90: 15 | G90: 849 | H90: 4 | I90: 284
A91: =row()-1 -> 90 | C91: 丸紅 | D91: 45809 | E91: 50 | F91: 9 | G91: 360 | H91: 7 | I91: 350
A92: =row()-1 -> 91 | C92: 双日 | D92: 45809 | E92: 75 | F92: 17 | G92: 1017 | H92: 10 | I92: 750
A93: =row()-1 -> 92 | C93: オリックス | D93: 45809 | E93: 57.84 | F93: 14 | G93: 646 | H93: 2 | I93: 117
A94: =row()-1 -> 93 | C94: 三菱HCキャピタル | D94: 45809 | E94: 20 | F94: 10 | G94: 160 | H94: 6 | I94: 120
... A103: =row()-1 -> 102 | C103: 小松製作所 | D103: 45809 | E103: 107 | F103: 0 | G103: 0 | H103: 2 | I103: 214
A104: =row()-1 -> 103 | C104: iシェアーズ コア 米国高配当株 ETF | D104: 45809 | E104: 0.82USD | F104: 51 | G104: 4821 | H104: 16 | I104: 1898
A105: =row()-1 -> 104 | C105: 三菱商事 | D105: 45809 | E105: 50 | F105: 15 | G105: 599 | H105: 6 | I105: 300
A106: =row()-1 -> 105 | C106: 住友商事 | D106: 45809 | E106: 65 | F106: 9 | G106: 467 | H106: 5 | I106: 325
A107: =row()-1 -> 106 | C107: 伊藤忠商事 | D107: 45809 | E107: 100 | F107: 6 | G107: 479 | H107: 3 | I107: 300
A108: =row()-1 -> 107 | C108: 東京海上ホールディングス | D108: 45809 | E108: 91 | F108: 26 | G108: 1886 | H108: 5 | I108: 455
A109: =row()-1 -> 108 | C109: SOMPOホールディングス | D109: 45809 | E109: 76 | F109: 33 | G109: 1999 | H109: 5 | I109: 380
A110: =row()-1 -> 109 | C110: バンガード 米国高配当株式ETF | D110: 45809 | E110: 0.77USD | F110: 0 | G110: 0 | H110: 17 | I110: 1908
A111: =row()-1 -> 110 | C111: あおぞら銀行 | D111: 45809 | E111: 22 | F111: 0 | G111: 0 | H111: 7 | I111: 154
A112: =row()-1 -> 111 | C112: SPDRポートフォリオS&P 500高配当株式ETF | D112: 45809 | E112: 0.45USD | F112: 191 | G112: 9858 | H112: 9 | I112: 583
A113: =row()-1 -> 112 | C113: 武田薬品工業 | D113: 45809 | E113: 98 | F113: 26 | G113: 2031 | H113: 5 | I113: 490
A114: =row()-1 -> 113 | C114: 電源開発 | D114: 45809 | E114: 50 | F114: 13 | G114: 519 | H114: 11 | I114: 550
A115: =row()-1 -> 114 | C115: ENEOSホールディングス | D115: 45809 | E115: 13 | F115: 0 | G115: 0 | H115: 4 | I115: 52
A116: =row()-1 -> 115 | C116: 三菱UFJフィナンシャル・グループ | D116: 45809 | E116: 39 | F116: 22 | G116: 685 | H116: 7 | I116: 273
A117: =row()-1 -> 116 | C117: 大和ハウス工業 | D117: 45809 | E117: 80 | F117: 8 | G117: 510 | H117: 5 | I117: 400
A118: =row()-1 -> 117 | C118: 長谷工コーポレーション | D118: 45809 | E118: 45 | F118: 8 | G118: 287 | H118: 6 | I118: 270
A119: =row()-1 -> 118 | C119: 三井住友フィナンシャルグループ | D119: 45839 | E119: 62 | F119: 30 | G119: 1483 | H119: 4 | I119: 248
A120: =row()-1 -> 119 | C120: キヤノン | D120: 45870 | E120: 80 | F120: 2 | G120: 128 | H120: 5 | I120: 400
A121: =row()-1 -> 120 | C121: ブリヂストン | D121: 45901 | E121: 115 | F121: 0 | G121: 0 | H121: 4 | I121: 460
A122: =row()-1 -> 121 | C122: 花王 | D122: 45901 | E122: 77 | F122: 0 | G122: 0 | H122: 5 | I122: 385
...

Sheet 新NISA戦略
A1: 年 | B1: 月 | C1: 予定投資額 （積立投資枠） | D1: 予定投資額 （成長投資枠） | E1: 予定投資額合計 | F1: 新NISA投資枠残額 | G1: 内訳 | I1: 月額 | J1: 年額
A2: 2024 | B2: 1 | C2: =I2 -> 53000 | D2: =I3 -> 80000 | E2: =C2+D2 -> 133000 | F2: =18000000-E2 -> 17867000 | G2: 新NISA | H2: 積立投資枠 | I2: 53000 | J2: =I2*12 -> 636000
B3: 2 | C3: =$I$2+C2 -> 106000 | D3: =$I$3+D2 -> 160000 | E3: =C3+D3 -> 266000 | F3: =18000000-E3 -> 17734000 | H3: 成長投資枠 | I3: 80000 | J3: =I3*12 -> 960000
B4: 3 | C4: =$I$2+C3 -> 159000 | D4: =$I$3+D3 -> 240000 | E4: =C4+D4 -> 399000 | F4: =18000000-E4 -> 17601000 | G4: 合計 | I4: =SUM(I2:I3) -> 133000 | J4: =I4*12 -> 1596000
B5: 4 | C5: =$I$2+C4 -> 212000 | D5: =$I$3+D4 -> 320000 | E5: =C5+D5 -> 532000 | F5: =18000000-E5 -> 17468000
B6: 5 | C6: =$I$2+C5 -> 265000 | D6: =$I$3+D5 -> 400000 | E6: =C6+D6 -> 665000 | F6: =18000000-E6 -> 17335000
B7: 6 | C7: =$I$2+C6 -> 318000 | D7: =$I$3+D6 -> 480000 | E7: =C7+D7 -> 798000 | F7: =18000000-E7 -> 17202000
B8: 7 | C8: =$I$2+C7 -> 371000 | D8: =$I$3+D7 -> 560000 | E8: =C8+D8 -> 931000 | F8: =18000000-E8 -> 17069000
B9: 8 | C9: =$I$2+C8 -> 424000 | D9: =$I$3+D8 -> 640000 | E9: =C9+D9 -> 1064000 | F9: =18000000-E9 -> 16936000
B10: 9 | C10: =$I$2+C9 -> 477000 | D10: =$I$3+D9 -> 720000 | E10: =C10+D10 -> 1197000 | F10: =18000000-E10 -> 16803000
B11: 10 | C11: =$I$2+C10 -> 530000 | D11: =$I$3+D10 -> 800000 | E11: =C11+D11 -> 1330000 | F11: =18000000-E11 -> 16670000
B12: 11 | C12: =$I$2+C11 -> 583000 | D12: =$I$3+D11 -> 880000 | E12: =C12+D12 -> 1463000 | F12: =18000000-E12 -> 16537000
B13: 12 | C13: =$I$2+C12 -> 636000 | D13: =$I$3+D12 -> 960000 | E13: =C13+D13 -> 1596000 | F13: =18000000-E13 -> 16404000
A14: 2025 | B14: 1 | C14: =$I$2+C13 -> 689000 | D14: =$I$3+D13 -> 1040000 | E14: =C14+D14 -> 1729000 | F14: =18000000-E14 -> 16271000
B15: 2 | C15: =$I$2+C14 -> 742000 | D15: =$I$3+D14 -> 1120000 | E15: =C15+D15 -> 1862000 | F15: =18000000-E15 -> 16138000
B16: 3 | C16: =$I$2+C15 -> 795000 | D16: =$I$3+D15 -> 1200000 | E16: =C16+D16 -> 1995000 | F16: =18000000-E16 -> 16005000
B17: 4 | C17: =$I$2+C16 -> 848000 | D17: =$I$3+D16 -> 1280000 | E17: =C17+D17 -> 2128000 | F17: =18000000-E17 -> 15872000
B18: 5 | C18: =$I$2+C17 -> 901000 | D18: =$I$3+D17 -> 1360000 | E18: =C18+D18 -> 2261000 | F18: =18000000-E18 -> 15739000
B19: 6 | C19: =$I$2+C18 -> 954000 | D19: =$I$3+D18 -> 1440000 | E19: =C19+D19 -> 2394000 | F19: =18000000-E19 -> 15606000
B20: 7 | C20: =$I$2+C19 -> 1007000 | D20: =$I$3+D19 -> 1520000 | E20: =C20+D20 -> 2527000 | F20: =18000000-E20 -> 15473000
B21: 8 | C21: =$I$2+C20 -> 1060000 | D21: =$I$3+D20 -> 1600000 | E21: =C21+D21 -> 2660000 | F21: =18000000-E21 -> 15340000
B22: 9 | C22: =$I$2+C21 -> 1113000 | D22: =$I$3+D21 -> 1680000 | E22: =C22+D22 -> 2793000 | F22: =18000000-E22 -> 15207000
B23: 10 | C23: =$I$2+C22 -> 1166000 | D23: =$I$3+D22 -> 1760000 | E23: =C23+D23 -> 2926000 | F23: =18000000-E23 -> 15074000
B24: 11 | C24: =$I$2+C23 -> 1219000 | D24: =$I$3+D23 -> 1840000 | E24: =C24+D24 -> 3059000 | F24: =18000000-E24 -> 14941000
B25: 12 | C25: =$I$2+C24 -> 1272000 | D25: =$I$3+D24 -> 1920000 | E25: =C25+D25 -> 3192000 | F25: =18000000-E25 -> 14808000
A26: 2026 | B26: 1 | C26: =$I$2+C25 -> 1325000 | D26: =$I$3+D25 -> 2000000 | E26: =C26+D26 -> 3325000 | F26: =18000000-E26 -> 14675000
B27: 2 | C27: =$I$2+C26 -> 1378000 | D27: =$I$3+D26 -> 2080000 | E27: =C27+D27 -> 3458000 | F27: =18000000-E27 -> 14542000
B28: 3 | C28: =$I$2+C27 -> 1431000 | D28: =$I$3+D27 -> 2160000 | E28: =C28+D28 -> 3591000 | F28: =18000000-E28 -> 14409000
B29: 4 | C29: =$I$2+C28 -> 1484000 | D29: =$I$3+D28 -> 2240000 | E29: =C29+D29 -> 3724000 | F29: =18000000-E29 -> 14276000
B30: 5 | C30: =$I$2+C29 -> 1537000 | D30: =$I$3+D29 -> 2320000 | E30: =C30+D30 -> 3857000 | F30: =18000000-E30 -> 14143000
B31: 6 | C31: =$I$2+C30 -> 1590000 | D31: =$I$3+D30 -> 2400000 | E31: =C31+D31 -> 3990000 | F31: =18000000-E31 -> 14010000
B32: 7 | C32: =$I$2+C31 -> 1643000 | D32: =$I$3+D31 -> 2480000 | E32: =C32+D32 -> 4123000 | F32: =18000000-E32 -> 13877000
B33: 8 | C33: =$I$2+C32 -> 1696000 | D33: =$I$3+D32 -> 2560000 | E33: =C33+D33 -> 4256000 | F33: =18000000-E33 -> 13744000
B34: 9 | C34: =$I$2+C33 -> 1749000 | D34: =$I$3+D33 -> 2640000 | E34: =C34+D34 -> 4389000 | F34: =18000000-E34 -> 13611000
B35: 10 | C35: =$I$2+C34 -> 1802000 | D35: =$I$3+D34 -> 2720000 | E35: =C35+D35 -> 4522000 | F35: =18000000-E35 -> 13478000
B36: 11 | C36: =$I$2+C35 -> 1855000 | D36: =$I$3+D35 -> 2800000 | E36: =C36+D36 -> 4655000 | F36: =18000000-E36 -> 13345000
B37: 12 | C37: =$I$2+C36 -> 1908000 | D37: =$I$3+D36 -> 2880000 | E37: =C37+D37 -> 4788000 | F37: =18000000-E37 -> 13212000
A38: 2027 | B38: 1 | C38: =$I$2+C37 -> 1961000 | D38: =$I$3+D37 -> 2960000 | E38: =C38+D38 -> 4921000 | F38: =18000000-E38 -> 13079000
B39: 2 | C39: =$I$2+C38 -> 2014000 | D39: =$I$3+D38 -> 3040000 | E39: =C39+D39 -> 5054000 | F39: =18000000-E39 -> 12946000
B40: 3 | C40: =$I$2+C39 -> 2067000 | D40: =$I$3+D39 -> 3120000 | E40: =C40+D40 -> 5187000 | F40: =18000000-E40 -> 12813000
B41: 4 | C41: =$I$2+C40 -> 2120000 | D41: =$I$3+D40 -> 3200000 | E41: =C41+D41 -> 5320000 | F41: =18000000-E41 -> 12680000
B42: 5 | C42: =$I$2+C41 -> 2173000 | D42: =$I$3+D41 -> 3280000 | E42: =C42+D42 -> 5453000 | F42: =18000000-E42 -> 12547000
B43: 6 | C43: =$I$2+C42 -> 2226000 | D43: =$I$3+D42 -> 3360000 | E43: =C43+D43 -> 5586000 | F43: =18000000-E43 -> 12414000
B44: 7 | C44: =$I$2+C43 -> 2279000 | D44: =$I$3+D43 -> 3440000 | E44: =C44+D44 -> 5719000 | F44: =18000000-E44 -> 12281000
B45: 8 | C45: =$I$2+C44 -> 2332000 | D45: =$I$3+D44 -> 3520000 | E45: =C45+D45 -> 5852000 | F45: =18000000-E45 -> 12148000
B46: 9 | C46: =$I$2+C45 -> 2385000 | D46: =$I$3+D45 -> 3600000 | E46: =C46+D46 -> 5985000 | F46: =18000000-E46 -> 12015000
B47: 10 | C47: =$I$2+C46 -> 2438000 | D47: =$I$3+D46 -> 3680000 | E47: =C47+D47 -> 6118000 | F47: =18000000-E47 -> 11882000
B48: 11 | C48: =$I$2+C47 -> 2491000 | D48: =$I$3+D47 -> 3760000 | E48: =C48+D48 -> 6251000 | F48: =18000000-E48 -> 11749000
B49: 12 | C49: =$I$2+C48 -> 2544000 | D49: =$I$3+D48 -> 3840000 | E49: =C49+D49 -> 6384000 | F49: =18000000-E49 -> 11616000
A50: 2028 | B50: 1 | C50: =$I$2+C49 -> 2597000 | D50: =$I$3+D49 -> 3920000 | E50: =C50+D50 -> 6517000 | F50: =18000000-E50 -> 11483000
B51: 2 | C51: =$I$2+C50 -> 2650000 | D51: =$I$3+D50 -> 4000000 | E51: =C51+D51 -> 6650000 | F51: =18000000-E51 -> 11350000
B52: 3 | C52: =$I$2+C51 -> 2703000 | D52: =$I$3+D51 -> 4080000 | E52: =C52+D52 -> 6783000 | F52: =18000000-E52 -> 11217000
B53: 4 | C53: =$I$2+C52 -> 2756000 | D53: =$I$3+D52 -> 4160000 | E53: =C53+D53 -> 6916000 | F53: =18000000-E53 -> 11084000
B54: 5 | C54: =$I$2+C53 -> 2809000 | D54: =$I$3+D53 -> 4240000 | E54: =C54+D54 -> 7049000 | F54: =18000000-E54 -> 10951000
B55: 6 | C55: =$I$2+C54 -> 2862000 | D55: =$I$3+D54 -> 4320000 | E55: =C55+D55 -> 7182000 | F55: =18000000-E55 -> 10818000
B56: 7 | C56: =$I$2+C55 -> 2915000 | D56: =$I$3+D55 -> 4400000 | E56: =C56+D56 -> 7315000 | F56: =18000000-E56 -> 10685000
B57: 8 | C57: =$I$2+C56 -> 2968000 | D57: =$I$3+D56 -> 4480000 | E57: =C57+D57 -> 7448000 | F57: =18000000-E57 -> 10552000
B58: 9 | C58: =$I$2+C57 -> 3021000 | D58: =$I$3+D57 -> 4560000 | E58: =C58+D58 -> 7581000 | F58: =18000000-E58 -> 10419000
B59: 10 | C59: =$I$2+C58 -> 3074000 | D59: =$I$3+D58 -> 4640000 | E59: =C59+D59 -> 7714000 | F59: =18000000-E59 -> 10286000
B60: 11 | C60: =$I$2+C59 -> 3127000 | D60: =$I$3+D59 -> 4720000 | E60: =C60+D60 -> 7847000 | F60: =18000000-E60 -> 10153000
B61: 12 | C61: =$I$2+C60 -> 3180000 | D61: =$I$3+D60 -> 4800000 | E61: =C61+D61 -> 7980000 | F61: =18000000-E61 -> 10020000
A62: 2029 | B62: 1 | C62: =$I$2+C61 -> 3233000 | D62: =$I$3+D61 -> 4880000 | E62: =C62+D62 -> 8113000 | F62: =18000000-E62 -> 9887000
B63: 2 | C63: =$I$2+C62 -> 3286000 | D63: =$I$3+D62 -> 4960000 | E63: =C63+D63 -> 8246000 | F63: =18000000-E63 -> 9754000
B64: 3 | C64: =$I$2+C63 -> 3339000 | D64: =$I$3+D63 -> 5040000 | E64: =C64+D64 -> 8379000 | F64: =18000000-E64 -> 9621000
B65: 4 | C65: =$I$2+C64 -> 3392000 | D65: =$I$3+D64 -> 5120000 | E65: =C65+D65 -> 8512000 | F65: =18000000-E65 -> 9488000
B66: 5 | C66: =$I$2+C65 -> 3445000 | D66: =$I$3+D65 -> 5200000 | E66: =C66+D66 -> 8645000 | F66: =18000000-E66 -> 9355000
B67: 6 | C67: =$I$2+C66 -> 3498000 | D67: =$I$3+D66 -> 5280000 | E67: =C67+D67 -> 8778000 | F67: =18000000-E67 -> 9222000
B68: 7 | C68: =$I$2+C67 -> 3551000 | D68: =$I$3+D67 -> 5360000 | E68: =C68+D68 -> 8911000 | F68: =18000000-E68 -> 9089000
B69: 8 | C69: =$I$2+C68 -> 3604000 | D69: =$I$3+D68 -> 5440000 | E69: =C69+D69 -> 9044000 | F69: =18000000-E69 -> 8956000
B70: 9 | C70: =$I$2+C69 -> 3657000 | D70: =$I$3+D69 -> 5520000 | E70: =C70+D70 -> 9177000 | F70: =18000000-E70 -> 8823000
B71: 10 | C71: =$I$2+C70 -> 3710000 | D71: =$I$3+D70 -> 5600000 | E71: =C71+D71 -> 9310000 | F71: =18000000-E71 -> 8690000
B72: 11 | C72: =$I$2+C71 -> 3763000 | D72: =$I$3+D71 -> 5680000 | E72: =C72+D72 -> 9443000 | F72: =18000000-E72 -> 8557000
B73: 12 | C73: =$I$2+C72 -> 3816000 | D73: =$I$3+D72 -> 5760000 | E73: =C73+D73 -> 9576000 | F73: =18000000-E73 -> 8424000
A74: 2030 | B74: 1 | C74: =$I$2+C73 -> 3869000 | D74: =$I$3+D73 -> 5840000 | E74: =C74+D74 -> 9709000 | F74: =18000000-E74 -> 8291000
B75: 2 | C75: =$I$2+C74 -> 3922000 | D75: =$I$3+D74 -> 5920000 | E75: =C75+D75 -> 9842000 | F75: =18000000-E75 -> 8158000
B76: 3 | C76: =$I$2+C75 -> 3975000 | D76: =$I$3+D75 -> 6000000 | E76: =C76+D76 -> 9975000 | F76: =18000000-E76 -> 8025000
B77: 4 | C77: =$I$2+C76 -> 4028000 | D77: =$I$3+D76 -> 6080000 | E77: =C77+D77 -> 10108000 | F77: =18000000-E77 -> 7892000
B78: 5 | C78: =$I$2+C77 -> 4081000 | D78: =$I$3+D77 -> 6160000 | E78: =C78+D78 -> 10241000 | F78: =18000000-E78 -> 7759000
B79: 6 | C79: =$I$2+C78 -> 4134000 | D79: =$I$3+D78 -> 6240000 | E79: =C79+D79 -> 10374000 | F79: =18000000-E79 -> 7626000
B80: 7 | C80: =$I$2+C79 -> 4187000 | D80: =$I$3+D79 -> 6320000 | E80: =C80+D80 -> 10507000 | F80: =18000000-E80 -> 7493000
B81: 8 | C81: =$I$2+C80 -> 4240000 | D81: =$I$3+D80 -> 6400000 | E81: =C81+D81 -> 10640000 | F81: =18000000-E81 -> 7360000
B82: 9 | C82: =$I$2+C81 -> 4293000 | D82: =$I$3+D81 -> 6480000 | E82: =C82+D82 -> 10773000 | F82: =18000000-E82 -> 7227000
B83: 10 | C83: =$I$2+C82 -> 4346000 | D83: =$I$3+D82 -> 6560000 | E83: =C83+D83 -> 10906000 | F83: =18000000-E83 -> 7094000
B84: 11 | C84: =$I$2+C83 -> 4399000 | D84: =$I$3+D83 -> 6640000 | E84: =C84+D84 -> 11039000 | F84: =18000000-E84 -> 6961000
B85: 12 | C85: =$I$2+C84 -> 4452000 | D85: =$I$3+D84 -> 6720000 | E85: =C85+D85 -> 11172000 | F85: =18000000-E85 -> 6828000
A86: 2031 | B86: 1 | C86: =$I$2+C85 -> 4505000 | D86: =$I$3+D85 -> 6800000 | E86: =C86+D86 -> 11305000 | F86: =18000000-E86 -> 6695000
B87: 2 | C87: =$I$2+C86 -> 4558000 | D87: =$I$3+D86 -> 6880000 | E87: =C87+D87 -> 11438000 | F87: =18000000-E87 -> 6562000
B88: 3 | C88: =$I$2+C87 -> 4611000 | D88: =$I$3+D87 -> 6960000 | E88: =C88+D88 -> 11571000 | F88: =18000000-E88 -> 6429000
B89: 4 | C89: =$I$2+C88 -> 4664000 | D89: =$I$3+D88 -> 7040000 | E89: =C89+D89 -> 11704000 | F89: =18000000-E89 -> 6296000
B90: 5 | C90: =$I$2+C89 -> 4717000 | D90: =$I$3+D89 -> 7120000 | E90: =C90+D90 -> 11837000 | F90: =18000000-E90 -> 6163000
B91: 6 | C91: =$I$2+C90 -> 4770000 | D91: =$I$3+D90 -> 7200000 | E91: =C91+D91 -> 11970000 | F91: =18000000-E91 -> 6030000
B92: 7 | C92: =$I$2+C91 -> 4823000 | D92: =$I$3+D91 -> 7280000 | E92: =C92+D92 -> 12103000 | F92: =18000000-E92 -> 5897000
B93: 8 | C93: =$I$2+C92 -> 4876000 | D93: =$I$3+D92 -> 7360000 | E93: =C93+D93 -> 12236000 | F93: =18000000-E93 -> 5764000
B94: 9 | C94: =$I$2+C93 -> 4929000 | D94: =$I$3+D93 -> 7440000 | E94: =C94+D94 -> 12369000 | F94: =18000000-E94 -> 5631000
B95: 10 | C95: =$I$2+C94 -> 4982000 | D95: =$I$3+D94 -> 7520000 | E95: =C95+D95 -> 12502000 | F95: =18000000-E95 -> 5498000
B96: 11 | C96: =$I$2+C95 -> 5035000 | D96: =$I$3+D95 -> 7600000 | E96: =C96+D96 -> 12635000 | F96: =18000000-E96 -> 5365000
B97: 12 | C97: =$I$2+C96 -> 5088000 | D97: =$I$3+D96 -> 7680000 | E97: =C97+D97 -> 12768000 | F97: =18000000-E97 -> 5232000
A98: 2032 | B98: 1 | C98: =$I$2+C97 -> 5141000 | D98: =$I$3+D97 -> 7760000 | E98: =C98+D98 -> 12901000 | F98: =18000000-E98 -> 5099000
B99: 2 | C99: =$I$2+C98 -> 5194000 | D99: =$I$3+D98 -> 7840000 | E99: =C99+D99 -> 13034000 | F99: =18000000-E99 -> 4966000
B100: 3 | C100: =$I$2+C99 -> 5247000 | D100: =$I$3+D99 -> 7920000 | E100: =C100+D100 -> 13167000 | F100: =18000000-E100 -> 4833000
...
